Workbook
Name FP.DataSourceName: '[1]Front Page'!$H$15
Name FP.LastPrice: '[1]Front Page'!$H$20
Name FP.LastPriceDate: '[1]Front Page'!$F$20
Name FP.RealTimeToggle: '[1]Front Page'!$H$18
Name GD_Guidance_High: [2]Guidance!$J:$J
Name GD_Guidance_Low: [2]Guidance!$I:$I
Name GD_Guidance_Mid: [2]Guidance!$K:$K
Name GD_Item_FiscalPeriod: [2]Guidance!$F:$F
Name GD_Item_Name: [2]Guidance!$E:$E
Name GD_Update_Date: [2]Guidance!$S:$S
Name HP.MRFX: WSM!$B$1290
Name HP.ReportCurrency: WSM!$B$1289
Name HP.Ticker: WSM!$A$2
Name HP.TradeCurrency: WSM!$B$1287
Name HP.TradeCurrency.HardCoded: WSM!$B$1288
Name MO.ApplyTradeCurrencyScaling: WSM!$B$1286
Name MO.DataSourceIndex: WSM!$B$1297
Name MO.DataSourceName: WSM!$A$4
Name MO.LastPrice: WSM!$B$3
Name MO.LastPriceFormula: WSM!$B$1285
Name MO.LastPriceHardcoded: WSM!$B$1282
Name MO.MRFP: WSM!$B$1293
Name MO.MRFPColumnNumber: WSM!$B$1292
Name MO.MRFX.Hardcoded: WSM!$B$1291
Name MO.RealTime: WSM!$B$4
Name MO.RealTimeStockPriceToggle: WSM!$B$1284
Name MO.ReportCurrency: WSM!$B$1289
Name MO.ReportFX: WSM!$A$5
Name MO.Ticker.Bloomberg: WSM!$A$1189
Name MO.Ticker.CapIQ: WSM!$A$1190
Name MO.Ticker.FactSet: WSM!$A$1191
Name MO.Ticker.Thomson: WSM!$A$1192
Name MO.ValuationToggle: WSM!$B$924
Name MO_CFS_Buyback: WSM!$1045:$1045
Name MO_CFS_CFF: WSM!$1054:$1054
Name MO_CFS_CFI: WSM!$1039:$1039
Name MO_CFS_CFO: WSM!$1030:$1030
Name MO_CFS_CFO_BeforeWC: WSM!$1019:$1019
Name MO_CFSum_Acquisition: WSM!$881:$881
Name MO_CFSum_Capex: WSM!$879:$879
Name MO_CFSum_Divestiture: WSM!$882:$882
Name MO_CFSum_Dividend: WSM!$883:$883
Name MO_Common_ColumnHeader: WSM!$5:$5
Name MO_Common_FPDays: WSM!$3:$3
Name MO_Common_QEndDate: WSM!$4:$4
Name MO_IS_EBIT: WSM!$644:$644
Name MO_IS_FirstRow: WSM!$640:$640
Name MO_OS_EBIT: WSM!$352:$352
Name MO_OS_EBIT_Adj: WSM!$366:$366
Name MO_OS_EBT: WSM!$379:$379
Name MO_OS_EBT_Adj: WSM!$381:$381
Name MO_RIS_EBIT: WSM!$762:$762
Name MO_RIS_EBIT_Adj: WSM!$763:$763
Name MO_RIS_EBITDA_Adj: WSM!$769:$769
Name MO_RIS_EBT: WSM!$778:$778
Name MO_RIS_EBT_Adj: WSM!$779:$779
Name MO_RIS_EPS_WAD_Adj: WSM!$811:$811
Name MO_RIS_NI_NONGAAP_Diluted: WSM!$802:$802
Name MO_RIS_REV: WSM!$749:$749
Name MO_SCA_ShareCount_EoP_Diluted: WSM!$833:$833

Sheet P&L
B6: CONFIDENTIAL
B7: mock analysis
B9: Green = to fill out
B10: 1. Compute each fee as a % of STOWED product revenue.
B11: 2. Compute total fees and revenue per resort.
B12: 3. Compute FY1, 2, and 3 revenue using table in rows 29-32.
B13: 4. Compute COGS using a 60% margin.
B14: 5. Compute gross profit $ and %.
B15: 6. Add SG&A categories + estimates.
B16: 7. Compute net operating profit $ and %.
B18: Revenue Streams | C18: as % of STOWED product budget | D18: resort a | E18: resort b | F18: resort c | G18: resort d | H18: resort e | I18: resort f | J18: resort g | K18: resort h | L18: resort i | M18: TOTAL
B19: STOWED product | D19: 1000000 | E19: 2000000 | F19: 1000000 | G19: 3000000 | H19: 2000000 | I19: 3000000 | J19: 1000000 | K19: 2000000 | L19: 2000000 | M19: =SUM(D19:L19) -> 17000000
B20: Fees
B21: Design | C21: 0.03 | D21: =D$19*$C21 -> 30000 | E21: =E$19*$C21 -> 60000 | F21: =F$19*$C21 -> 30000 | G21: =G$19*$C21 -> 90000 | H21: =H$19*$C21 -> 60000 | I21: =I$19*$C21 -> 90000 | J21: =J$19*$C21 -> 30000 | K21: =K$19*$C21 -> 60000 | L21: =L$19*$C21 -> 60000 | M21: =SUM(D21:L21) -> 510000
B22: Product Development | C22: 0.06 | D22: =D$19*$C22 -> 60000 | E22: =E$19*$C22 -> 120000 | F22: =F$19*$C22 -> 60000 | G22: =G$19*$C22 -> 180000 | H22: =H$19*$C22 -> 120000 | I22: =I$19*$C22 -> 180000 | J22: =J$19*$C22 -> 60000 | K22: =K$19*$C22 -> 120000 | L22: =L$19*$C22 -> 120000 | M22: =SUM(D22:L22) -> 1020000
B23: Consulting | C23: 0.07 | D23: =D$19*$C23 -> 70000 | E23: =E$19*$C23 -> 140000 | F23: =F$19*$C23 -> 70000 | G23: =G$19*$C23 -> 210000 | H23: =H$19*$C23 -> 140000 | I23: =I$19*$C23 -> 210000 | J23: =J$19*$C23 -> 70000 | K23: =K$19*$C23 -> 140000 | L23: =L$19*$C23 -> 140000 | M23: =SUM(D23:L23) -> 1190000
B24: Logistics | C24: 0.02 | D24: =D$19*$C24 -> 20000 | E24: =E$19*$C24 -> 40000 | F24: =F$19*$C24 -> 20000 | G24: =G$19*$C24 -> 60000 | H24: =H$19*$C24 -> 40000 | I24: =I$19*$C24 -> 60000 | J24: =J$19*$C24 -> 20000 | K24: =K$19*$C24 -> 40000 | L24: =L$19*$C24 -> 40000 | M24: =SUM(D24:L24) -> 340000
B25: Total Fees | D25: =SUM(D21:D24) -> 180000 | E25: =SUM(E21:E24) -> 360000 | F25: =SUM(F21:F24) -> 180000 | G25: =SUM(G21:G24) -> 540000 | H25: =SUM(H21:H24) -> 360000 | I25: =SUM(I21:I24) -> 540000 | J25: =SUM(J21:J24) -> 180000 | K25: =SUM(K21:K24) -> 360000 | ... M25: =SUM(M21:M24) -> 3060000
B26: Total Revenue | D26: =D19+D25 -> 1180000 | E26: =E19+E25 -> 2360000 | F26: =F19+F25 -> 1180000 | G26: =G19+G25 -> 3540000 | H26: =H19+H25 -> 2360000 | I26: =I19+I25 -> 3540000 | J26: =J19+J25 -> 1180000 | K26: =K19+K25 -> 2360000 | ... M26: =M19+M25 -> 20060000
B29: % of resort revenue per year
B30: Yr1 | D30: 1 | E30: 0.75 | F30: 0.6 | G30: 0.8 | H30: 0 | I30: 0 | J30: 0.5 | K30: 0 | L30: 0
B31: Yr2 | D31: 0 | E31: 0 | F31: 0.3 | G31: 0.1 | H31: 0.3 | I31: 0 | J31: 0.25 | K31: 0.15 | L31: 1
B32: Yr3 | D32: =1-D31-D30 -> 0 | E32: =1-E31-E30 -> 0.25 | F32: =1-F31-F30 -> 0.1 | G32: 0.1 | H32: 0.7 | I32: 1 | J32: 0.25 | K32: 0.85 | L32: =1-L31-L30 -> 0
B37: P&L
B38: REVENUE | D38: FY1 | F38: FY2 | H38: FY3 | J38: Total
B39: STOWED product | D39: =SUMPRODUCT($D$19:$L$19,D30:L30) -> 6000000 | F39: =SUMPRODUCT($D$19:$L$19,D31:L31) -> 3750000 | H39: =SUMPRODUCT($D$19:$L$19,D32:L32) -> 7250000 | J39: =SUM(H39,F39,D39) -> 17000000
B40: Fees | D40: =SUMPRODUCT($D$25:$L$25,D30:L30) -> 1080000 | F40: =SUMPRODUCT($D$25:$L$25,F30:N30) -> 576000 | H40: =SUMPRODUCT($D$25:$L$25,H30:P30) -> 90000 | J40: =SUM(H40,F40,D40) -> 1746000
B41: Revenue | D41: =SUMPRODUCT($D$26:$L$26,D30:L30) -> 7080000 | F41: =SUMPRODUCT($D$26:$L$26,D31:L31) -> 4425000 | H41: =SUMPRODUCT($D$26:$L$26,D32:L32) -> 8555000 | J41: =SUM(H41,F41,D41) -> 20060000
B42: STOWED COGS (use 60% margin) | C42: 0.6 | D42: =-D41*$C$42 -> -4248000 | F42: =-F41*$C$42 -> -2655000 | H42: =-H41*$C$42 -> -5133000 | J42: =SUM(H42,F42,D42) -> -12036000
B43: Gross profit $ | D43: =SUM(D41:D42) -> 2832000 | F43: =SUM(F41:F42) -> 1770000 | H43: =SUM(H41:H42) -> 3422000 | J43: =SUM(J41:J42) -> 8024000
B44: Gross profit % | D44: =D43/D41 -> 0.4 | F44: =F43/F41 -> 0.4 | H44: =H43/H41 -> 0.4 | J44: =J43/J41 -> 0.4
B45: SG&A
B46: Selling
B47: General | D47: -200000 | F47: -200000 | H47: -200000 | J47: 0
B48: Administrative | D48: ='Team Structure'!M110*-1 -> -1087647.1 | F48: ='Team Structure'!N110*-1 -> -1070000 | H48: ='Team Structure'!O110*-1 -> -1168382.4 | J48: =SUM(D48:H48) -> -3326029.4
B49: Net Operating Profit $ | D49: =D43+SUM(D46:D48) -> 1544352.9 | F49: =F43+SUM(F46:F48) -> 500000 | H49: =H43+SUM(H46:H48) -> 2053617.6 | J49: =J43+SUM(J46:J48) -> 4697970.6
B50: Net Operating Profit % | D50: =D49/D41 -> 0.21812895 | F50: =F49/F41 -> 0.11299435 | H50: =H49/H41 -> 0.24004882 | J50: =J49/J41 -> 0.23419594
B53: General as a % of revenue | D53: =D47/D41*-1 -> 0.028248588 | F53: =F47/F41*-1 -> 0.04519774 | H53: =H47/H41*-1 -> 0.023378141
B54: Selling

Sheet Comps
C2: RH | D2: WSM | E2: Wayfair
B4: Gross Margin | C4: =RH!BI23 -> 0.45855438 | D4: =WSM!BI41 -> 0.42651147 | E4: =Wayfair!BI97 -> 0.30550696
B5: SG&A | C5: =RH!BI638 -> 0.32855418 | D5: =D4-D7 -> 0.26257681
B7: Operating margin | C7: =C4-C5 -> 0.1300002 | D7: =WSM!BI46 -> 0.16393466

Sheet Team Structure
C2: 1. Compute annual and total salaries per team (assume all W2 employees with full benefits).
C3: 2. Compute annual and total fees per team.
C4: 3. Compute ROI per team.
C5: 4. Provide a hypothesis for current allocation of team members and salaries vs. ROI.
C6: 5. Provide a suggestion for reallocation of team members and salaries vs. ROI.
C8: Employee | E8: Team | F8: Salary | G8: Assumed hours worked if completed within a year | H8: Salary per Hour | J8: Group | K8: Average Salary | L8: Total Hours to Complete Project | M8: Average Hour per year | N8: Total personel Required
C9: A | E9: Design | F9: 150000 | G9: =(40*49) -> 1960 | H9: =F9/G9 -> 76.530612 | J9: Design | K9: =AVERAGE(F9:F13) -> 110000 | L9: =SUMIF($E$9:$E$20,$J9,$G$9:$G$20) -> 9800 | M9: =L9/3 -> 3266.6667 | N9: =ROUND(M9/G9,0) -> 2
C10: B | E10: Design | F10: 125000 | G10: =(40*49) -> 1960 | H10: =F10/G10 -> 63.77551 | J10: Product Development | K10: =AVERAGE(F14:F15) -> 135000 | L10: =SUMIF($E$9:$E$20,$J10,$G$9:$G$20) -> 3920 | M10: =L10/3 -> 1306.6667 | N10: =M10/G14 -> 0.66666667
C11: C | E11: Design | F11: 110000 | G11: =(40*49) -> 1960 | H11: =F11/G11 -> 56.122449 | J11: Consulting | K11: =AVERAGE(F16:F19) -> 168750 | L11: =SUMIF($E$9:$E$20,$J11,$G$9:$G$20) -> 7840 | M11: =L11/3 -> 2613.3333 | N11: =M11/G16 -> 1.3333333
C12: D | E12: Design | F12: 90000 | G12: =(40*49) -> 1960 | H12: =F12/G12 -> 45.918367 | J12: Logistics | K12: =AVERAGE(F20) -> 125000 | L12: =SUMIF($E$9:$E$20,$J12,$G$9:$G$20) -> 1960 | M12: =L12/3 -> 653.33333 | N12: =M12/G20 -> 0.33333333
C13: E | E13: Design | F13: 75000 | G13: =(40*49) -> 1960 | H13: =F13/G13 -> 38.265306 | J13: Total | L13: =SUM(L9:L12) -> 23520 | M13: =L13/3 -> 7840 | N13: =M13/G13 -> 4
C14: F | E14: Product Development | F14: 150000 | G14: =(40*49) -> 1960 | H14: =F14/G14 -> 76.530612
C15: G | E15: Product Development | F15: 120000 | G15: =(40*49) -> 1960 | H15: =F15/G15 -> 61.22449
C16: H | E16: Consulting | F16: 200000 | G16: =(40*49) -> 1960 | H16: =F16/G16 -> 102.04082
C17: I | E17: Consulting | F17: 200000 | G17: =(40*49) -> 1960 | H17: =F17/G17 -> 102.04082
C18: J | E18: Consulting | F18: 150000 | G18: =(40*49) -> 1960 | H18: =F18/G18 -> 76.530612
C19: K | E19: Consulting | F19: 125000 | G19: =(40*49) -> 1960 | H19: =F19/G19 -> 63.77551
C20: L | E20: Logistics | F20: 125000 | G20: =(40*49) -> 1960 | H20: =F20/G20 -> 63.77551
A22: 1
F24: Annual Salary | H24: FY1 | I24: FY2 | J24: FY3 | K24: Total
C25: Design | F25: =SUMIFS($F$9:$F$20,$E$9:$E$20,$C25) -> 550000 | H25: =$F25 -> 550000 | I25: =$F25 -> 550000 | J25: =$F25 -> 550000 | K25: =SUM(H25:J25) -> 1650000
C26: Product Development | F26: =SUMIFS($F$9:$F$20,$E$9:$E$20,$C26) -> 270000 | H26: =$F26 -> 270000 | I26: =$F26 -> 270000 | J26: =$F26 -> 270000 | K26: =SUM(H26:J26) -> 810000
C27: Consulting | F27: =SUMIFS($F$9:$F$20,$E$9:$E$20,$C27) -> 675000 | H27: =$F27 -> 675000 | I27: =$F27 -> 675000 | J27: =$F27 -> 675000 | K27: =SUM(H27:J27) -> 2025000
C28: Logistics | F28: =SUMIFS($F$9:$F$20,$E$9:$E$20,$C28) -> 125000 | H28: =$F28 -> 125000 | I28: =$F28 -> 125000 | J28: =$F28 -> 125000 | K28: =SUM(H28:J28) -> 375000
C29: Total | H29: =SUM(H25:H28) -> 1620000 | I29: =SUM(I25:I28) -> 1620000 | J29: =SUM(J25:J28) -> 1620000 | K29: =SUM(H29:J29) -> 4860000
A31: 2
H33: =H39/$K$39 -> 0.35294118 | I33: =I39/$K$39 -> 0.22058824 | J33: =J39/$K$39 -> 0.42647059 | N33: Total Hours worked
C34: Fees Generated | H34: FY1 | I34: FY2 | J34: FY3 | K34: Total | L34: Avg Fee per Hour | N34: FY1 | O34: =I34 -> FY2 | P34: =J34 -> FY3 | Q34: Total
C35: Design | H35: =SUMPRODUCT('P&L'!$D21:$L21,'P&L'!$D$30:$L$30) -> 180000 | I35: =SUMPRODUCT('P&L'!$D21:$L21,'P&L'!$D$31:$L$31) -> 112500 | J35: =SUMPRODUCT('P&L'!$D21:$L21,'P&L'!$D$32:$L$32) -> 217500 | K35: =SUM(H35:J35) -> 510000 | L35: =K35/L9 -> 52.040816
C36: Product Development | H36: =SUMPRODUCT('P&L'!$D22:$L22,'P&L'!$D$30:$L$30) -> 360000 | I36: =SUMPRODUCT('P&L'!$D22:$L22,'P&L'!$D$31:$L$31) -> 225000 | J36: =SUMPRODUCT('P&L'!$D22:$L22,'P&L'!$D$32:$L$32) -> 435000 | K36: =SUM(H36:J36) -> 1020000 | L36: =K36/L10 -> 260.20408
C37: Consulting | H37: =SUMPRODUCT('P&L'!$D23:$L23,'P&L'!$D$30:$L$30) -> 420000 | I37: =SUMPRODUCT('P&L'!$D23:$L23,'P&L'!$D$31:$L$31) -> 262500 | J37: =SUMPRODUCT('P&L'!$D23:$L23,'P&L'!$D$32:$L$32) -> 507500 | K37: =SUM(H37:J37) -> 1190000 | L37: =K37/L11 -> 151.78571
C38: Logistics | H38: =SUMPRODUCT('P&L'!$D24:$L24,'P&L'!$D$30:$L$30) -> 120000 | I38: =SUMPRODUCT('P&L'!$D24:$L24,'P&L'!$D$31:$L$31) -> 75000 | J38: =SUMPRODUCT('P&L'!$D24:$L24,'P&L'!$D$32:$L$32) -> 145000 | K38: =SUM(H38:J38) -> 340000 | L38: =K38/L12 -> 173.46939
C39: Total | H39: =SUM(H35:H38) -> 1080000 | I39: =SUM(I35:I38) -> 675000 | J39: =SUM(J35:J38) -> 1305000 | K39: =SUM(K35:K38) -> 3060000
A41: 3 | C41: ROI
C43: ROI | H43: FY1 | I43: FY2 | J43: FY3 | K43: Total
C44: Design | H44: =H35/H25 -> 0.32727273 | I44: =I35/I25 -> 0.20454545 | J44: =J35/J25 -> 0.39545455 | K44: =K35/K25 -> 0.30909091
C45: Product Development | H45: =H36/H26 -> 1.3333333 | I45: =I36/I26 -> 0.83333333 | J45: =J36/J26 -> 1.6111111 | K45: =K36/K26 -> 1.2592593
C46: Consulting | H46: =H37/H27 -> 0.62222222 | I46: =I37/I27 -> 0.38888889 | J46: =J37/J27 -> 0.75185185 | K46: =K37/K27 -> 0.58765432
C47: Logistics | H47: =H38/H28 -> 0.96 | I47: =I38/I28 -> 0.6 | J47: =J38/J28 -> 1.16 | K47: =K38/K28 -> 0.90666667
C48: Total | H48: =H39/H29 -> 0.66666667 | I48: =I39/I29 -> 0.41666667 | J48: =J39/J29 -> 0.80555556 | K48: =K39/K29 -> 0.62962963
A50: 4 | C50: Hypothesis
C52: Design and Consulting have the lowest ROI (31% and 59%). Despite consulting having the highest fees (7% of total budget), timing of consulting + payout of salary is not optimized for the 3 year period
C53: Alternatively, Design has a lower fee based, but is paid the second highest in total salaries at $550k driving the lower ROI.
C54: In General, timing of recognized revenue and fixed salaries cause ROI to fluctuate and as a result drives lumpier operating margins. This is specificallly seen in FY2 with consulting and design being the two largest drivers.
C55: To alleviate and smooth out this issue, some of the staff should be a on variable basis based on total number of hours required to complete the project.
C56: See below for adjusted salaries with part of pay being allocated based on hour time
C57: Note - further diligence required to determine
A60: 5 | C60: Reallocation of Team Members
H62: Hours | M62: Salary
E63: Salary | F63: Hourly salary | G63: Fixed / Variable? | H63: =H43 -> FY1 | I63: =I43 -> FY2 | J63: =J43 -> FY3 | K63: Total | M63: FY1 | N63: FY2 | O63: FY3 | P63: Total
C65: Design
C66: Hours Required | H66: =H35/$L35 -> 3458.8235 | I66: =I35/$L35 -> 2161.7647 | J66: =J35/$L35 -> 4179.4118 | K66: =K35/$L35 -> 9800
C67: Increase in hours for extra weighting | E67: 0 | H67: =H66*(1+$E$67) -> 3458.8235 | I67: =I66*(1+$E$67) -> 2161.7647 | J67: =J66*(1+$E$67) -> 4179.4118 | K67: =K66*(1+$E$67) -> 9800
C68: People Required | H68: =H67/(40*49) -> 1.7647059 | I68: =I67/(40*49) -> 1.1029412 | J68: =J67/(40*49) -> 2.1323529 | K68: =K67/(40*49) -> 5
C70: Reallocated Team Members
C71: =C9 -> A | E71: =F9 -> 150000 | F71: =H9 -> 76.530612 | G71: 1 | H71: =1960*$G$71 -> 1960 | I71: =1960*$G$71 -> 1960 | J71: =1960*$G$71 -> 1960 | M71: =H71*$F71 -> 150000 | N71: =I71*$F71 -> 150000 | O71: =J71*$F71 -> 150000 | P71: =SUM(M71:O71) -> 450000
C72: =C10 -> B | E72: =F10 -> 125000 | F72: =H10 -> 63.77551 | G72: 1 | H72: =1960*$G$72 -> 1960 | I72: =1960*$G$72 -> 1960 | J72: =1960*$G$72 -> 1960 | M72: =H72*$F72 -> 125000 | N72: =I72*$F72 -> 125000 | O72: =J72*$F72 -> 125000 | P72: =SUM(M72:O72) -> 375000
C73: =C11 -> C | E73: =F11 -> 110000 | F73: =H11 -> 56.122449 | G73: 0 | H73: =IF(H67-SUM(H71:H72)<0,0,MIN(1960,H67-SUM(H71:H72))) -> 0 | I73: =IF(I67-SUM(I71:I72)<0,0,MIN(1960,I67-SUM(I71:I72))) -> 0 | J73: =IF(J67-SUM(J71:J72)<0,0,MIN(1960,J67-SUM(J71:J72))) -> 259.41176 | M73: =H73*$F73 -> 0 | N73: =I73*$F73 -> 0 | O73: =J73*$F73 -> 14558.824 | P73: =SUM(M73:O73) -> 14558.824
C74: =C12 -> D | E74: =F12 -> 90000 | F74: =H12 -> 45.918367 | G74: 0 | H74: =IF(H67-SUM(H71:H73)<0,0,MIN(1960,H67-SUM(H71:H73))) -> 0 | I74: =IF(I67-SUM(I71:I73)<0,0,MIN(1960,I67-SUM(I71:I73))) -> 0 | J74: =IF(J67-SUM(J71:J73)<0,0,MIN(1960,J67-SUM(J71:J73))) -> 0 | M74: =H74*$F74 -> 0 | N74: =I74*$F74 -> 0 | O74: =J74*$F74 -> 0 | P74: =SUM(M74:O74) -> 0
C75: =C13 -> E | E75: =F13 -> 75000 | F75: =H13 -> 38.265306 | G75: 0 | H75: =IF(H67-SUM(H71:H74)<0,0,MIN(1960,H67-SUM(H71:H74))) -> 0 | I75: =IF(I67-SUM(I71:I74)<0,0,MIN(1960,I67-SUM(I71:I74))) -> 0 | J75: =IF(J67-SUM(J71:J74)<0,0,MIN(1960,J67-SUM(J71:J74))) -> 0 | M75: =H75*$F75 -> 0 | N75: =I75*$F75 -> 0 | O75: =J75*$F75 -> 0 | P75: =SUM(M75:O75) -> 0
C76: Total | H76: =SUM(H71:H75) -> 3920 | I76: =SUM(I71:I75) -> 3920 | J76: =SUM(J71:J75) -> 4179.4118 | M76: =SUM(M71:M75) -> 275000 | N76: =SUM(N71:N75) -> 275000 | O76: =SUM(O71:O75) -> 289558.82 | P76: =SUM(P71:P75) -> 839558.82
C78: Product Development
C79: Hours Required | H79: =H36/$L36 -> 1383.5294 | I79: =I36/$L36 -> 864.70588 | J79: =J36/$L36 -> 1671.7647 | K79: =K36/$L36 -> 3920
C80: Increase in hours for extra weighting | E80: =E67 -> 0 | H80: =H79*(1+$E$80) -> 1383.5294 | I80: =I79*(1+$E$80) -> 864.70588 | J80: =J79*(1+$E$80) -> 1671.7647 | K80: =K79*(1+$E$80) -> 3920
C81: People Required | H81: =H80/(40*49) -> 0.70588235 | I81: =I80/(40*49) -> 0.44117647 | J81: =J80/(40*49) -> 0.85294118 | K81: =K80/(40*49) -> 2
C83: Product Development
C84: =C14 -> F | E84: =F14 -> 150000 | F84: =H14 -> 76.530612 | G84: 1 | H84: =1960*$G$84 -> 1960 | I84: =1960*$G$84 -> 1960 | J84: =1960*$G$84 -> 1960 | M84: =H84*$F84 -> 150000 | N84: =I84*$F84 -> 150000 | O84: =J84*$F84 -> 150000 | P84: =SUM(M84:O84) -> 450000
C85: =C15 -> G | E85: =F15 -> 120000 | F85: =H15 -> 61.22449 | G85: 0 | H85: =1960*$G$84 -> 1960 | I85: =1960*$G$84 -> 1960 | J85: =1960*$G$84 -> 1960 | M85: =H85*$F85 -> 120000 | N85: =I85*$F85 -> 120000 | O85: =J85*$F85 -> 120000 | P85: =SUM(M85:O85) -> 360000
C86: Total | H86: =SUM(H84:H85) -> 3920 | I86: =SUM(I84:I85) -> 3920 | J86: =SUM(J84:J85) -> 3920 | M86: =SUM(M84:M85) -> 270000 | N86: =SUM(N84:N85) -> 270000 | O86: =SUM(O84:O85) -> 270000 | P86: =SUM(P84:P85) -> 810000
C88: Consulting
C89: Hours Required | H89: =H37/$L37 -> 2767.0588 | I89: =I37/$L37 -> 1729.4118 | J89: =J37/$L37 -> 3343.5294 | K89: =K37/$L37 -> 7840
C90: Increase in hours for extra weighting | E90: 0.5 | H90: =H89*(1+$E$90) -> 4150.5882 | I90: =I89*(1+$E$90) -> 2594.1176 | J90: =J89*(1+$E$90) -> 5015.2941 | K90: =K89*(1+$E$90) -> 11760
C91: People Required | H91: =H90/(40*49) -> 2.1176471 | I91: =I90/(40*49) -> 1.3235294 | J91: =J90/(40*49) -> 2.5588235 | K91: =K90/(40*49) -> 6
C94: Consulting
C95: =C16 -> H | E95: =F16 -> 200000 | F95: =H16 -> 102.04082 | G95: 1 | H95: =1960*$G$95 -> 1960 | I95: =1960*$G$95 -> 1960 | J95: =1960*$G$95 -> 1960 | M95: =H95*$F95 -> 200000 | N95: =I95*$F95 -> 200000 | O95: =J95*$F95 -> 200000 | P95: =SUM(M95:O95) -> 600000
C96: =C17 -> I | E96: =F17 -> 200000 | F96: =H17 -> 102.04082 | G96: 1 | H96: =1960*$G$96 -> 1960 | I96: =1960*$G$96 -> 1960 | J96: =1960*$G$96 -> 1960 | M96: =H96*$F96 -> 200000 | N96: =I96*$F96 -> 200000 | O96: =J96*$F96 -> 200000 | P96: =SUM(M96:O96) -> 600000
C97: =C18 -> J | E97: =F18 -> 150000 | F97: =H18 -> 76.530612 | G97: 0 | H97: =IF(H90-SUM(H95:H96)<0,0,MIN(1960,H90-SUM(H95:H96))) -> 230.58824 | I97: =IF(I90-SUM(I95:I96)<0,0,MIN(1960,I90-SUM(I95:I96))) -> 0 | J97: =IF(J90-SUM(J95:J96)<0,0,MIN(1960,J90-SUM(J95:J96))) -> 1095.2941 | M97: =H97*$F97 -> 17647.059 | N97: =I97*$F97 -> 0 | O97: =J97*$F97 -> 83823.529 | P97: =SUM(M97:O97) -> 101470.59
C98: =C19 -> K | E98: =F19 -> 125000 | F98: =H19 -> 63.77551 | G98: 0 | H98: =IF(H90-SUM(H95:H97)<0,0,MIN(1960,H90-SUM(H95:H97))) -> 0 | I98: =IF(I90-SUM(I95:I97)<0,0,MIN(1960,I90-SUM(I95:I97))) -> 0 | J98: =IF(J90-SUM(J95:J97)<0,0,MIN(1960,J90-SUM(J95:J97))) -> 0 | M98: =H98*$F98 -> 0 | N98: =I98*$F98 -> 0 | O98: =J98*$F98 -> 0 | P98: =SUM(M98:O98) -> 0
C99: Total | H99: =SUM(H95:H98) -> 4150.5882 | I99: =SUM(I95:I98) -> 3920 | J99: =SUM(J95:J98) -> 5015.2941 | M99: =SUM(M95:M98) -> 417647.06 | N99: =SUM(N95:N98) -> 400000 | O99: =SUM(O95:O98) -> 483823.53 | P99: =SUM(P95:P98) -> 1301470.6
C101: Logistics
C102: Hours Required | H102: =H38/$L38 -> 691.76471 | I102: =I38/$L38 -> 432.35294 | J102: =J38/$L38 -> 835.88235 | K102: =K38/$L38 -> 1960
C103: Increase in hours for extra weighting | E103: 0.5 | H103: =H102*(1+$E$103) -> 1037.6471 | I103: =I102*(1+$E$103) -> 648.52941 | J103: =J102*(1+$E$103) -> 1253.8235 | K103: =K102*(1+$E$103) -> 2940
C104: People Required | H104: =H103/(40*49) -> 0.52941176 | I104: =I103/(40*49) -> 0.33088235 | J104: =J103/(40*49) -> 0.63970588 | K104: =K103/(40*49) -> 1.5
C106: Logistics
C107: =C20 -> L | E107: =F20 -> 125000 | F107: =H20 -> 63.77551 | G107: 1 | H107: 1960 | I107: 1960 | J107: 1960 | M107: =H107*$F107 -> 125000 | N107: =I107*$F107 -> 125000 | O107: =J107*$F107 -> 125000 | P107: =SUM(M107:O107) -> 375000
C108: Total | H108: =SUM(H107) -> 1960 | I108: =SUM(I107) -> 1960 | J108: =SUM(J107) -> 1960 | M108: =SUM(M107) -> 125000 | N108: =SUM(N107) -> 125000 | O108: =SUM(O107) -> 125000 | P108: =SUM(P107) -> 375000
C110: Total | M110: =M108+M99+M86+M76 -> 1087647.1 | N110: =N108+N99+N86+N76 -> 1070000 | O110: =O108+O99+O86+O76 -> 1168382.4 | P110: =P108+P99+P86+P76 -> 3326029.4
A113: 6 | C113: New ROI
C115: ROI | H115: FY1 | I115: FY2 | J115: FY3 | K115: Total
C116: Design | H116: =H35/M76 -> 0.65454545 | I116: =I35/N76 -> 0.40909091 | J116: =J35/O76 -> 0.75114271 | K116: =K35/P76 -> 0.6074619
C117: Product Development | H117: =H36/M86 -> 1.3333333 | I117: =I36/N86 -> 0.83333333 | J117: =J36/O86 -> 1.6111111 | K117: =K36/P86 -> 1.2592593
C118: Consulting | H118: =H37/M99 -> 1.0056338 | I118: =I37/N99 -> 0.65625 | J118: =J37/O99 -> 1.0489362 | K118: =K37/P99 -> 0.91435028
C119: Logistics | H119: =H38/M108 -> 0.96 | I119: =I38/N108 -> 0.6 | J119: =J38/O108 -> 1.16 | K119: =K38/P108 -> 0.90666667
C120: Total | H120: =H39/M110 -> 0.99296917 | I120: =I39/N110 -> 0.63084112 | J120: =J39/O110 -> 1.1169289 | K120: =K39/P110 -> 0.92001592

Sheet Questions
B2: Questions
B3: Are Fees paid on the same schedule as Revenue?
B4: Is COGS based on total revenue or just STOWED product?

Sheet Support>>>

Sheet RH
A1: RH
A2: RH US | C2: 39844 | AF2: Restated | AG2: Restated | AH2: Restated | AI2: Restated | AJ2: Restated | AZ2: Restated | BA2: Restated | BB2: Restated
A3: USD | B3: 334.75 | C3: 364 | D3: 364 | E3: 364 | F3: 371 | G3: 91 | H3: 91 | I3: 91 | J3: 91 | K3: 364 | L3: 91 | M3: 91 | N3: 91 | O3: 91 | P3: 364 | Q3: 91 | R3: 91 | S3: 91 | T3: 91 | U3: 364 | V3: 91 | W3: 91 | X3: 91 | Y3: 91 | Z3: 364 | AA3: 91 | AB3: 91 | AC3: 91 | AD3: 98 | AE3: 371 | AF3: 91 | AG3: 91 | AH3: 91 | AI3: 91 | AJ3: 364 | AK3: 91 | AL3: 91 | AM3: 91 | AN3: 91 | AO3: 364 | AP3: 91 | AQ3: 91 | AR3: 91 | AS3: 91 | AT3: 364 | AU3: 91 | AV3: 91 | AW3: 91 | AX3: 91 | AY3: 364 | AZ3: 91 | BA3: 91 | BB3: 91 | BC3: 91 | BD3: 364 | BE3: 91 | BF3: 91 | BG3: 91 | BH3: 98 | BI3: 371 | BJ3: 91 | BK3: 91 | BL3: 91 | BM3: 91 | BN3: 364 | BO3: 91 | BP3: 91 | BQ3: 91 | BR3: 91 | BS3: 364 | BT3: 364 | BU3: 364 | BV3: 371
A4: Bloomberg | B4: OFF | C4: 40208 | D4: 40572 | E4: 40936 | F4: 41307 | G4: 41398 | H4: 41489 | I4: 41580 | J4: 41671 | K4: 41671 | L4: 41762 | M4: 41853 | N4: 41944 | O4: 42035 | P4: 42035 | Q4: 42126 | R4: 42217 | S4: 42308 | T4: 42399 | U4: 42399 | V4: 42490 | W4: 42581 | X4: 42672 | Y4: 42763 | Z4: 42763 | AA4: 42854 | AB4: 42945 | AC4: 43036 | AD4: 43134 | AE4: 43134 | AF4: 43225 | AG4: 43316 | AH4: 43407 | AI4: 43498 | AJ4: 43498 | AK4: 43589 | AL4: 43680 | AM4: 43771 | AN4: 43862 | AO4: 43862 | AP4: 43953 | AQ4: 44044 | AR4: 44135 | AS4: 44226 | AT4: 44226 | AU4: 44317 | AV4: 44408 | AW4: 44499 | AX4: 44590 | AY4: 44590 | AZ4: 44681 | BA4: 44772 | BB4: 44863 | BC4: 44954 | BD4: 44954 | BE4: 45045 | BF4: 45136 | BG4: 45227 | BH4: 45325 | BI4: 45325 | BJ4: 45416 | BK4: 45507 | BL4: 45598 | BM4: 45689 | BN4: 45689 | BO4: 45780 | BP4: 45871 | BQ4: 45962 | BR4: 46053 | BS4: 46053 | BT4: 46417 | BU4: 46781 | BV4: 47152
A5: USD | C5: FY2009 | D5: FY2010 | E5: FY2011 | F5: FY2012 | G5: Q1-2013 | H5: Q2-2013 | I5: Q3-2013 | J5: Q4-2013 | K5: FY2013 | L5: Q1-2014 | M5: Q2-2014 | N5: Q3-2014 | O5: Q4-2014 | P5: FY2014 | Q5: Q1-2015 | R5: Q2-2015 | S5: Q3-2015 | T5: Q4-2015 | U5: FY2015 | V5: Q1-2016 | W5: Q2-2016 | X5: Q3-2016 | Y5: Q4-2016 | Z5: FY2016 | AA5: Q1-2017 | AB5: Q2-2017 | AC5: Q3-2017 | AD5: Q4-2017 | AE5: FY2017 | AF5: Q1-2018 | AG5: Q2-2018 | AH5: Q3-2018 | AI5: Q4-2018 | AJ5: FY2018 | AK5: Q1-2019 | AL5: Q2-2019 | AM5: Q3-2019 | AN5: Q4-2019 | AO5: FY2019 | AP5: Q1-2020 | AQ5: Q2-2020 | AR5: Q3-2020 | AS5: Q4-2020 | AT5: FY2020 | AU5: Q1-2021 | AV5: Q2-2021 | AW5: Q3-2021 | AX5: Q4-2021 | AY5: FY2021 | AZ5: Q1-2022 | BA5: Q2-2022 | BB5: Q3-2022 | BC5: Q4-2022 | BD5: FY2022 | BE5: Q1-2023 | BF5: Q2-2023 | BG5: Q3-2023 | BH5: Q4-2023 | BI5: FY2023 | BJ5: Q1-2024 | BK5: Q2-2024 | BL5: Q3-2024 | BM5: Q4-2024 | BN5: FY2024 | BO5: Q1-2025 | BP5: Q2-2025 | BQ5: Q3-2025 | BR5: Q4-2025 | BS5: FY2025 | BT5: FY2026 | BU5: FY2027 | BV5: FY2028
A6: Consolidated Summary
A7: Total Retail Locations - EoP, # of stores | C7: 95 | D7: 91 | E7: 74 | F7: 71 | G7: 70 | H7: 70 | I7: 70 | J7: 70 | K7: 70 | L7: 69 | M7: 68 | N7: 68 | O7: 67 | P7: 67 | Q7: 67 | R7: 67 | S7: 68 | T7: 69 | U7: 69 | V7: 69 | W7: 84 | X7: 85 | Y7: 85 | Z7: 85 | AA7: 85 | AB7: 85 | AC7: 84 | AD7: 83 | AE7: 83 | AF7: 84 | AG7: 85 | AH7: 86 | AI7: 86 | AJ7: 86 | AK7: 85 | AL7: 85 | AM7: 85 | AN7: 83 | AO7: 83 | AP7: 84 | AQ7: 83 | AR7: 82 | AS7: 82 | AT7: 82 | AU7: 82 | AV7: 80 | AW7: 80 | AX7: 81 | AY7: 81 | AZ7: 81 | BA7: 81 | BB7: 81 | BC7: 81 | BD7: 81 | BE7: 81 | BF7: 82 | BG7: 82 | BH7: 84 | BI7: 84 | BJ7: 86 | BK7: 88 | BL7: 90 | BM7: 91 | BN7: 91 | BO7: 92 | BP7: 93 | BQ7: 94 | BR7: 94 | BS7: 94 | BT7: 95 | BU7: 95 | BV7: 95
A8: Q/Q Total retail locations - EoP growth, % | G8: -0.014084507 | H8: 0 | I8: 0 | J8: 0 | L8: -0.014285714 | M8: -0.014492754 | N8: 0 | O8: -0.014705882 | Q8: 0 | R8: 0 | S8: 0.014925373 | T8: 0.014705882 | V8: 0 | W8: 0.2173913 | X8: 0.011904762 | Y8: 0 | AA8: 0 | AB8: 0 | AC8: -0.011764706 | AD8: -0.011904762 | AF8: 0.012048193 | AG8: 0.011904762 | AH8: 0.011764706 | AI8: 0 | AK8: -0.011627907 | AL8: 0 | AM8: 0 | AN8: -0.023529412 | AP8: 0.012048193 | AQ8: -0.011904762 | AR8: -0.012048193 | AS8: 0 | AU8: 0 | AV8: -0.024390244 | AW8: 0 | AX8: 0.0125 | AZ8: 0 | BA8: 0 | BB8: 0 | BC8: 0 | BE8: 0 | BF8: 0.012345679 | BG8: 0 | BH8: 0.024390244 | BJ8: 0.023809524 | BK8: 0.023255814 | BL8: 0.022727273 | BM8: 0.011111111 | BO8: 0.010989011 | BP8: 0.010869565 | BQ8: 0.010752688 | BR8: 0
A9: Y/Y Total retail locations - EoP growth, % | D9: -0.042105263 | E9: -0.18681319 | F9: -0.040540541 | K9: -0.014084507 | L9: -0.014285714 | M9: -0.028571429 | N9: -0.028571429 | O9: -0.042857143 | P9: -0.042857143 | Q9: -0.028985507 | R9: -0.014705882 | S9: 0 | T9: 0.029850746 | U9: 0.029850746 | V9: 0.029850746 | W9: 0.25373134 | X9: 0.25 | Y9: 0.23188406 | Z9: 0.23188406 | AA9: 0.23188406 | AB9: 0.011904762 | AC9: -0.011764706 | AD9: -0.023529412 | AE9: -0.023529412 | AF9: -0.011764706 | AG9: 0 | AH9: 0.023809524 | AI9: 0.036144578 | AJ9: 0.036144578 | AK9: 0.011904762 | AL9: 0 | AM9: -0.011627907 | AN9: -0.034883721 | AO9: -0.034883721 | AP9: -0.011764706 | AQ9: -0.023529412 | AR9: -0.035294118 | AS9: -0.012048193 | AT9: -0.012048193 | AU9: -0.023809524 | AV9: -0.036144578 | AW9: -0.024390244 | AX9: -0.012195122 | AY9: -0.012195122 | AZ9: -0.012195122 | BA9: 0.0125 | BB9: 0.0125 | BC9: 0 | BD9: 0 | BE9: 0 | BF9: 0.012345679 | BG9: 0.012345679 | BH9: 0.037037037 | BI9: 0.037037037 | BJ9: 0.061728395 | BK9: 0.073170732 | BL9: 0.097560976 | BM9: 0.083333333 | BN9: 0.083333333 | BO9: 0.069767442 | BP9: 0.056818182 | BQ9: 0.044444444 | BR9: 0.032967033 | BS9: 0.032967033 | BT9: 0.010638298 | BU9: 0 | BV9: 0
A11: RH Segment revenue, mm | C11: 625.685 | D11: 772.752 | E11: 958.084 | F11: 1193.046 | G11: 301.337 | H11: 382.098 | I11: 395.832 | J11: 471.694 | K11: 1550.961 | L11: 366.254 | M11: 433.766 | N11: 484.675 | O11: 582.727 | P11: 1867.422 | Q11: 422.445 | R11: 506.942 | S11: 532.411 | T11: 647.208 | U11: 2109.006 | V11: 455.456 | W11: 522.618 | X11: 521.027 | Y11: 560.943 | Z11: 2060.044 | AA11: 533.528 | AB11: 583.793 | AC11: 563.174 | AD11: 638.837 | AE11: 2319.332 | AF11: 526.007 | AG11: 607.604 | AH11: 604.322 | AI11: 637.539 | AJ11: 2375.472 | AK11: 563.706 | AL11: 672.328 | AM11: 645.378 | AN11: 632.884 | AO11: 2514.296 | AP11: 454.957 | AQ11: 681.387 | AR11: 812.782 | AS11: 780.296 | AT11: 2729.422 | AU11: 819.823 | AV11: 947.618 | AW11: 964.859 | AX11: 861.542 | AY11: 3593.842 | AZ11: 908.948 | BA11: 940.182 | BB11: 821.26 | BC11: 728.248 | BD11: 3398.638 | BE11: 690.516 | BF11: 753.55 | BG11: 705.061 | BH11: 686.49 | BI11: 2835.617 | BJ11: 676.85902 | BK11: 795.63632 | BL11: 809.15842 | BM11: 765.7331 | BN11: 3047.3869 | BO11: 805.83872 | BP11: 921.16825 | BQ11: 931.43026 | BR11: 842.84749 | BS11: 3501.2847 | BT11: 3708.4598 | BU11: 3827.795 | BV11: 3907.1631
A12: Y/Y RH core demand growth, % | AP12: -0.11 | AQ12: 0.24 | AR12: 0.42 | AS12: 0.36 | AU12: 1.09
A13: Y/Y RH Segment revenue growth, % | D13: 0.23504959 | E13: 0.23983374 | F13: 0.24524154 | K13: 0.30000101 | L13: 0.2154299 | M13: 0.13522185 | N13: 0.22444623 | O13: 0.23539201 | P13: 0.20404188 | Q13: 0.15342085 | R13: 0.16869925 | S13: 0.098490741 | T13: 0.11065387 | U13: 0.12936765 | V13: 0.078142717 | W13: 0.03092267 | X13: -0.021381977 | Y13: -0.13328791 | Z13: -0.023215676 | AA13: 0.17141502 | AB13: 0.1170549 | AC13: 0.080892161 | AD13: 0.13886259 | AE13: 0.12586527 | AF13: -0.01409673 | AG13: 0.040786717 | AH13: 0.073064453 | AI13: -0.0020318172 | AJ13: 0.024205245 | AK13: 0.071670149 | AL13: 0.10652333 | AM13: 0.067937292 | AN13: -0.0073015141 | AO13: 0.058440596 | AP13: -0.19291794 | AQ13: 0.013474078 | AR13: 0.25938907 | AS13: 0.23292104 | AT13: 0.085561127 | AU13: 0.80197909 | AV13: 0.39071922 | AW13: 0.18710675 | AX13: 0.10412203 | AY13: 0.31670442 | AZ13: 0.10871249 | BA13: -0.0078470439 | BB13: -0.148829 | BC13: -0.15471561 | BD13: -0.054316244 | BE13: -0.24031298 | BF13: -0.19850625 | BG13: -0.14148869 | BH13: -0.057340357 | BI13: -0.16566077 | BJ13: -0.019777931 | BK13: 0.055850731 | BL13: 0.14764314 | BM13: 0.11543227 | BN13: 0.07468211 | BO13: 0.19055622 | BP13: 0.15777551 | BQ13: 0.1511099 | BR13: 0.10070661 | BS13: 0.14894658 | BT13: 0.059171164 | BU13: 0.032179171 | BV13: 0.020734696
A14: Waterworks revenue, mm | W14: 20.763 | X14: 28.301 | Y14: 25.763 | Z14: 74.827 | AA14: 28.552 | AB14: 31.533 | AC14: 29.299 | AD14: 31.458 | AE14: 120.842 | AF14: 31.399 | AG14: 33.194 | AH14: 32.236 | AI14: 33.352 | AJ14: 130.181 | AK14: 34.715 | AL14: 34.186 | AM14: 32.148 | AN14: 32.092 | AO14: 133.141 | AP14: 27.938 | AQ14: 27.895 | AR14: 31.231 | AS14: 32.14 | AT14: 119.204 | AU14: 40.969 | AV14: 41.241 | AW14: 41.569 | AX14: 41.199 | AY14: 164.978 | AZ14: 48.344 | BA14: 51.438 | BB14: 47.806 | BC14: 44.251 | BD14: 191.839 | BE14: 48.646 | BF14: 46.929 | BG14: 46.164 | BH14: 51.77 | BI14: 193.509 | BJ14: 47.447647 | BK14: 48.233855 | BL14: 48.900061 | BM14: 51.41254 | BN14: 195.9941 | BO14: 48.871077 | BP14: 49.680871 | BQ14: 51.345065 | BR14: 53.983167 | BS14: 203.88018 | BT14: 209.99658 | BU14: 216.29648 | BV14: 222.78538
A15: Y/Y Waterworks revenue growth, % | AB15: 0.51871117 | AC15: 0.035263772 | AD15: 0.22105345 | AE15: NMF | AF15: 0.099712805 | AG15: 0.052674975 | AH15: 0.10024233 | AI15: 0.06020726 | AJ15: 0.077282733 | AK15: 0.10560846 | AL15: 0.029884919 | AM15: -0.0027298672 | AN15: -0.037778844 | AO15: 0.022737573 | AP15: -0.19521821 | AQ15: -0.1840227 | AR15: -0.028524325 | AS15: 0.0014956999 | AT15: -0.1046785 | AU15: 0.46642566 | AV15: 0.478437 | AW15: 0.33101726 | AX15: 0.28186061 | AY15: 0.38399718 | AZ15: 0.18001416 | BA15: 0.24725395 | BB15: 0.15003969 | BC15: 0.074079468 | BD15: 0.16281565 | BE15: 0.0062468972 | BF15: -0.087658929 | BG15: -0.034347153 | BH15: 0.16991706 | BI15: 0.0087052164 | BJ15: -0.024634146 | BK15: 0.027804878 | BL15: 0.059268293 | BM15: -0.0069047619 | BN15: 0.012842319 | BO15: 0.03 | BP15: 0.03 | BQ15: 0.05 | BR15: 0.05 | BS15: 0.040236288 | BT15: 0.03 | BU15: 0.03 | BV15: 0.03
A16: Total Revenue, mm | C16: 625.685 | D16: 772.752 | E16: 958.084 | F16: 1193.046 | G16: 301.337 | H16: 382.098 | I16: 395.832 | J16: 471.694 | K16: 1550.961 | L16: 366.254 | M16: 433.766 | N16: 484.675 | O16: 582.727 | P16: 1867.422 | Q16: 422.445 | R16: 506.942 | S16: 532.411 | T16: 647.208 | U16: 2109.006 | V16: 455.456 | W16: 543.381 | X16: 549.328 | Y16: 586.706 | Z16: 2134.871 | AA16: 562.08 | AB16: 615.326 | AC16: 592.473 | AD16: 670.295 | AE16: 2440.174 | AF16: 557.406 | AG16: 640.798 | AH16: 636.558 | AI16: 670.891 | AJ16: 2505.653 | AK16: 598.421 | AL16: 706.514 | AM16: 677.526 | AN16: 664.976 | AO16: 2647.437 | AP16: 482.895 | AQ16: 709.282 | AR16: 844.013 | AS16: 812.436 | AT16: 2848.626 | AU16: 860.792 | AV16: 988.859 | AW16: 1006.428 | AX16: 902.741 | AY16: 3758.82 | AZ16: 957.292 | BA16: 991.62 | BB16: 869.066 | BC16: 772.499 | BD16: 3590.477 | BE16: 739.162 | BF16: 800.479 | BG16: 751.225 | BH16: 738.26 | BI16: 3029.126 | BJ16: 724.30667 | BK16: 843.87017 | BL16: 858.05848 | BM16: 817.14564 | BN16: 3243.381 | BO16: 854.70979 | BP16: 970.84912 | BQ16: 982.77533 | BR16: 896.83066 | BS16: 3705.1649 | BT16: 3918.4564 | BU16: 4044.0915 | BV16: 4129.9485
A17: Consensus Estimates - Net Revenue | BJ17: N/A | BK17: N/A | BL17: N/A | BM17: N/A | BN17: N/A | BO17: N/A | BP17: N/A | BQ17: N/A | BR17: N/A | BS17: N/A | BT17: N/A | BU17: N/A | BV17: N/A
A18: Y/Y Total company demand growth, % | AP18: -0.17 | AQ18: 0.16 | AR18: 0.33 | AS18: 0.29 | AU18: 1.01
A19: Y/Y Total revenue growth, % | D19: 0.23504959 | E19: 0.23983374 | F19: 0.24524154 | K19: 0.30000101 | L19: 0.2154299 | M19: 0.13522185 | N19: 0.22444623 | O19: 0.23539201 | P19: 0.20404188 | Q19: 0.15342085 | R19: 0.16869925 | S19: 0.098490741 | T19: 0.11065387 | U19: 0.12936765 | V19: 0.078142717 | W19: 0.071880018 | X19: 0.031774325 | Y19: -0.093481539 | Z19: 0.012264071 | AA19: 0.23410384 | AB19: 0.13240249 | AC19: 0.078541418 | AD19: 0.1424717 | AE19: 0.1430077 | AF19: -0.0083155423 | AG19: 0.041395943 | AH19: 0.074408454 | AI19: 0.00088916074 | AJ19: 0.026833742 | AK19: 0.073581913 | AL19: 0.10255338 | AM19: 0.064358629 | AN19: -0.0088166334 | AO19: 0.056585649 | AP19: -0.19305138 | AQ19: 0.0039178275 | AR19: 0.24572784 | AS19: 0.22175236 | AT19: 0.075993876 | AU19: 0.78256557 | AV19: 0.39416903 | AW19: 0.19243187 | AX19: 0.11115337 | AY19: 0.31952036 | AZ19: 0.11210606 | BA19: 0.0027921069 | BB19: -0.13648468 | BC19: -0.14427394 | BD19: -0.04478613 | BE19: -0.22786151 | BF19: -0.1927563 | BG19: -0.135595 | BH19: -0.044322387 | BI19: -0.15634441 | BJ19: -0.02009753 | BK19: 0.054206511 | BL19: 0.14221236 | BM19: 0.10685347 | BN19: 0.070731612 | BO19: 0.18003855 | BP19: 0.15047213 | BQ19: 0.14534773 | BR19: 0.097516295 | BS19: 0.14237733 | BT19: 0.057565993 | BU19: 0.032062385 | BV19: 0.021230247
A21: Adjusted Gross Profit, mm | C21: 200.276 | D21: 271.62 | E21: 356.349 | F21: 439.699 | G21: 101.877 | H21: 139.226 | I21: 140.8 | J21: 174.977 | K21: 556.88 | L21: 124.349 | M21: 167.909 | N21: 180.373 | O21: 218.143 | P21: 690.774 | Q21: 144.797 | R21: 199.107 | S21: 195.551 | T21: 230.451 | U21: 769.906 | V21: 135.204 | W21: 183.24 | X21: 177.605 | Y21: 204.463 | Z21: 700.512 | AA21: 171.636 | AB21: 210.869 | AC21: 218.622 | AD21: 257.524 | AE21: 858.651 | AF21: 209.269 | AG21: 267.125 | AH21: 255.185 | AI21: 260.257 | AJ21: 991.836 | AK21: 234.159 | AL21: 296.554 | AM21: 282.371 | AN21: 283.073 | AO21: 1096.157 | AP21: 202.004 | AQ21: 337.199 | AR21: 409.111 | AS21: 385.494 | AT21: 1333.808 | AU21: 406.977 | AV21: 487.676 | AW21: 505.254 | AX21: 454.304 | AY21: 1854.211 | AZ21: 498.583 | BA21: 523.218 | BB21: 431.704 | BC21: 369.406 | BD21: 1822.911 | BE21: 347.545 | BF21: 380.073 | BG21: 340.45 | BH21: 320.951 | BI21: 1389.019 | BJ21: 301.52462 | BK21: 384.71654 | BL21: 393.57637 | BM21: 366.25384 | BN21: 1446.0714 | BO21: 367.21034 | BP21: 446.69644 | BQ21: 453.68544 | BR21: 406.05243 | BS21: 1673.6447 | BT21: 1780.7683 | BU21: 1849.5216 | BV21: 1900.912
A22: Consensus Estimates - Adjusted Gross Profit | BJ22: N/A | BK22: N/A | BL22: N/A | BM22: N/A | BN22: N/A | BO22: N/A | BP22: N/A | BQ22: N/A | BR22: N/A | BS22: N/A | BT22: N/A | BU22: N/A | BV22: N/A
A23: Adjusted gross margin, % | C23: 0.32009078 | D23: 0.35149699 | E23: 0.3719392 | F23: 0.36855159 | G23: 0.33808328 | H23: 0.36437249 | I23: 0.35570646 | J23: 0.37095447 | K23: 0.35905481 | L23: 0.33951575 | M23: 0.38709581 | N23: 0.37215247 | O23: 0.37434854 | P23: 0.36990782 | Q23: 0.34275941 | R23: 0.39276091 | S23: 0.36729331 | T23: 0.35606946 | U23: 0.36505633 | V23: 0.29685414 | W23: 0.33722195 | X23: 0.32331321 | Y23: 0.34646114 | Z23: 0.32760046 | AA23: 0.30535867 | AB23: 0.34058426 | AC23: 0.36899909 | AD23: 0.38454268 | AE23: 0.3514192 | AF23: 0.37543371 | AG23: 0.41566107 | AH23: 0.39965952 | AI23: 0.38738924 | AJ23: 0.39509303 | AK23: 0.39102489 | AL23: 0.41974257 | AM23: 0.41726292 | AN23: 0.42568905 | AO23: 0.41410576 | AP23: 0.41831868 | AQ23: 0.47513696 | AR23: 0.48427309 | AS23: 0.47438292 | AT23: 0.46800297 | AU23: 0.47279366 | AV23: 0.49317041 | AW23: 0.50202697 | AX23: 0.5039194 | AY23: 0.49345357 | AZ23: 0.52082646 | BA23: 0.52763962 | BB23: 0.49674478 | BC23: 0.47819609 | BD23: 0.50770719 | BE23: 0.47018786 | BF23: 0.47480696 | BG23: 0.45319312 | BH23: 0.43473979 | BI23: 0.45855438 | BJ23: 0.41629414 | BK23: 0.45589541 | BL23: 0.45868245 | BM23: 0.44821122 | BN23: 0.44585307 | BO23: 0.4296316 | BP23: 0.46010903 | BQ23: 0.46163699 | BR23: 0.45276377 | BS23: 0.45170585 | BT23: 0.45445658 | BU23: 0.45733922 | BV23: 0.46027499
A24: Consensus Estimates - Adjusted Gross Margin, % | BJ24: N/A | BK24: N/A | BL24: N/A | BM24: N/A | BN24: N/A | BO24: N/A | BP24: N/A | BQ24: N/A | BR24: N/A | BS24: N/A | BT24: N/A | BU24: N/A | BV24: N/A
A25: Y/Y Adjusted gross margin improvement, bps | D25: 314.06207 | E25: 204.42216 | F25: -33.876139 | K25: -94.967844 | L25: 14.324704 | M25: 227.23317 | N25: 164.46012 | O25: 33.940624 | P25: 108.53014 | Q25: 32.436666 | R25: 56.651001 | S25: -48.591604 | T25: -182.79082 | U25: -48.514848 | V25: -459.05271 | W25: -555.38958 | X25: -439.80101 | Y25: -96.083193 | Z25: -374.55872 | AA25: 85.04526 | AB25: 33.623137 | AC25: 456.85882 | AD25: 380.8154 | AE25: 238.18739 | AF25: 700.75038 | AG25: 750.76803 | AH25: 306.60424 | AI25: 28.465622 | AJ25: 436.73824 | AK25: 155.91186 | AL25: 40.815006 | AM25: 176.03406 | AN25: 382.99809 | AO25: 190.12736 | AP25: 272.9379 | AQ25: 553.94395 | AR25: 670.10166 | AS25: 486.93876 | AT25: 538.9721 | AU25: 544.74978 | AV25: 180.3345 | AW25: 177.53882 | AX25: 295.36477 | AY25: 254.50598 | AZ25: 480.32797 | BA25: 344.69208 | BB25: -52.821895 | BC25: -257.23312 | BD25: 142.53624 | BE25: -506.38595 | BF25: -528.32661 | BG25: -435.51663 | BH25: -434.56295 | BI25: -491.52812 | BJ25: -538.93722 | BK25: -189.11545 | BL25: 54.893337 | BM25: 134.71424 | BN25: -127.01307 | BO25: 133.37464 | BP25: 42.13613 | BQ25: 29.545385 | BR25: 45.52548 | BS25: 58.527738 | BT25: 27.507337 | BU25: 28.826362 | BV25: 29.357739
A27: Adjusted Operating Income, mm | C27: -27.564 | D27: 8.192 | E27: 49.219 | F27: 68.674 | G27: 4.601 | H27: 34.18 | I27: 23.86 | J27: 58.26 | K27: 120.901 | L27: 13.978 | M27: 48.935 | N27: 36.688 | O27: 73.825 | P27: 173.426 | Q27: 18.597 | R27: 61.897 | S27: 49.952 | T27: 74.161 | U27: 204.607 | V27: 0.71 | W27: 33.175 | X27: 18.146 | Y27: 50.883 | Z27: 102.914 | AA27: 8.276 | AB27: 39.908 | AC27: 48.005 | AD27: 75.109 | AE27: 171.298 | AF27: 49.158 | AG27: 75.466 | AH27: 61.075 | AI27: 101.485 | AJ27: 287.184 | AK27: 70.494 | AL27: 105.013 | AM27: 87.761 | AN27: 115.827 | AO27: 379.095 | AP27: 48.067 | AQ27: 154.923 | AR27: 225.311 | AS27: 192.241 | AT27: 620.542 | AU27: 194.252 | AV27: 262.655 | AW27: 278.71 | AX27: 227.011 | AY27: 962.628 | AZ27: 236.53 | BA27: 244.734 | BB27: 180.349 | BC27: 128.213 | BD27: 789.826 | BE27: 110.392 | BF27: 161.364 | BG27: 55.163 | BH27: 66.868 | BI27: 393.787 | BJ27: 50.573551 | BK27: 149.10355 | BL27: 124.48482 | BM27: 109.02981 | BN27: 433.19173 | BO27: 99.686446 | BP27: 184.59997 | BQ27: 148.30292 | BR27: 140.63884 | BS27: 573.22818 | BT27: 654.25112 | BU27: 724.58128 | BV27: 790.17582
A28: Consensus Estimates - Adjusted EBIT | BJ28: N/A | BK28: N/A | BL28: N/A | BM28: N/A | BN28: N/A | BO28: N/A | BP28: N/A | BQ28: N/A | BR28: N/A | BS28: N/A | BT28: N/A | BU28: N/A | BV28: N/A
A29: Adjusted operating margin, % | C29: -0.044054117 | D29: 0.010601073 | E29: 0.051372322 | F29: 0.057561905 | G29: 0.01526862 | H29: 0.089453491 | I29: 0.060278098 | J29: 0.12351228 | K29: 0.077952315 | L29: 0.038164771 | M29: 0.11281428 | N29: 0.075696085 | O29: 0.12668883 | P29: 0.092869207 | Q29: 0.044022299 | R29: 0.12209878 | S29: 0.093822254 | T29: 0.11458604 | U29: 0.097015845 | V29: 0.0015588773 | W29: 0.061052926 | X29: 0.033033088 | Y29: 0.086220891 | Z29: 0.048128617 | AA29: 0.014723883 | AB29: 0.064457254 | AC29: 0.081024789 | AD29: 0.11215505 | AE29: 0.070106954 | AF29: 0.088190655 | AG29: 0.11742921 | AH29: 0.095652977 | AI29: 0.15105913 | AJ29: 0.11439834 | AK29: 0.11771877 | AL29: 0.14863541 | AM29: 0.12968545 | AN29: 0.17418223 | AO29: 0.14321436 | AP29: 0.099539237 | AQ29: 0.21829734 | AR29: 0.26670526 | AS29: 0.23656879 | AT29: 0.21773411 | AU29: 0.2256666 | AV29: 0.26561421 | AW29: 0.27692989 | AX29: 0.2518033 | AY29: 0.25618024 | AZ29: 0.24708239 | BA29: 0.2468022 | BB29: 0.20752049 | BC29: 0.16597174 | BD29: 0.21997801 | BE29: 0.1493475 | BF29: 0.2015843 | BG29: 0.07343073 | BH29: 0.090575136 | BI29: 0.1300002 | BJ29: 0.069823395 | BK29: 0.17669015 | BL29: 0.14507731 | BM29: 0.13342764 | BN29: 0.13356178 | BO29: 0.11663192 | BP29: 0.1901428 | BQ29: 0.15090216 | BR29: 0.15681761 | BS29: 0.15471057 | BT29: 0.16696654 | BU29: 0.17917035 | BV29: 0.19132825
A30: Consensus Estimates - Adjusted EBIT Margin, % | BJ30: 0 | BK30: 0 | BL30: 0 | BM30: 0 | BN30: 0 | BO30: 0 | BP30: 0 | BQ30: 0 | BR30: 0 | BS30: 0 | BT30: 0 | BU30: 0 | BV30: 0
A31: Y/Y Adjusted operating margin improvement, bps | D31: 546.55189 | E31: 407.7125 | F31: 61.895823 | K31: 203.9041 | L31: 228.96151 | M31: 233.60791 | N31: 154.17987 | O31: 31.765498 | P31: 149.16892 | Q31: 58.575279 | R31: 92.844982 | S31: 181.26169 | T31: -121.0279 | U31: 41.466385 | V31: -424.63422 | W31: -610.45854 | X31: -607.89166 | Y31: -283.65147 | Z31: -488.87228 | AA31: 131.65005 | AB31: 34.043283 | AC31: 479.91702 | AD31: 259.34154 | AE31: 219.78337 | AF31: 734.66772 | AG31: 529.71957 | AH31: 146.28188 | AI31: 389.04088 | AJ31: 442.91389 | AK31: 295.28112 | AL31: 312.06202 | AM31: 340.32477 | AN31: 231.23093 | AO31: 288.16017 | AP31: -181.79529 | AQ31: 696.61924 | AR31: 1370.198 | AS31: 623.8656 | AT31: 745.19751 | AU31: 1261.2736 | AV31: 473.16872 | AW31: 102.24639 | AX31: 152.34515 | AY31: 384.4613 | AZ31: 214.158 | BA31: -188.12005 | BB31: -694.09407 | BC31: -858.31565 | BD31: -362.02228 | BE31: -977.34891 | BF31: -452.17901 | BG31: -1340.8976 | BH31: -753.966 | BI31: -899.77809 | BJ31: -795.2411 | BK31: -248.94148 | BL31: 716.46581 | BM31: 428.52503 | BN31: 35.615742 | BO31: 468.08527 | BP31: 134.52649 | BQ31: 58.248505 | BR31: 233.89975 | BS31: 211.48794 | BT31: 122.55972 | BU31: 122.03806 | BV31: 121.57899
A33: Adjusted Diluted EPS, $/share | F33: 1.0163528 | G33: 0.055335274 | H33: 0.48635386 | I33: 0.31707629 | J33: 0.8276917 | K33: 1.709717 | L33: 0.17537139 | M33: 0.67128539 | N33: 0.49010902 | O33: 1.017222 | P33: 2.3595994 | Q33: 0.2345583 | R33: 0.85271463 | S33: 0.65394031 | T33: 0.97506055 | U33: 2.7160754 | V33: -0.050901643 | W33: 0.4387012 | X33: 0.19593686 | Y33: 0.68115811 | Z33: 1.2654043 | AA33: 0.047361201 | AB33: 0.64879713 | AC33: 1.0377463 | AD33: 1.6863051 | AE33: 3.0492382 | AF33: 1.212276 | AG33: 2.0125687 | AH33: 1.5965385 | AI33: 2.9168145 | AJ33: 7.804062 | AK33: 1.8482251 | AL33: 3.1996793 | AM33: 2.7875311 | AN33: 3.7158508 | AO33: 11.659361 | AP33: 1.2683022 | AQ33: 4.9046141 | AR33: 6.1965904 | AS33: 5.0670986 | AT33: 17.829649 | AU33: 4.8900846 | AV33: 8.4843377 | AW33: 7.0315687 | AX33: 5.6632401 | AY33: 26.12108 | AZ33: 6.6260853 | BA33: 6.1160517 | BB33: 4.2551045 | BC33: 2.8824524 | BD33: 20.062481 | BE33: 2.212408 | BF33: 3.9266444 | BG33: -0.42451519 | BH33: 0.72285549 | BI33: 6.8696863 | BJ33: -0.26183576 | BK33: 3.5653928 | BL33: 2.6272311 | BM33: 2.0429248 | BN33: 7.9952171 | BO33: 1.6813606 | BP33: 4.9503245 | BQ33: 3.5729358 | BR33: 3.2976647 | BS33: 13.502459 | BT33: 16.779161 | BU33: 19.824705 | BV33: 22.802822
A34: Consensus Estimates - Adjusted Earnings Per Share - WAD | BJ34: N/A | BK34: N/A | BL34: N/A | BM34: N/A | BN34: N/A | BO34: N/A | BP34: N/A | BQ34: N/A | BR34: N/A | BS34: N/A | BT34: N/A | BU34: N/A | BV34: N/A
A35: Y/Y Adjusted diluted EPS growth, % | K35: 0.68220814 | L35: 2.1692512 | M35: 0.3802407 | N35: 0.54571323 | O35: 0.22898655 | P35: 0.38011109 | Q35: 0.33749469 | R35: 0.27027139 | S35: 0.33427519 | T35: -0.04144761 | U35: 0.15107479 | V35: -1.2170106 | W35: -0.48552402 | X35: -0.70037501 | Y35: -0.30141969 | Z35: -0.5341056 | AA35: 1.9304454 | AB35: 0.4789044 | AC35: 4.2963303 | AD35: 1.4756442 | AE35: 1.4096948 | AF35: 24.596395 | AG35: 2.102 | AH35: 0.53846707 | AI35: 0.72970746 | AJ35: 1.5593481 | AK35: 0.524591 | AL35: 0.58984852 | AM35: 0.74598419 | AN35: 0.27394141 | AO35: 0.49401179 | AP35: -0.31377286 | AQ35: 0.53284552 | AR35: 1.2229673 | AS35: 0.36364425 | AT35: 0.52921329 | AU35: 2.8556147 | AV35: 0.72986854 | AW35: 0.13474803 | AX35: 0.11764949 | AY35: 0.46503612 | AZ35: 0.35500422 | BA35: -0.27913623 | BB35: -0.39485701 | BC35: -0.49102416 | BD35: -0.2319429 | BE35: -0.66610632 | BF35: -0.35797724 | BG35: -1.0997661 | BH35: -0.74922205 | BI35: -0.65758541 | BJ35: -1.1183488 | BK35: -0.092000074 | BL35: 7.18878 | BM35: 1.8261871 | BN35: 0.1638402 | BO35: 7.4214322 | BP35: 0.38843736 | BQ35: 0.3599625 | BR35: 0.61418799 | BS35: 0.68881709 | BT35: 0.24267441 | BU35: 0.18150753 | BV35: 0.15022254
A37: Segmented Results - RH Segment
A38: Segmented Results - RH Segment Revenue Forecasting (FS)
A39: Design Galleries - BoP, # of stores | G39: 3 | H39: 5 | I39: 5 | J39: 5 | K39: 3 | L39: 5 | M39: 5 | N39: 6 | O39: 6 | P39: 5 | Q39: 7 | R39: 7 | S39: 7 | T39: 9 | U39: 7 | V39: 10 | W39: 10 | X39: 10 | Y39: 13 | Z39: 10 | AA39: 14 | AB39: 14 | AC39: 14 | AD39: 15 | AE39: 14 | AF39: 16 | AG39: 17 | AH39: 18 | AI39: 20 | AJ39: 16 | AK39: 20 | AL39: 20 | AM39: 20 | AN39: 21 | AO39: 20 | AP39: 22 | AQ39: 22 | AR39: 24 | AS39: 24 | AT39: 22 | AU39: 24 | AV39: 24 | AW39: 25 | AX39: 26 | AY39: 24 | AZ39: 27 | BA39: 27 | BB39: 28 | BC39: 28 | BD39: 27 | BE39: 28 | BF39: 27 | BG39: 28 | BH39: 28 | BI39: 28 | BJ39: 31 | BK39: 33 | BL39: 35 | BM39: 37 | BN39: 31 | BO39: 38 | BP39: 39 | BQ39: 40 | BR39: 41 | BS39: 38 | BT39: 41 | BU39: 42 | BV39: 42
A40: England Design Galleries opened, # of stores | O40: 0 | T40: 0 | Y40: 0 | AD40: 0 | AI40: 0 | AN40: 0 | AS40: 0 | AX40: 0 | BC40: 0 | BF40: 1 | BH40: 0 | BI40: 1
A41: Munich Design Galleries opened, # of stores | O41: 0 | T41: 0 | Y41: 0 | AD41: 0 | AI41: 0 | AN41: 0 | AS41: 0 | AX41: 0 | BC41: 0 | BH41: 1 | BI41: 1
A42: Düsseldorf Design Galleries opened, # of stores | O42: 0 | T42: 0 | Y42: 0 | AD42: 0 | AI42: 0 | AN42: 0 | AS42: 0 | AX42: 0 | BC42: 0 | BH42: 1 | BI42: 1
A43: Indianapolis Design Galleries opened, # of stores | O43: 0 | T43: 0 | Y43: 0 | AD43: 0 | AI43: 0 | AN43: 0 | AS43: 0 | AX43: 0 | BC43: 0 | BH43: 1 | BI43: 1
A44: San Francisco Design Galleries opened, # of stores | O44: 0 | T44: 0 | Y44: 0 | AD44: 0 | AI44: 0 | AN44: 0 | AS44: 0 | AX44: 0 | BA44: 1 | BC44: 0 | BD44: 1 | BH44: 0
A45: Dallas Design Galleries opened, # of stores | O45: 0 | T45: 0 | Y45: 0 | AD45: 0 | AI45: 0 | AN45: 0 | AS45: 0 | AV45: 1 | AX45: 0 | AY45: 1 | BC45: 0 | BH45: 0
A46: Oak Brook Design Galleries opened, # of stores | O46: 0 | T46: 0 | Y46: 0 | AD46: 0 | AI46: 0 | AN46: 0 | AS46: 0 | AW46: 1 | AX46: 0 | AY46: 1 | BC46: 0 | BH46: 0
A47: Jacksonville Design Galleries opened, # of stores | O47: 0 | T47: 0 | Y47: 0 | AD47: 0 | AI47: 0 | AN47: 0 | AS47: 0 | AX47: 1 | AY47: 1 | BC47: 0 | BH47: 0
A48: Marin Design Galleries opened, # of stores | O48: 0 | T48: 0 | Y48: 0 | AD48: 0 | AI48: 0 | AN48: 0 | AQ48: 1 | AS48: 0 | AT48: 1 | AX48: 0 | BC48: 0 | BH48: 0
A49: Charlotte Design Galleries opened, # of stores | O49: 0 | T49: 0 | Y49: 0 | AD49: 0 | AI49: 0 | AN49: 0 | AQ49: 1 | AS49: 0 | AT49: 1 | AX49: 0 | BC49: 0 | BH49: 0
A50: Minneapolis Design Galleries opened, # of stores | O50: 0 | T50: 0 | Y50: 0 | AD50: 0 | AI50: 0 | AM50: 1 | AN50: 0 | AO50: 1 | AS50: 0 | AX50: 0 | BC50: 0 | BH50: 0
A51: Columbus Design Galleries opened, # of stores | O51: 0 | T51: 0 | Y51: 0 | AD51: 0 | AI51: 0 | AN51: 1 | AO51: 1 | AS51: 0 | AX51: 0 | BC51: 0 | BH51: 0
A52: Portland Design Galleries opened, # of stores | O52: 0 | T52: 0 | Y52: 0 | AD52: 0 | AF52: 1 | AI52: 0 | AJ52: 1 | AN52: 0 | AS52: 0 | AX52: 0 | BC52: 0 | BH52: 0
A53: Nashville Design Galleries opened, # of stores | O53: 0 | T53: 0 | Y53: 0 | AD53: 0 | AG53: 1 | AI53: 0 | AJ53: 1 | AN53: 0 | AS53: 0 | AX53: 0 | BC53: 0 | BH53: 0
A54: New York Design Galleries opened, # of stores | O54: 0 | T54: 0 | Y54: 0 | AD54: 0 | AH54: 1 | AI54: 0 | AJ54: 1 | AN54: 0 | AS54: 0 | AX54: 0 | BC54: 0 | BH54: 0
A55: Yountville Design Galleries opened, # of stores | O55: 0 | T55: 0 | Y55: 0 | AD55: 0 | AH55: 1 | AI55: 0 | AJ55: 1 | AN55: 0 | AS55: 0 | AX55: 0 | BC55: 0 | BH55: 0
A56: Toronto (Yorkdale) Design Galleries opened, # of stores | O56: 0 | T56: 0 | Y56: 0 | AC56: 1 | AD56: 0 | AE56: 1 | AI56: 0 | AN56: 0 | AS56: 0 | AX56: 0 | BC56: 0 | BH56: 0
A57: West Palm Design Galleries opened, # of stores | O57: 0 | T57: 0 | Y57: 0 | AD57: 1 | AE57: 1 | AI57: 0 | AN57: 0 | AS57: 0 | AX57: 0 | BC57: 0 | BH57: 0
A58: Leawood Design Galleries opened, # of stores | O58: 0 | T58: 0 | X58: 1 | Y58: 0 | Z58: 1 | AD58: 0 | AI58: 0 | AN58: 0 | AS58: 0 | AX58: 0 | BC58: 0 | BH58: 0
A59: Austin Design Galleries opened, # of stores | O59: 0 | T59: 0 | X59: 1 | Y59: 0 | Z59: 1 | AD59: 0 | AI59: 0 | AN59: 0 | AS59: 0 | AX59: 0 | BC59: 0 | BH59: 0
A60: Las Vegas Design Galleries opened, # of stores | O60: 0 | T60: 0 | X60: 1 | Y60: 0 | Z60: 1 | AD60: 0 | AI60: 0 | AN60: 0 | AS60: 0 | AX60: 0 | BC60: 0 | BH60: 0
A61: Seattle Design Galleries opened, # of stores | O61: 0 | T61: 0 | Y61: 1 | Z61: 1 | AD61: 0 | AI61: 0 | AN61: 0 | AS61: 0 | AX61: 0 | BC61: 0 | BH61: 0
A62: Chicago Design Galleries opened, # of stores | O62: 0 | S62: 1 | T62: 0 | U62: 1 | Y62: 0 | AD62: 0 | AI62: 0 | AN62: 0 | AS62: 0 | AX62: 0 | BC62: 0 | BH62: 0
A63: Denver Design Galleries opened, # of stores | O63: 0 | S63: 1 | T63: 0 | U63: 1 | Y63: 0 | AD63: 0 | AI63: 0 | AN63: 0 | AS63: 0 | AX63: 0 | BC63: 0 | BH63: 0
A64: Tampa Design Galleries opened, # of stores | O64: 0 | T64: 1 | U64: 1 | Y64: 0 | AD64: 0 | AI64: 0 | AN64: 0 | AS64: 0 | AX64: 0 | BC64: 0 | BH64: 0
A65: Greenwich Design Galleries opened, # of stores | M65: 1 | O65: 0 | P65: 1 | T65: 0 | Y65: 0 | AD65: 0 | AI65: 0 | AN65: 0 | AS65: 0 | AX65: 0 | BC65: 0 | BH65: 0
A66: Los Angeles Design Galleries opened, # of stores | N66: 1 | O66: 0 | P66: 1 | T66: 0 | Y66: 0 | AD66: 0 | AI66: 0 | AN66: 0 | AS66: 0 | AX66: 0 | BC66: 0 | BH66: 0
A67: Atlanta Design Galleries opened, # of stores | O67: 1 | P67: 1 | T67: 0 | Y67: 0 | AD67: 0 | AI67: 0 | AN67: 0 | AS67: 0 | AX67: 0 | BC67: 0 | BH67: 0
A68: Design Galleries opened, # of stores | L68: 0 | M68: 1 | N68: 1 | O68: 1 | P68: 3 | Q68: 0 | R68: 0 | S68: 2 | T68: 1 | U68: 3 | V68: 0 | W68: 0 | X68: 3 | Y68: 1 | Z68: 4 | AA68: 0 | AB68: 0 | AC68: 1 | AD68: 1 | AE68: 2 | AF68: 1 | AG68: 1 | AH68: 2 | AI68: 0 | AJ68: 4 | AK68: 0 | AL68: 0 | AM68: 1 | AN68: 1 | AO68: 2 | AP68: 0 | AQ68: 2 | AR68: 0 | AS68: 0 | AT68: 2 | AU68: 0 | AV68: 1 | AW68: 1 | AX68: 1 | AY68: 3 | AZ68: 0 | BA68: 1 | BB68: 0 | BC68: 0 | BD68: 1 | BE68: 0 | BF68: 1 | BG68: 0 | BH68: 3 | BI68: 4 | BJ68: 2 | BK68: 2 | BL68: 2 | BM68: 1 | BN68: 7 | BO68: 1 | BP68: 1 | BQ68: 1 | BR68: 0 | BS68: 3 | BT68: 1 | BU68: 0 | BV68: 0
A69: Indianapolis Design Galleries closed, # of stores | O69: 0 | T69: 0 | Y69: 0 | AD69: 0 | AI69: 0 | AN69: 0 | AS69: 0 | AX69: 0 | BC69: 0 | BE69: -1 | BH69: 0 | BI69: -1
A70: Los Angeles Design Galleries closed, # of stores | N70: -1 | O70: 0 | P70: -1 | T70: 0 | Y70: 0 | AD70: 0 | AI70: 0 | AN70: 0 | AS70: 0 | AX70: 0 | BC70: 0 | BH70: 0
A71: Design Galleries closed, # of stores | L71: 0 | M71: 0 | N71: -1 | O71: 0 | P71: -1 | Q71: 0 | R71: 0 | S71: 0 | T71: 0 | U71: 0 | V71: 0 | W71: 0 | X71: 0 | Y71: 0 | Z71: 0 | AA71: 0 | AB71: 0 | AC71: 0 | AD71: 0 | AE71: 0 | AF71: 0 | AG71: 0 | AH71: 0 | AI71: 0 | AJ71: 0 | AK71: 0 | AL71: 0 | AM71: 0 | AN71: 0 | AO71: 0 | AP71: 0 | AQ71: 0 | AR71: 0 | AS71: 0 | AT71: 0 | AU71: 0 | AV71: 0 | AW71: 0 | AX71: 0 | AY71: 0 | AZ71: 0 | BA71: 0 | BB71: 0 | BC71: 0 | BD71: 0 | BE71: -1 | BF71: 0 | BG71: 0 | BH71: 0 | BI71: -1 | BJ71: 0 | BK71: 0 | BL71: 0 | BM71: 0 | BN71: 0 | BO71: 0 | BP71: 0 | BQ71: 0 | BR71: 0 | BS71: 0 | BT71: 0 | BU71: 0 | BV71: 0
A72: Design Galleries - EoP, # of stores | F72: 3 | G72: 5 | H72: 5 | I72: 5 | J72: 5 | K72: 5 | L72: 5 | M72: 6 | N72: 6 | O72: 7 | P72: 7 | Q72: 7 | R72: 7 | S72: 9 | T72: 10 | U72: 10 | V72: 10 | W72: 10 | X72: 13 | Y72: 14 | Z72: 14 | AA72: 14 | AB72: 14 | AC72: 15 | AD72: 16 | AE72: 16 | AF72: 17 | AG72: 18 | AH72: 20 | AI72: 20 | AJ72: 20 | AK72: 20 | AL72: 20 | AM72: 21 | AN72: 22 | AO72: 22 | AP72: 22 | AQ72: 24 | AR72: 24 | AS72: 24 | AT72: 24 | AU72: 24 | AV72: 25 | AW72: 26 | AX72: 27 | AY72: 27 | AZ72: 27 | BA72: 28 | BB72: 28 | BC72: 28 | BD72: 28 | BE72: 27 | BF72: 28 | BG72: 28 | BH72: 31 | BI72: 31 | BJ72: 33 | BK72: 35 | BL72: 37 | BM72: 38 | BN72: 38 | BO72: 39 | BP72: 40 | BQ72: 41 | BR72: 41 | BS72: 41 | BT72: 42 | BU72: 42 | BV72: 42
A73: Design Galleries - Average, # of stores | G73: 4 | H73: 5 | I73: 5 | J73: 5 | K73: 4.75 | L73: 5 | M73: 5.5 | N73: 6 | O73: 6.5 | P73: 5.75 | Q73: 7 | R73: 7 | S73: 8 | T73: 9.5 | U73: 7.875 | V73: 10 | W73: 10 | X73: 11.5 | Y73: 13.5 | Z73: 11.25 | AA73: 14 | AB73: 14 | AC73: 14.5 | AD73: 15.5 | AE73: 14.518868 | AF73: 16.5 | AG73: 17.5 | AH73: 19 | AI73: 20 | AJ73: 18.25 | AK73: 20 | AL73: 20 | AM73: 20.5 | AN73: 21.5 | AO73: 20.5 | AP73: 22 | AQ73: 23 | AR73: 24 | AS73: 24 | AT73: 23.25 | AU73: 24 | AV73: 24.5 | AW73: 25.5 | AX73: 26.5 | AY73: 25.125 | AZ73: 27 | BA73: 27.5 | BB73: 28 | BC73: 28 | BD73: 27.625 | BE73: 27.5 | BF73: 27.5 | BG73: 28 | BH73: 29.5 | BI73: 28.150943 | BJ73: 32 | BK73: 34 | BL73: 36 | BM73: 37.5 | BN73: 34.875 | BO73: 38.5 | BP73: 39.5 | BQ73: 40.5 | BR73: 41 | BS73: 39.875 | BT73: 41.5 | BU73: 42 | BV73: 42
A75: Design Galleries Leased Selling Square Footage - BoP, 000s sq ft | L75: 88.5 | M75: 88.5 | N75: 102.5 | O75: 113.9 | P75: 88.5 | Q75: 160 | R75: 160 | S75: 160 | T75: 251.2 | U75: 160 | V75: 287.3 | W75: 287.3 | X75: 287.3 | Y75: 408 | Z75: 287.3 | AA75: 443.7 | AB75: 443.7 | AC75: 443.7 | AD75: 487 | AE75: 443.7 | AF75: 533.5 | AG75: 559.5 | AH75: 605.1 | AI75: 662.3 | AJ75: 533.5 | AK75: 662.3 | AL75: 662.3 | AM75: 662.3 | AN75: 695.2 | AO75: 662.3 | AP75: 728.2 | AQ75: 728.2 | AR75: 793.5 | AS75: 793.5 | AT75: 728.2 | AU75: 792 | AV75: 792 | AW75: 830 | AX75: 867.7 | AY75: 792 | AZ75: 904.5 | BA75: 904.5 | BB75: 946.6 | BC75: 946.6 | BD75: 904.5 | BE75: 946.4 | BF75: 933.4 | BG75: 968.5 | BH75: 968.5 | BI75: 946.4 | BJ75: 1035.4 | BK75: 1115.56 | BL75: 1196.6916 | BM75: 1278.7505 | BN75: 1035.4 | BO75: 1320.2235 | BP75: 1361.9147 | BQ75: 1403.8198 | BR75: 1445.9344 | BS75: 1320.2235 | BT75: 1445.9344 | BU75: 1488.2544 | BV75: 1488.2544
A76: England Design Galleries leased selling square footage opened, 000s sq ft | O76: 0 | T76: 0 | Y76: 0 | AD76: 0 | AI76: 0 | AN76: 0 | AS76: 0 | AX76: 0 | BC76: 0 | BF76: 35.1 | BH76: 0 | BI76: 35.1
A77: Munich Design Galleries leased selling square footage opened, 000s sq ft | BH77: 26.4 | BI77: 26.4
A78: Düsseldorf Design Galleries leased selling square footage opened, 000s sq ft | BH78: 19.6 | BI78: 19.6
A79: Indianapolis Design Galleries leased selling square footage opened, 000s sq ft | BH79: 20.6 | BI79: 20.6
A80: San Francisco Design Galleries leased selling square footage opened, 000s sq ft | O80: 0 | T80: 0 | Y80: 0 | AD80: 0 | AI80: 0 | AN80: 0 | AS80: 0 | AX80: 0 | BA80: 42.1 | BC80: 0 | BD80: 42.1 | BH80: 0
A81: Dallas Design Galleries leased selling square footage opened, 000s sq ft | O81: 0 | T81: 0 | Y81: 0 | AD81: 0 | AI81: 0 | AN81: 0 | AS81: 0 | AV81: 38 | AX81: 0 | AY81: 38 | BC81: 0 | BH81: 0
A82: Oak Brook Design Galleries leased selling square footage opened, 000s sq ft | O82: 0 | T82: 0 | Y82: 0 | AD82: 0 | AI82: 0 | AN82: 0 | AS82: 0 | AW82: 37.7 | AX82: 0 | AY82: 37.7 | BC82: 0 | BH82: 0
A83: Jacksonville Design Galleries leased selling square footage opened, 000s sq ft | O83: 0 | T83: 0 | Y83: 0 | AD83: 0 | AI83: 0 | AN83: 0 | AS83: 0 | AX83: 37.7 | AY83: 37.7 | BC83: 0 | BH83: 0
A84: Marin Design Galleries leased selling square footage opened, 000s sq ft | O84: 0 | T84: 0 | Y84: 0 | AD84: 0 | AI84: 0 | AN84: 0 | AQ84: 32.9 | AS84: 0 | AT84: 32.9 | AX84: 0 | BC84: 0 | BH84: 0
A85: Charlotte Design Galleries leased selling square footage opened, 000s sq ft | O85: 0 | T85: 0 | Y85: 0 | AD85: 0 | AI85: 0 | AN85: 0 | AQ85: 32.4 | AS85: 0 | AT85: 32.4 | AX85: 0 | BC85: 0 | BH85: 0
A86: Minneapolis Design Galleries leased selling square footage opened, 000s sq ft | O86: 0 | T86: 0 | Y86: 0 | AD86: 0 | AI86: 0 | AM86: 32.9 | AN86: 0 | AO86: 32.9 | AS86: 0 | AX86: 0 | BC86: 0 | BH86: 0
A87: Columbus Design Galleries leased selling square footage opened, 000s sq ft | O87: 0 | T87: 0 | Y87: 0 | AD87: 0 | AI87: 0 | AN87: 33 | AO87: 33 | AS87: 0 | AX87: 0 | BC87: 0 | BH87: 0
A88: Portland Design Galleries leased selling square footage opened, 000s sq ft | O88: 0 | T88: 0 | Y88: 0 | AD88: 0 | AF88: 26 | AI88: 0 | AJ88: 26 | AN88: 0 | AS88: 0 | AX88: 0 | BC88: 0 | BH88: 0
A89: Nashville Design Galleries leased selling square footage opened, 000s sq ft | O89: 0 | T89: 0 | Y89: 0 | AD89: 0 | AG89: 45.6 | AI89: 0 | AJ89: 45.6 | AN89: 0 | AS89: 0 | AX89: 0 | BC89: 0 | BH89: 0
A90: New York Design Galleries leased selling square footage opened, 000s sq ft | O90: 0 | T90: 0 | Y90: 0 | AD90: 0 | AH90: 50.5 | AI90: 0 | AJ90: 50.5 | AN90: 0 | AS90: 0 | AX90: 0 | BC90: 0 | BH90: 0
A91: Yountville Design Galleries leased selling square footage opened, 000s sq ft | O91: 0 | T91: 0 | Y91: 0 | AD91: 0 | AH91: 6.7 | AI91: 0 | AJ91: 6.7 | AN91: 0 | AS91: 0 | AX91: 0 | BC91: 0 | BH91: 0
A92: Toronto (Yorkdale) Design Galleries leased selling square footage opened, 000s sq ft | O92: 0 | T92: 0 | Y92: 0 | AC92: 43.3 | AD92: 0 | AE92: 43.3 | AI92: 0 | AN92: 0 | AS92: 0 | AX92: 0 | BC92: 0 | BH92: 0
A93: West Palm Design Galleries leased selling square footage opened, 000s sq ft | O93: 0 | T93: 0 | Y93: 0 | AD93: 46.5 | AE93: 46.5 | AI93: 0 | AN93: 0 | AS93: 0 | AX93: 0 | BC93: 0 | BH93: 0
A94: Leawood Design Galleries leased selling square footage opened, 000s sq ft | O94: 0 | T94: 0 | X94: 33.5 | Y94: 0 | Z94: 33.5 | AD94: 0 | AI94: 0 | AN94: 0 | AS94: 0 | AX94: 0 | BC94: 0 | BH94: 0
A95: Austin Design Galleries leased selling square footage opened, 000s sq ft | O95: 0 | T95: 0 | X95: 39.6 | Y95: 0 | Z95: 39.6 | AD95: 0 | AI95: 0 | AN95: 0 | AS95: 0 | AX95: 0 | BC95: 0 | BH95: 0
A96: Las Vegas Design Galleries leased selling square footage opened, 000s sq ft | O96: 0 | T96: 0 | X96: 47.6 | Y96: 0 | Z96: 47.6 | AD96: 0 | AI96: 0 | AN96: 0 | AS96: 0 | AX96: 0 | BC96: 0 | BH96: 0
A97: Seattle Design Galleries leased selling square footage opened, 000s sq ft | O97: 0 | T97: 0 | Y97: 35.7 | Z97: 35.7 | AD97: 0 | AI97: 0 | AN97: 0 | AS97: 0 | AX97: 0 | BC97: 0 | BH97: 0
A98: Chicago Design Galleries leased selling square footage opened, 000s sq ft | O98: 0 | S98: 44.8 | T98: 0 | U98: 44.8 | Y98: 0 | AD98: 0 | AI98: 0 | AN98: 0 | AS98: 0 | AX98: 0 | BC98: 0 | BH98: 0
A99: Denver Design Galleries leased selling square footage opened, 000s sq ft | O99: 0 | S99: 46.4 | T99: 0 | U99: 46.4 | Y99: 0 | AD99: 0 | AI99: 0 | AN99: 0 | AS99: 0 | AX99: 0 | BC99: 0 | BH99: 0
A100: Tampa Design Galleries leased selling square footage opened, 000s sq ft | O100: 0 | T100: 36.1 | U100: 36.1 | Y100: 0 | AD100: 0 | AI100: 0 | AN100: 0 | AS100: 0 | AX100: 0 | BC100: 0 | BH100: 0
A101: Greenwich Design Galleries leased selling square footage opened, 000s sq ft | M101: 14 | O101: 0 | P101: 14 | T101: 0 | Y101: 0 | AD101: 0 | AI101: 0 | AN101: 0 | AS101: 0 | AX101: 0 | BC101: 0 | BH101: 0
A102: Los Angeles Design Galleries leased selling square footage opened, 000s sq ft | N102: 25.2 | O102: 0 | P102: 25.2 | T102: 0 | Y102: 0 | AD102: 0 | AI102: 0 | AN102: 0 | AS102: 0 | AX102: 0 | BC102: 0 | BH102: 0
A103: Atlanta Design Galleries leased selling square footage opened, 000s sq ft | O103: 46.1 | P103: 46.1 | T103: 0 | Y103: 0 | AD103: 0 | AI103: 0 | AN103: 0 | AS103: 0 | AX103: 0 | BC103: 0 | BH103: 0
A104: Design Galleries leased selling square footage opened, 000s sq ft | L104: 0 | M104: 14 | N104: 25.2 | O104: 46.1 | P104: 85.3 | Q104: 0 | R104: 0 | S104: 91.2 | T104: 36.1 | U104: 127.3 | V104: 0 | W104: 0 | X104: 120.7 | Y104: 35.7 | Z104: 156.4 | AA104: 0 | AB104: 0 | AC104: 43.3 | AD104: 46.5 | AE104: 89.8 | AF104: 26 | AG104: 45.6 | AH104: 57.2 | AI104: 0 | AJ104: 128.8 | AK104: 0 | AL104: 0 | AM104: 32.9 | AN104: 33 | AO104: 65.9 | AP104: 0 | AQ104: 65.3 | AR104: 0 | AS104: 0 | AT104: 65.3 | AU104: 0 | AV104: 38 | AW104: 37.7 | AX104: 37.7 | AY104: 113.4 | AZ104: 0 | BA104: 42.1 | BB104: 0 | BC104: 0 | BD104: 42.1 | BE104: 0 | BF104: 35.1 | BG104: 0 | BH104: 66.6 | BI104: 101.7 | BJ104: 80.16 | BK104: 81.131636 | BL104: 82.058855 | BM104: 41.472989 | BN104: 284.82348 | BO104: 41.691268 | BP104: 41.905069 | BQ104: 42.114595 | BR104: 0 | BS104: 125.71093 | BT104: 42.320032 | BU104: 0 | BV104: 0
A105: Indianapolis Design Galleries leased selling square footage closed, 000s sq ft | O105: 0 | T105: 0 | Y105: 0 | AD105: 0 | AI105: 0 | AN105: 0 | AS105: 0 | AX105: 0 | BC105: 0 | BE105: -13 | BI105: -13
A106: Los Angeles Design Galleries leased selling square footage closed, 000s sq ft | N106: -13.8 | O106: 0 | P106: -13.8 | T106: 0 | Y106: 0 | AD106: 0 | AI106: 0 | AN106: 0 | AS106: 0 | AX106: 0 | BC106: 0 | BH106: 0
...

Sheet WSM
A1: Williams Sonoma Inc.
A2: =CHOOSE(MO.DataSourceIndex,MO.Ticker.Bloomberg,MO.Ticker.CapIQ,MO.Ticker.FactSet,MO.Ticker.Thomson) -> WSM US | C2: 39845
A3: =HP.TradeCurrency -> USD | B3: =IF(MO.RealTime="OFF",MO.LastPriceHardcoded,MO.LastPriceFormula) -> 292.52 | C3: =C4-C2 -> 364 | D3: =D4-C4 -> 364 | E3: =E4-D4 -> 364 | F3: =F4-E4 -> 371 | G3: =G4-F4 -> 91 | H3: =H4-G4 -> 91 | I3: =I4-H4 -> 91 | J3: =J4-I4 -> 91 | K3: =K4-F4 -> 364 | L3: =L4-K4 -> 91 | M3: =M4-L4 -> 91 | N3: =N4-M4 -> 91 | O3: =O4-N4 -> 91 | P3: =P4-K4 -> 364 | Q3: =Q4-P4 -> 91 | R3: =R4-Q4 -> 91 | S3: =S4-R4 -> 91 | T3: =T4-S4 -> 91 | U3: =U4-P4 -> 364 | V3: =V4-U4 -> 91 | W3: =W4-V4 -> 91 | X3: =X4-W4 -> 91 | Y3: =Y4-X4 -> 91 | Z3: =Z4-U4 -> 364 | AA3: =AA4-Z4 -> 91 | AB3: =AB4-AA4 -> 91 | AC3: =AC4-AB4 -> 91 | AD3: =AD4-AC4 -> 91 | AE3: =AE4-Z4 -> 364 | AF3: =AF4-AE4 -> 91 | AG3: =AG4-AF4 -> 91 | AH3: =AH4-AG4 -> 91 | AI3: =AI4-AH4 -> 98 | AJ3: =AJ4-AE4 -> 371 | AK3: =AK4-AJ4 -> 91 | AL3: =AL4-AK4 -> 91 | AM3: =AM4-AL4 -> 91 | AN3: =AN4-AM4 -> 91 | AO3: =AO4-AJ4 -> 364 | AP3: =AP4-AO4 -> 91 | AQ3: =AQ4-AP4 -> 91 | AR3: =AR4-AQ4 -> 91 | AS3: =AS4-AR4 -> 91 | AT3: =AT4-AO4 -> 364 | AU3: =AU4-AT4 -> 91 | AV3: =AV4-AU4 -> 91 | AW3: =AW4-AV4 -> 91 | AX3: =AX4-AW4 -> 91 | AY3: =AY4-AT4 -> 364 | AZ3: =AZ4-AY4 -> 91 | BA3: =BA4-AZ4 -> 91 | BB3: =BB4-BA4 -> 91 | BC3: =BC4-BB4 -> 91 | BD3: =BD4-AY4 -> 364 | BE3: =BE4-BD4 -> 91 | BF3: =BF4-BE4 -> 91 | BG3: =BG4-BF4 -> 91 | BH3: =BH4-BG4 -> 91 | BI3: =BI4-BD4 -> 364 | BJ3: =BJ4-BI4 -> 91 | BK3: 91 | BL3: 91 | BM3: 98 | BN3: =BN4-BI4 -> 371 | BO3: 91 | BP3: 91 | BQ3: 91 | BR3: 91 | BS3: =BS4-BN4 -> 364 | BT3: 364 | BU3: 364 | BV3: 364
A4: =FP.DataSourceName -> Bloomberg | B4: =IF(AND(MO.RealTimeStockPriceToggle,MO.LastPriceFormula<>"N/A"),"ON","OFF") -> OFF | C4: 40209 | D4: 40573 | E4: 40937 | F4: 41308 | G4: 41399 | H4: 41490 | I4: 41581 | J4: =K4 -> 41672 | K4: 41672 | L4: 41763 | M4: 41854 | N4: 41945 | O4: =P4 -> 42036 | P4: 42036 | Q4: 42127 | R4: 42218 | S4: 42309 | T4: =U4 -> 42400 | U4: 42400 | V4: 42491 | W4: 42582 | X4: 42673 | Y4: =Z4 -> 42764 | Z4: 42764 | AA4: 42855 | AB4: 42946 | AC4: 43037 | AD4: =AE4 -> 43128 | AE4: 43128 | AF4: 43219 | AG4: 43310 | AH4: 43401 | AI4: =AJ4 -> 43499 | AJ4: 43499 | AK4: 43590 | AL4: 43681 | AM4: 43772 | AN4: =AO4 -> 43863 | AO4: 43863 | AP4: 43954 | AQ4: 44045 | AR4: 44136 | AS4: =AT4 -> 44227 | AT4: 44227 | AU4: 44318 | AV4: 44409 | AW4: 44500 | AX4: =AY4 -> 44591 | AY4: 44591 | AZ4: 44682 | BA4: 44773 | BB4: 44864 | BC4: =BD4 -> 44955 | BD4: 44955 | BE4: 45046 | BF4: 45137 | BG4: 45228 | BH4: =BI4 -> 45319 | BI4: 45319 | BJ4: 45410 | BK4: =BJ4+BK3 -> 45501 | BL4: =BK4+BL3 -> 45592 | BM4: =BL4+BM3 -> 45690 | BN4: =BM4 -> 45690 | BO4: =BN4+BO3 -> 45781 | BP4: =BO4+BP3 -> 45872 | BQ4: =BP4+BQ3 -> 45963 | BR4: =BQ4+BR3 -> 46054 | BS4: =BR4 -> 46054 | BT4: =BS4+BT3 -> 46418 | BU4: =BT4+BU3 -> 46782 | BV4: =BU4+BV3 -> 47146
A5: =MO.ReportCurrency -> USD | C5: FY2009 | D5: =CONCATENATE("FY",RIGHT(C5,4)+1) -> FY2010 | E5: =CONCATENATE("FY",RIGHT(D5,4)+1) -> FY2011 | F5: =CONCATENATE("FY",RIGHT(E5,4)+1) -> FY2012 | G5: =CONCATENATE("Q1","-",RIGHT(F5,4)+1) -> Q1-2013 | H5: =CONCATENATE("Q2","-",RIGHT(G5,4)) -> Q2-2013 | I5: =CONCATENATE("Q3","-",RIGHT(H5,4)) -> Q3-2013 | J5: =CONCATENATE("Q4","-",RIGHT(I5,4)) -> Q4-2013 | K5: =CONCATENATE("FY",RIGHT(F5,4)+1) -> FY2013 | L5: =CONCATENATE("Q1","-",RIGHT(K5,4)+1) -> Q1-2014 | M5: =CONCATENATE("Q2","-",RIGHT(L5,4)) -> Q2-2014 | N5: =CONCATENATE("Q3","-",RIGHT(M5,4)) -> Q3-2014 | O5: =CONCATENATE("Q4","-",RIGHT(N5,4)) -> Q4-2014 | P5: =CONCATENATE("FY",RIGHT(K5,4)+1) -> FY2014 | Q5: =CONCATENATE("Q1","-",RIGHT(P5,4)+1) -> Q1-2015 | R5: =CONCATENATE("Q2","-",RIGHT(Q5,4)) -> Q2-2015 | S5: =CONCATENATE("Q3","-",RIGHT(R5,4)) -> Q3-2015 | T5: =CONCATENATE("Q4","-",RIGHT(S5,4)) -> Q4-2015 | U5: =CONCATENATE("FY",RIGHT(P5,4)+1) -> FY2015 | V5: =CONCATENATE("Q1","-",RIGHT(U5,4)+1) -> Q1-2016 | W5: =CONCATENATE("Q2","-",RIGHT(V5,4)) -> Q2-2016 | X5: =CONCATENATE("Q3","-",RIGHT(W5,4)) -> Q3-2016 | Y5: =CONCATENATE("Q4","-",RIGHT(X5,4)) -> Q4-2016 | Z5: =CONCATENATE("FY",RIGHT(U5,4)+1) -> FY2016 | AA5: =CONCATENATE("Q1","-",RIGHT(Z5,4)+1) -> Q1-2017 | AB5: =CONCATENATE("Q2","-",RIGHT(AA5,4)) -> Q2-2017 | AC5: =CONCATENATE("Q3","-",RIGHT(AB5,4)) -> Q3-2017 | AD5: =CONCATENATE("Q4","-",RIGHT(AC5,4)) -> Q4-2017 | AE5: =CONCATENATE("FY",RIGHT(Z5,4)+1) -> FY2017 | AF5: =CONCATENATE("Q1","-",RIGHT(AE5,4)+1) -> Q1-2018 | AG5: =CONCATENATE("Q2","-",RIGHT(AF5,4)) -> Q2-2018 | AH5: =CONCATENATE("Q3","-",RIGHT(AG5,4)) -> Q3-2018 | AI5: =CONCATENATE("Q4","-",RIGHT(AH5,4)) -> Q4-2018 | AJ5: =CONCATENATE("FY",RIGHT(AE5,4)+1) -> FY2018 | AK5: =CONCATENATE("Q1","-",RIGHT(AJ5,4)+1) -> Q1-2019 | AL5: =CONCATENATE("Q2","-",RIGHT(AK5,4)) -> Q2-2019 | AM5: =CONCATENATE("Q3","-",RIGHT(AL5,4)) -> Q3-2019 | AN5: =CONCATENATE("Q4","-",RIGHT(AM5,4)) -> Q4-2019 | AO5: =CONCATENATE("FY",RIGHT(AJ5,4)+1) -> FY2019 | AP5: =CONCATENATE("Q1","-",RIGHT(AO5,4)+1) -> Q1-2020 | AQ5: =CONCATENATE("Q2","-",RIGHT(AP5,4)) -> Q2-2020 | AR5: =CONCATENATE("Q3","-",RIGHT(AQ5,4)) -> Q3-2020 | AS5: =CONCATENATE("Q4","-",RIGHT(AR5,4)) -> Q4-2020 | AT5: =CONCATENATE("FY",RIGHT(AO5,4)+1) -> FY2020 | AU5: =CONCATENATE("Q1","-",RIGHT(AT5,4)+1) -> Q1-2021 | AV5: =CONCATENATE("Q2","-",RIGHT(AU5,4)) -> Q2-2021 | AW5: =CONCATENATE("Q3","-",RIGHT(AV5,4)) -> Q3-2021 | AX5: =CONCATENATE("Q4","-",RIGHT(AW5,4)) -> Q4-2021 | AY5: =CONCATENATE("FY",RIGHT(AT5,4)+1) -> FY2021 | AZ5: =CONCATENATE("Q1","-",RIGHT(AY5,4)+1) -> Q1-2022 | BA5: =CONCATENATE("Q2","-",RIGHT(AZ5,4)) -> Q2-2022 | BB5: =CONCATENATE("Q3","-",RIGHT(BA5,4)) -> Q3-2022 | BC5: =CONCATENATE("Q4","-",RIGHT(BB5,4)) -> Q4-2022 | BD5: =CONCATENATE("FY",RIGHT(AY5,4)+1) -> FY2022 | BE5: =CONCATENATE("Q1","-",RIGHT(BD5,4)+1) -> Q1-2023 | BF5: =CONCATENATE("Q2","-",RIGHT(BE5,4)) -> Q2-2023 | BG5: =CONCATENATE("Q3","-",RIGHT(BF5,4)) -> Q3-2023 | BH5: =CONCATENATE("Q4","-",RIGHT(BG5,4)) -> Q4-2023 | BI5: =CONCATENATE("FY",RIGHT(BD5,4)+1) -> FY2023 | BJ5: =CONCATENATE("Q1","-",RIGHT(BI5,4)+1) -> Q1-2024 | BK5: =CONCATENATE("Q2","-",RIGHT(BJ5,4)) -> Q2-2024 | BL5: =CONCATENATE("Q3","-",RIGHT(BK5,4)) -> Q3-2024 | BM5: =CONCATENATE("Q4","-",RIGHT(BL5,4)) -> Q4-2024 | BN5: =CONCATENATE("FY",RIGHT(BI5,4)+1) -> FY2024 | BO5: =CONCATENATE("Q1","-",RIGHT(BN5,4)+1) -> Q1-2025 | BP5: =CONCATENATE("Q2","-",RIGHT(BO5,4)) -> Q2-2025 | BQ5: =CONCATENATE("Q3","-",RIGHT(BP5,4)) -> Q3-2025 | BR5: =CONCATENATE("Q4","-",RIGHT(BQ5,4)) -> Q4-2025 | BS5: =CONCATENATE("FY",RIGHT(BN5,4)+1) -> FY2025 | BT5: =CONCATENATE("FY",RIGHT(BS5,4)+1) -> FY2026 | BU5: =CONCATENATE("FY",RIGHT(BT5,4)+1) -> FY2027 | BV5: =CONCATENATE("FY",RIGHT(BU5,4)+1) -> FY2028
A6: Consolidated Summary
A7: Total Company Operated Stores - EoP, # of stores | C7: =C272 -> 610 | D7: =D272 -> 592 | E7: =E272 -> 576 | F7: =F272 -> 581 | G7: =G272 -> 587 | H7: =H272 -> 590 | I7: =I272 -> 595 | J7: =J272 -> 585 | ... BV7: =BV272 -> 459
A8: Q/Q Total company operated store growth, % | G8: =G7/F7-1 -> 0.010327022 | H8: =H7/G7-1 -> 0.0051107325 | I8: =I7/H7-1 -> 0.0084745763 | J8: =J7/I7-1 -> -0.016806723 | L8: =L7/J7-1 -> 0.0068376068 | M8: =M7/L7-1 -> 0 | N8: =N7/M7-1 -> 0.0237691 | O8: =O7/N7-1 -> -0.0033167496 | Q8: =Q7/O7-1 -> 0.003327787 | R8: =R7/Q7-1 -> 0.014925373 | S8: =S7/R7-1 -> 0.017973856 | T8: =T7/S7-1 -> -0.0080256822 | V8: =V7/T7-1 -> 0.0097087379 | W8: =W7/V7-1 -> 0.0032051282 | X8: =X7/W7-1 -> 0.014376997 | Y8: =Y7/X7-1 -> -0.0094488189 | AA8: =AA7/Y7-1 -> -0.0015898251 | AB8: =AB7/AA7-1 -> 0.011146497 | AC8: =AC7/AB7-1 -> 0.0015748031 | AD8: =AD7/AC7-1 -> -0.0078616352 | AF8: =AF7/AD7-1 -> -0.0063391442 | AG8: =AG7/AF7-1 -> 0.0079744817 | AH8: =AH7/AG7-1 -> 0.0015822785 | AI8: =AI7/AH7-1 -> -0.012638231 | AK8: =AK7/AI7-1 -> 0 | AL8: =AL7/AK7-1 -> -0.0032 | AM8: =AM7/AL7-1 -> 0.0048154093 | AN8: =AN7/AM7-1 -> -0.019169329 | AP8: =AP7/AN7-1 -> 0.003257329 | AQ8: =AQ7/AP7-1 -> -0.0032467532 | AR8: =AR7/AQ7-1 -> 0 | AS8: =AS7/AR7-1 -> -0.053745928 | AU8: =AU7/AS7-1 -> -0.0051635112 | AV8: =AV7/AU7-1 -> 0.0051903114 | AW8: =AW7/AV7-1 -> -0.0068846816 | AX8: =AX7/AW7-1 -> -0.057192374 | AZ8: =AZ7/AX7-1 -> 0.0018382353 | BA8: =BA7/AZ7-1 -> 0.0018348624 | BB8: =BB7/BA7-1 -> 0.0018315018 | BC8: =BC7/BB7-1 -> -0.031078611 | BE8: =BE7/BC7-1 -> 0.0018867925 | BF8: =BF7/BE7-1 -> 0.0018832392 | BG8: =BG7/BF7-1 -> 0.0018796992 | BH8: =BH7/BG7-1 -> -0.028142589 | BJ8: =BJ7/BH7-1 -> -0.0019305019 | BK8: =BK7/BJ7-1 -> -0.0077369439 | BL8: =BL7/BK7-1 -> -0.007797271 | BM8: =BM7/BL7-1 -> -0.0078585462 | BO8: =BO7/BM7-1 -> -0.0079207921 | BP8: =BP7/BO7-1 -> -0.0079840319 | BQ8: =BQ7/BP7-1 -> -0.0080482897 | BR8: =BR7/BQ7-1 -> -0.0081135903
A9: Y/Y Total company operated store growth, % | D9: =D7/C7-1 -> -0.029508197 | E9: =E7/D7-1 -> -0.027027027 | F9: =F7/E7-1 -> 0.0086805556 | K9: =K7/F7-1 -> 0.0068846816 | L9: =L7/G7-1 -> 0.003407155 | M9: =M7/H7-1 -> -0.0016949153 | N9: =N7/I7-1 -> 0.013445378 | O9: =O7/J7-1 -> 0.027350427 | P9: =P7/K7-1 -> 0.027350427 | Q9: =Q7/L7-1 -> 0.0237691 | R9: =R7/M7-1 -> 0.039049236 | ... BS9: =BS7/BN7-1 -> -0.031683168 | BT9: =BT7/BS7-1 -> -0.020449898 | BU9: =BU7/BT7-1 -> -0.020876827 | BV9: =BV7/BU7-1 -> -0.021321962
A11: Pottery Barn Revenue, mm | C11: =C284 -> 1304.319 | D11: =D284 -> 1511.029 | E11: =E284 -> 1600.847 | F11: =F284 -> 1752.997 | K11: =K284 -> 1910.978 | P11: =P284 -> 2022.331 | U11: =U284 -> 2074.051 | Z11: =Z284 -> 2024.218 | AE11: =AE284 -> 2066.302 | AF11: =AF284 -> 490.372 | AG11: =AG284 -> 506.46 | AH11: =AH284 -> 533.469 | AI11: =AI284 -> 647.043 | AJ11: =AJ284 -> 2177.344 | AK11: =AK284 -> 492.126 | AL11: =AL284 -> 524.847 | ... BV11: =BV284 -> 4050.6768
A12: Y/Y Pottery Barn comparable brand revenue growth, % | C12: =C274 -> -0.111 | D12: =D274 -> 0.177 | E12: =E274 -> 0.076 | F12: =F274 -> 0.085 | G12: =G274 -> 0.076 | H12: =H274 -> 0.099 | I12: =I274 -> 0.084 | J12: =J274 -> 0.146 | ... BV12: =BV274 -> 0.09
A13: Y/Y Pottery Barn revenue growth, % | D13: =D11/C11-1 -> 0.15848117 | E13: =E11/D11-1 -> 0.059441612 | F13: =F11/E11-1 -> 0.095043436 | K13: =K11/F11-1 -> 0.090120519 | P13: =P11/K11-1 -> 0.058270163 | U13: =U11/P11-1 -> 0.025574448 | Z13: =Z11/U11-1 -> -0.024026892 | AE13: =AE11/Z11-1 -> 0.020790251 | AJ13: =AJ11/AE11-1 -> 0.053739482 | AK13: =AK11/AF11-1 -> 0.0035768763 | AL13: =AL11/AG11-1 -> 0.03630494 | AM13: =AM11/AH11-1 -> 0.044081287 | AN13: =AN11/AI11-1 -> -0.010206431 | AO13: =AO11/AJ11-1 -> 0.017017522 | AP13: =AP11/AK11-1 -> -0.025422351 | AQ13: =AQ11/AL11-1 -> 0.073219433 | ... BS13: =BS11/BN11-1 -> 0.014895422 | BT13: =BT11/BS11-1 -> 0.064953002 | BU13: =BU11/BT11-1 -> 0.09 | BV13: =BV11/BU11-1 -> 0.09
A15: West Elm Revenue, mm | C15: =C285 -> 211.576 | D15: =D285 -> 259.936 | E15: =E285 -> 335.98 | F15: =F285 -> 430.099 | K15: =K285 -> 531.305 | P15: =P285 -> 669.074 | U15: =U285 -> 821.136 | Z15: =Z285 -> 971.568 | AE15: =AE285 -> 1114.339 | AF15: =AF285 -> 273.349 | AG15: =AG285 -> 301.213 | AH15: =AH285 -> 339.099 | AI15: =AI285 -> 379.267 | AJ15: =AJ285 -> 1292.928 | AK15: =AK285 -> 309.483 | AL15: =AL285 -> 357.574 | ... BV15: =BV285 -> 2257.3246
A16: Y/Y West Elm comparable brand revenue growth, % | C16: =C275 -> -0.12 | D16: =D275 -> 0.164 | E16: =E275 -> 0.303 | F16: =F275 -> 0.174 | G16: =G275 -> 0.118 | H16: =H275 -> 0.165 | I16: =I275 -> 0.222 | J16: =J275 -> 0.183 | ... BV16: =BV275 -> 0.08
A17: Y/Y West Elm revenue growth, % | D17: =D15/C15-1 -> 0.22857035 | E17: =E15/D15-1 -> 0.29254894 | F17: =F15/E15-1 -> 0.28013275 | K17: =K15/F15-1 -> 0.23530861 | P17: =P15/K15-1 -> 0.25930304 | U17: =U15/P15-1 -> 0.22727232 | Z17: =Z15/U15-1 -> 0.18319986 | AE17: =AE15/Z15-1 -> 0.14694906 | AJ17: =AJ15/AE15-1 -> 0.16026452 | AK17: =AK15/AF15-1 -> 0.13218998 | AL17: =AL15/AG15-1 -> 0.18711344 | AM17: =AM15/AH15-1 -> 0.15111221 | AN17: =AN15/AI15-1 -> 0.078762455 | AO17: =AO15/AJ15-1 -> 0.13427585 | AP17: =AP15/AK15-1 -> 0.019215918 | AQ17: =AQ15/AL15-1 -> 0.064260824 | ... BS17: =BS15/BN15-1 -> 0.027787727 | BT17: =BT15/BS15-1 -> 0.075139028 | BU17: =BU15/BT15-1 -> 0.056853388 | BV17: =BV15/BU15-1 -> 0.055998153
A19: Williams Sonoma Revenue, mm | C19: =C286 -> 958.461 | D19: =D286 -> 1006.086 | E19: =E286 -> 994.425 | F19: =F286 -> 980.709 | K19: =K286 -> 978.002 | P19: =P286 -> 994.651 | U19: =U286 -> 993.609 | Z19: =Z286 -> 1002.194 | AE19: =AE286 -> 1022.434 | AF19: =AF286 -> 200.977 | AG19: =AG286 -> 195.178 | AH19: =AH286 -> 203.936 | AI19: =AI286 -> 456.034 | AJ19: =AJ286 -> 1056.125 | AK19: =AK286 -> 194.894 | AL19: =AL286 -> 191.374 | ... BV19: =BV286 -> 1648.7005
A20: Y/Y Williams Sonoma comparable brand revenue growth, % | C20: =C276 -> -0.032 | D20: =D276 -> 0.05 | E20: =E276 -> -0.003 | F20: =F276 -> -0.011 | G20: =G276 -> 0.019 | H20: =H276 -> -0.004 | I20: =I276 -> 0.014 | J20: =J276 -> 0.023 | ... BV20: =BV276 -> 0.08
A21: Y/Y Williams Sonoma revenue growth, % | D21: =D19/C19-1 -> 0.049689033 | E21: =E19/D19-1 -> -0.01159046 | F21: =F19/E19-1 -> -0.013792895 | K21: =K19/F19-1 -> -0.0027602479 | P21: =P19/K19-1 -> 0.017023483 | U21: =U19/P19-1 -> -0.0010476036 | Z21: =Z19/U19-1 -> 0.0086402196 | AE21: =AE19/Z19-1 -> 0.020195691 | AJ21: =AJ19/AE19-1 -> 0.03295176 | AK21: =AK19/AF19-1 -> -0.030267145 | AL21: =AL19/AG19-1 -> -0.019489902 | AM21: =AM19/AH19-1 -> 0.0076347482 | AN21: =AN19/AI19-1 -> -0.033828618 | AO21: =AO19/AJ19-1 -> -0.022494496 | AP21: =AP19/AK19-1 -> 0.022617423 | AQ21: =AQ19/AL19-1 -> 0.27045994 | ... BS21: =BS19/BN19-1 -> 0.015817189 | BT21: =BT19/BS19-1 -> 0.074623893 | BU21: =BU19/BT19-1 -> 0.082328805 | BV21: =BV19/BU19-1 -> 0.082371209
A23: Pottery Barn Kids and Teen Revenue, mm | C23: =C289 -> 596.239 | D23: =D289 -> 685.282 | E23: =E289 -> 733.835 | F23: =F289 -> 777.597 | K23: =K289 -> 844.077 | P23: =P289 -> 885.211 | U23: =U289 -> 893.675 | Z23: =Z289 -> 873.199 | AE23: =AE289 -> 860.468 | AF23: =AF289 -> 180.396 | AG23: =AG289 -> 213.807 | AH23: =AH289 -> 227.331 | AI23: =AI289 -> 274.228 | AJ23: =AJ289 -> 895.762 | AK23: =AK289 -> 177.046 | AL23: =AL289 -> 227.853 | ... BV23: =BV289 -> 1246.7476
A24: Y/Y Pottery Barn Kids and Teen comparable brand revenue growth, % | AG24: =AG279 -> 0.057 | AH24: =AH279 -> 0 | AI24: =AI279 -> 0.016 | AJ24: =AJ279 -> 0.028 | AK24: =AK279 -> 0.012 | AL24: =AL279 -> 0.037 | AM24: =AM279 -> 0.04 | AN24: =AN279 -> 0.079 | ... BV24: =BV279 -> 0.05
A25: Y/Y Pottery Barn Kids and Teen revenue growth, % | D25: =D23/C23-1 -> 0.14934112 | E25: =E23/D23-1 -> 0.070851124 | F25: =F23/E23-1 -> 0.059634659 | K25: =K23/F23-1 -> 0.085494157 | P25: =P23/K23-1 -> 0.048732521 | U25: =U23/P23-1 -> 0.0095615622 | Z25: =Z23/U23-1 -> -0.022912132 | AE25: =AE23/Z23-1 -> -0.014579724 | AJ25: =AJ23/AE23-1 -> 0.041017214 | AK25: =AK23/AF23-1 -> -0.018570257 | AL25: =AL23/AG23-1 -> 0.065694762 | AM25: =AM23/AH23-1 -> 0.0031671879 | AN25: =AN23/AI23-1 -> 0.0050432487 | AO25: =AO23/AJ23-1 -> 0.014288394 | AP25: =AP23/AK23-1 -> 0.06498876 | AQ25: =AQ23/AL23-1 -> 0.035698455 | ... BS25: =BS23/BN23-1 -> 0.05218104 | BT25: =BT23/BS23-1 -> 0.04 | BU25: =BU23/BT23-1 -> 0.04 | BV25: =BV23/BU23-1 -> 0.04
A27: Other Revenue, mm | C27: =C290 -> 32.109 | D27: =D290 -> 41.825 | E27: =E290 -> 55.808 | F27: =F290 -> 101.468 | K27: =K290 -> 123.527 | P27: =P290 -> 127.452 | U27: =U290 -> 193.619 | Z27: =Z290 -> 212.633 | AE27: =AE290 -> 228.816 | AF27: =AF290 -> 57.906 | AG27: =AG290 -> 58.516 | AH27: =AH290 -> 53.148 | AI27: =AI290 -> 79.864 | AJ27: =AJ290 -> 249.434 | AK27: =AK290 -> 67.583 | AL27: =AL290 -> 69.166 | ... BV27: =BV290 -> 482.06109
A28: Y/Y Other revenue growth, % | D28: =D27/C27-1 -> 0.30259429 | E28: =E27/D27-1 -> 0.33432158 | F28: =F27/E27-1 -> 0.81816227 | K28: =K27/F27-1 -> 0.21739859 | P28: =P27/K27-1 -> 0.03177443 | U28: =U27/P27-1 -> 0.51915231 | Z28: =Z27/U27-1 -> 0.098203172 | AE28: =AE27/Z27-1 -> 0.07610766 | AJ28: =AJ27/AE27-1 -> 0.090107335 | AK28: =AK27/AF27-1 -> 0.16711567 | AL28: =AL27/AG27-1 -> 0.1820015 | AM28: =AM27/AH27-1 -> 0.15906525 | AN28: =AN27/AI27-1 -> -0.025919062 | AO28: =AO27/AJ27-1 -> 0.10708644 | AP28: =AP27/AK27-1 -> -0.22607756 | AQ28: =AQ27/AL27-1 -> -0.019330307 | ... BS28: =BS27/BN27-1 -> 0.05 | BT28: =BT27/BS27-1 -> 0.05 | BU28: =BU27/BT27-1 -> 0.05 | BV28: =BV27/BU27-1 -> 0.05
A30: Total Revenue, mm | C30: =C749 -> 3102.704 | D30: =D749 -> 3504.158 | E30: =E749 -> 3720.895 | F30: =F749 -> 4042.87 | G30: =G749 -> 887.808 | H30: =H749 -> 982.209 | I30: =I749 -> 1051.548 | J30: =J749 -> 1466.324 | ... BV30: =BV749 -> 9685.5106
A31: =A752 -> Consensus Estimates - Net Revenue | BK31: =BK752 -> N/A | BL31: =BL752 -> N/A | BM31: =BM752 -> N/A | BN31: =BN752 -> N/A | BO31: =BO752 -> N/A | BP31: =BP752 -> N/A | BQ31: =BQ752 -> N/A | BR31: =BR752 -> N/A | ... BV31: =BV752 -> N/A
A32: Y/Y Comparable demand growth, % | AH32: =AH282 -> 0.046 | AQ32: =AQ282 -> 0.19 | AR32: =AR282 -> 0.31 | AS32: =AS282 -> 0.3 | AU32: =AU282 -> 0.4 | AW32: =AW282 -> 0.169 | AX32: =AX282 -> 0.108 | AZ32: =AZ282 -> 0.095 | BC32: =BC282 -> -0.05 | BE32: =BE282 -> -0.1 | BF32: =BF282 -> -0.114 | BG32: =BG282 -> -0.118
A33: Y/Y Comparable brand revenue growth, % | C33: =C280 -> -0.093 | D33: =D280 -> 0.139 | E33: =E280 -> 0.073 | F33: =F280 -> 0.061 | G33: =G280 -> 0.072 | H33: =H280 -> 0.084 | I33: =I280 -> 0.082 | J33: =J280 -> 0.104 | ... BV33: =BV280 -> 0.080139729
A34: Y/Y Total revenue growth, % | D34: =D30/C30-1 -> 0.12938843 | E34: =E30/D30-1 -> 0.061851378 | F34: =F30/E30-1 -> 0.086531601 | K34: =K30/F30-1 -> 0.085340117 | L34: =L30/G30-1 -> 0.097455756 | M34: =M30/H30-1 -> 0.057923517 | N34: =N30/I30-1 -> 0.087122984 | O34: =O30/J30-1 -> 0.051694578 | P34: =P30/K30-1 -> 0.070838164 | Q34: =Q30/L30-1 -> 0.057830509 | R34: =R30/M30-1 -> 0.084617295 | ... BS34: =BS30/BN30-1 -> 0.024991776 | BT34: =BT30/BS30-1 -> 0.064693372 | BU34: =BU30/BT30-1 -> 0.07185334 | BV34: =BV30/BU30-1 -> 0.072002431
A36: E-Commerce net revenue as % of total net revenue, % | C36: =C397 -> 0.39471055 | D36: =D397 -> 0.41452811 | E36: =E397 -> 0.43882211 | F36: =F397 -> 0.46239083 | G36: =G397 -> 0.4720435 | H36: =H397 -> 0.48630892 | I36: =I397 -> 0.48678139 | J36: =J397 -> 0.48175369 | ... AJ36: =AJ397 -> 0.54342122 | AL36: =AL397 -> 0.56610226 | AO36: =AO397 -> 0.562 | AP36: =AP397 -> 0.62758549 | AQ36: =AQ397 -> 0.76 | AR36: =AR397 -> 0.7 | AS36: =AS397 -> 0.7 | AT36: =AT397 -> 0.7 | AU36: =AU397 -> 0.65 | AV36: =AV397 -> 0.65 | ... BD36: =BD397 -> 0.66 | BF36: =BF397 -> 0.66 | BI36: =BI397 -> 0.66
A37: Y/Y E-Commerce net revenue growth, % | D37: =D390 -> 0.18609258 | E37: =E390 -> 0.12408266 | F37: =F390 -> 0.14488817 | K37: =K390 -> 0.13139929 | L37: =L390 -> 0.17229243 | M37: =M390 -> 0.0940675 | N37: =N390 -> 0.1467197 | O37: =O390 -> 0.089796675 | P37: =P390 -> 0.12088385 | Q37: =Q390 -> 0.084032006 | R37: =R390 -> 0.090556824 | ... AJ37: =AJ390 -> 0.1092718 | AL37: =AL390 -> 0.12967456 | AO37: =AO390 -> 0.075474259 | AQ37: =AQ390 -> 0.46 | AT37: =AT390 -> 0.43248567 | AU37: =AU390 -> 0.46655764 | AV37: =AV390 -> 0.11776783 | AW37: =AW390 -> 0.11065307 | AX37: =AX390 -> 0.038823261 | AY37: =AY390 -> 0.14617765 | AZ37: =AZ390 -> 0.081301111 | BA37: =BA390 -> 0.10385876 | ... BD37: =BD390 -> 0.051962688 | BF37: =BF390 -> -0.12062238 | BI37: =BI390 -> -0.10649304
A39: Adjusted Gross Profit, mm | C39: =C323 -> 1103.237 | D39: =D323 -> 1373.859 | E39: =E323 -> 1459.856 | F39: =F323 -> 1592.476 | G39: =G323 -> 334.185 | H39: =H323 -> 368.924 | I39: =I323 -> 405.388 | J39: =J323 -> 595.719 | ... BV39: =BV323 -> 4539.0662
A40: Consensus Estimates - Adjusted Gross Profit | BK40: =IFERROR(BK626*BK752,"N/A") -> N/A | BL40: =IFERROR(BL626*BL752,"N/A") -> N/A | BM40: =IFERROR(BM626*BM752,"N/A") -> N/A | BN40: =IFERROR(BN626*BN752,"N/A") -> N/A | BO40: =IFERROR(BO626*BO752,"N/A") -> N/A | BP40: =IFERROR(BP626*BP752,"N/A") -> N/A | BQ40: =IFERROR(BQ626*BQ752,"N/A") -> N/A | BR40: =IFERROR(BR626*BR752,"N/A") -> N/A | ... BV40: =IFERROR(BV626*BV752,"N/A") -> N/A
A41: Adjusted gross margin, % | C41: =C327 -> 0.35557275 | D41: =D327 -> 0.39206537 | E41: =E327 -> 0.39234001 | F41: =F327 -> 0.3938974 | G41: =G327 -> 0.37641585 | H41: =H327 -> 0.37560641 | I41: =I327 -> 0.38551545 | J41: =J327 -> 0.40626696 | ... BV41: =BV327 -> 0.468645
A42: Y/Y Adjusted gross margin improvement, bps | D42: =(D41-C41)*10000 -> 364.92617 | E42: =(E41-D41)*10000 -> 2.7464577 | F42: =(F41-E41)*10000 -> 15.573896 | K42: =(K41-F41)*10000 -> -55.065405 | L42: =(L41-G41)*10000 -> 16.983446 | M42: =(M41-H41)*10000 -> -78.86979 | N42: =(N41-I41)*10000 -> -81.349908 | O42: =(O41-J41)*10000 -> -51.380025 | P42: =(P41-K41)*10000 -> -52.004668 | Q42: =(Q41-L41)*10000 -> -105.48632 | R42: =(R41-M41)*10000 -> -69.253816 | ... BS42: =(BS41-BN41)*10000 -> -26.232159 | BT42: =(BT41-BS41)*10000 -> 38.192089 | BU42: =(BU41-BT41)*10000 -> 43.478671 | BV42: =(BV41-BU41)*10000 -> 42.102726
A44: Adjusted EBIT, mm | C44: =C366 -> 162.18514 | D44: =D366 -> 344.94729 | E44: =E366 -> 384.83459 | F44: =F366 -> 416.25421 | G44: =G366 -> 66.790843 | H44: =H366 -> 78.1655 | I44: =I366 -> 92.58196 | J44: =J366 -> 217.88349 | ... BV44: =BV366 -> 1668.9063
A45: Consensus Estimates - Adjusted EBIT | BK45: =BK764 -> N/A | BL45: =BL764 -> N/A | BM45: =BM764 -> N/A | BN45: =BN764 -> N/A | BO45: =BO764 -> N/A | BP45: =BP764 -> N/A | BQ45: =BQ764 -> N/A | BR45: =BR764 -> N/A | ... BV45: =BV764 -> N/A
A46: Adjusted EBIT margin, % | C46: =C370 -> 0.052272192 | D46: =D370 -> 0.098439424 | E46: =E370 -> 0.10342528 | F46: =F370 -> 0.10296008 | G46: =G370 -> 0.07523118 | H46: =H370 -> 0.079581332 | I46: =I370 -> 0.088043494 | J46: =J370 -> 0.14859164 | ... BV46: =BV370 -> 0.17230959
A47: Y/Y Adjusted EBIT margin improvement, bps | D47: =(D46-C46)*10000 -> 461.67231 | E47: =(E46-D46)*10000 -> 49.85852 | F47: =(F46-E46)*10000 -> -4.6519886 | K47: =(K46-F46)*10000 -> 7.6566301 | L47: =(L46-G46)*10000 -> 11.313301 | M47: =(M46-H46)*10000 -> 26.224602 | N47: =(N46-I46)*10000 -> 36.422039 | O47: =(O46-J46)*10000 -> 9.5736158 | P47: =(P46-K46)*10000 -> 16.131608 | Q47: =(Q46-L46)*10000 -> -65.075921 | R47: =(R46-M46)*10000 -> -81.88817 | ... BS47: =(BS46-BN46)*10000 -> -92.519565 | BT47: =(BT46-BS46)*10000 -> 8.1920894 | BU47: =(BU46-BT46)*10000 -> 13.478671 | BV47: =(BV46-BU46)*10000 -> 12.102726
A49: Adjusted Earnings Per Share - WAD, $/share | C49: =C811 -> 0.95124277 | D49: =D811 -> 1.9481898 | E49: =E811 -> 2.2429926 | F49: =F811 -> 2.5805983 | G49: =G811 -> 0.41658343 | H49: =H811 -> 0.49434603 | I49: =I811 -> 0.57957553 | J49: =J811 -> 1.3797449 | ... BV49: =BV811 -> 20.803688
A50: Consensus Estimates - Adjusted Earnings Per Share - WAD | BK50: =BK812 -> N/A | BL50: =BL812 -> N/A | BM50: =BM812 -> N/A | BN50: =BN812 -> N/A | BO50: =BO812 -> N/A | BP50: =BP812 -> N/A | BQ50: =BQ812 -> N/A | BR50: =BR812 -> N/A | ... BV50: =BV812 -> N/A
A51: Y/Y Adjusted EPS - WAD growth, % | D51: =IF(C49>0,D49/C49-1,-(D49/C49-1)) -> 1.0480469 | E51: =IF(D49>0,E49/D49-1,-(E49/D49-1)) -> 0.15132143 | F51: =IF(E49>0,F49/E49-1,-(F49/E49-1)) -> 0.15051574 | K51: =IF(F49>0,K49/F49-1,-(K49/F49-1)) -> 0.10202936 | L51: =IF(G49>0,L49/G49-1,-(L49/G49-1)) -> 0.15889201 | M51: =IF(H49>0,M49/H49-1,-(M49/H49-1)) -> 0.071117339 | N51: =IF(I49>0,N49/I49-1,-(N49/I49-1)) -> 0.17985995 | O51: =IF(J49>0,O49/J49-1,-(O49/J49-1)) -> 0.10181261 | P51: =IF(K49>0,P49/K49-1,-(P49/K49-1)) -> 0.12671691 | Q51: =IF(L49>0,Q49/L49-1,-(Q49/L49-1)) -> -0.0056152448 | R51: =IF(M49>0,R49/M49-1,-(R49/M49-1)) -> 0.094977506 | ... BS51: =IF(BN49>0,BS49/BN49-1,-(BS49/BN49-1)) -> 0.0091032423 | BT51: =IF(BS49>0,BT49/BS49-1,-(BT49/BS49-1)) -> 0.078603022 | BU51: =IF(BT49>0,BU49/BT49-1,-(BU49/BT49-1)) -> 0.089501986 | BV51: =IF(BU49>0,BV49/BU49-1,-(BV49/BU49-1)) -> 0.089102075
A53: Segmented Results - Pottery Barn (FS)
A54: Pottery Barn Stores - BoP, # of Stores | C54: 204 | D54: =C57 -> 199 | E54: =D57 -> 193 | F54: =E57 -> 194 | G54: =F57 -> 192 | H54: =G57 -> 195 | I54: =H57 -> 196 | J54: =I57 -> 196 | K54: =F57 -> 192 | L54: =K57 -> 194 | M54: =L57 -> 195 | N54: =M57 -> 195 | O54: =N57 -> 198 | P54: =K57 -> 194 | Q54: =P57 -> 199 | R54: =Q57 -> 198 | S54: =R57 -> 199 | T54: =S57 -> 200 | U54: =P57 -> 199 | V54: =U57 -> 197 | W54: =V57 -> 200 | X54: =W57 -> 201 | Y54: =X57 -> 202 | Z54: =U57 -> 197 | AA54: =Z57 -> 201 | AB54: =AA57 -> 199 | AC54: =AB57 -> 204 | AD54: =AC57 -> 202 | AE54: =Z57 -> 201 | AF54: =AE57 -> 203 | AG54: =AF57 -> 203 | AH54: =AG57 -> 205 | AI54: =AH57 -> 205 | AJ54: =AE57 -> 203 | AK54: =AJ57 -> 205 | AL54: =AK57 -> 205 | AM54: =AL57 -> 205 | AN54: =AM57 -> 205 | AO54: =AJ57 -> 205 | AP54: =AO57 -> 201 | AQ54: =AP57 -> 201 | AR54: =AQ57 -> 201 | AS54: =AR57 -> 201 | AT54: =AO57 -> 201 | AU54: =AT57 -> 195 | AV54: =AU57 -> 195 | AW54: =AV57 -> 195 | AX54: =AW57 -> 195 | AY54: =AT57 -> 195 | AZ54: =AY57 -> 188 | BA54: =AZ57 -> 188 | BB54: =BA57 -> 189 | BC54: =BB57 -> 189 | BD54: =AY57 -> 188 | BE54: =BD57 -> 188 | BF54: =BE57 -> 188 | BG54: =BF57 -> 190 | BH54: =BG57 -> 191 | BI54: =BD57 -> 188 | BJ54: =BI57 -> 184 | BK54: =BJ57 -> 184 | BL54: =BK57 -> 182 | BM54: =BL57 -> 180 | BN54: =BI57 -> 184 | BO54: =BN57 -> 178 | BP54: =BO57 -> 176 | BQ54: =BP57 -> 174 | BR54: =BQ57 -> 172 | BS54: =BN57 -> 178 | BT54: =BS57 -> 170 | BU54: =BT57 -> 170 | BV54: =BU57 -> 170
A55: Pottery Barn stores opened, # of stores | C55: =2+1+0+2 -> 5 | D55: =0+1+0+2 -> 3 | E55: =0+1+4+10+3 -> 18 | F55: =2+4+1+1 -> 8 | G55: 4 | H55: 1 | I55: 1 | J55: 1 | K55: =SUM(G55,H55,I55,J55) -> 7 | L55: 2 | M55: 0 | N55: 3 | O55: 2 | P55: =SUM(L55,M55,N55,O55) -> 7 | Q55: 0 | R55: 2 | S55: 2 | T55: 0 | U55: =SUM(Q55,R55,S55,T55) -> 4 | V55: 3 | W55: 1 | X55: 1 | Y55: 1 | Z55: =SUM(V55,W55,X55,Y55) -> 6 | AA55: 1 | AB55: 6 | AC55: 1 | AD55: 2 | AE55: =SUM(AA55,AB55,AC55,AD55) -> 10 | AF55: 1 | AG55: 2 | AH55: 0 | AI55: 3 | AJ55: =SUM(AF55,AG55,AH55,AI55) -> 6 | AK55: 0 | AL55: 2 | AM55: 0 | AN55: 0 | AO55: =SUM(AK55,AL55,AM55,AN55) -> 2 | AP55: 0 | AQ55: 0 | AR55: 1 | AS55: 0 | AT55: =SUM(AP55,AQ55,AR55,AS55) -> 1 | AU55: 2 | AV55: 1 | AW55: 0 | AX55: 1 | AY55: =SUM(AU55,AV55,AW55,AX55) -> 4 | AZ55: 1 | BA55: 2 | BB55: 2 | BC55: 2 | BD55: =SUM(AZ55,BA55,BB55,BC55) -> 7 | BE55: 0 | BF55: 3 | BG55: 2 | BH55: 1 | BI55: =SUM(BE55,BF55,BG55,BH55) -> 6 | BJ55: 1 | BK55: 0 | BL55: 0 | BM55: 0 | BN55: =SUM(BJ55,BK55,BL55,BM55) -> 1 | BO55: 0 | BP55: 0 | BQ55: 0 | BR55: 0 | BS55: =SUM(BO55,BP55,BQ55,BR55) -> 0 | BT55: 0 | BU55: 0 | BV55: 0
A56: Pottery Barn stores closed, # of stores | C56: =-7-1+0-2 -> -10 | D56: =-5+0-2-2 -> -9 | E56: =-7+0-5-5 -> -17 | F56: =-3-4-1-2 -> -10 | G56: -1 | H56: 0 | I56: -1 | J56: -3 | K56: =SUM(G56,H56,I56,J56) -> -5 | L56: -1 | M56: 0 | N56: 0 | O56: -1 | P56: =SUM(L56,M56,N56,O56) -> -2 | Q56: -1 | R56: -1 | S56: -1 | T56: -3 | U56: =SUM(Q56,R56,S56,T56) -> -6 | V56: 0 | W56: 0 | X56: 0 | Y56: -2 | Z56: =SUM(V56,W56,X56,Y56) -> -2 | AA56: -3 | AB56: -1 | AC56: -3 | AD56: -1 | AE56: =SUM(AA56,AB56,AC56,AD56) -> -8 | AF56: -1 | AG56: 0 | AH56: 0 | AI56: -3 | AJ56: =SUM(AF56,AG56,AH56,AI56) -> -4 | AK56: 0 | AL56: -2 | AM56: 0 | AN56: -4 | AO56: =SUM(AK56,AL56,AM56,AN56) -> -6 | AP56: 0 | AQ56: 0 | AR56: -1 | AS56: -6 | AT56: =SUM(AP56,AQ56,AR56,AS56) -> -7 | AU56: -2 | AV56: -1 | AW56: 0 | AX56: -8 | AY56: =SUM(AU56,AV56,AW56,AX56) -> -11 | AZ56: -1 | BA56: -1 | BB56: -2 | BC56: -3 | BD56: =SUM(AZ56,BA56,BB56,BC56) -> -7 | BE56: 0 | BF56: -1 | BG56: -1 | BH56: -8 | BI56: =SUM(BE56,BF56,BG56,BH56) -> -10 | BJ56: -1 | BK56: -2 | BL56: -2 | BM56: -2 | BN56: =SUM(BJ56,BK56,BL56,BM56) -> -7 | BO56: -2 | BP56: -2 | BQ56: -2 | BR56: -2 | BS56: =SUM(BO56,BP56,BQ56,BR56) -> -8 | BT56: 0 | BU56: 0 | BV56: 0
A57: Pottery Barn Stores - EoP, # of Stores | C57: =SUM(C54:C56) -> 199 | D57: =SUM(D54:D56) -> 193 | E57: =SUM(E54:E56) -> 194 | F57: =SUM(F54:F56) -> 192 | G57: =SUM(G54:G56) -> 195 | H57: =SUM(H54:H56) -> 196 | I57: =SUM(I54:I56) -> 196 | J57: =SUM(J54:J56) -> 194 | K57: =J57 -> 194 | L57: =SUM(L54:L56) -> 195 | M57: =SUM(M54:M56) -> 195 | N57: =SUM(N54:N56) -> 198 | O57: =SUM(O54:O56) -> 199 | P57: =O57 -> 199 | Q57: =SUM(Q54:Q56) -> 198 | R57: =SUM(R54:R56) -> 199 | S57: =SUM(S54:S56) -> 200 | T57: =SUM(T54:T56) -> 197 | U57: =T57 -> 197 | V57: =SUM(V54:V56) -> 200 | W57: =SUM(W54:W56) -> 201 | X57: =SUM(X54:X56) -> 202 | Y57: =SUM(Y54:Y56) -> 201 | Z57: =Y57 -> 201 | AA57: =SUM(AA54:AA56) -> 199 | AB57: =SUM(AB54:AB56) -> 204 | AC57: =SUM(AC54:AC56) -> 202 | AD57: =SUM(AD54:AD56) -> 203 | AE57: =AD57 -> 203 | AF57: =SUM(AF54:AF56) -> 203 | AG57: =SUM(AG54:AG56) -> 205 | AH57: =SUM(AH54:AH56) -> 205 | AI57: =SUM(AI54:AI56) -> 205 | AJ57: =AI57 -> 205 | AK57: =SUM(AK54:AK56) -> 205 | AL57: =SUM(AL54:AL56) -> 205 | AM57: =SUM(AM54:AM56) -> 205 | AN57: =SUM(AN54:AN56) -> 201 | AO57: =AN57 -> 201 | AP57: =SUM(AP54:AP56) -> 201 | AQ57: =SUM(AQ54:AQ56) -> 201 | AR57: =SUM(AR54:AR56) -> 201 | AS57: =SUM(AS54:AS56) -> 195 | AT57: =AS57 -> 195 | AU57: =SUM(AU54:AU56) -> 195 | AV57: =SUM(AV54:AV56) -> 195 | AW57: =SUM(AW54:AW56) -> 195 | AX57: =SUM(AX54:AX56) -> 188 | AY57: =AX57 -> 188 | AZ57: =SUM(AZ54:AZ56) -> 188 | BA57: =SUM(BA54:BA56) -> 189 | BB57: =SUM(BB54:BB56) -> 189 | BC57: =SUM(BC54:BC56) -> 188 | BD57: =BC57 -> 188 | BE57: =SUM(BE54:BE56) -> 188 | BF57: =SUM(BF54:BF56) -> 190 | BG57: =SUM(BG54:BG56) -> 191 | BH57: =SUM(BH54:BH56) -> 184 | BI57: =BH57 -> 184 | BJ57: =SUM(BJ54:BJ56) -> 184 | BK57: =SUM(BK54:BK56) -> 182 | BL57: =SUM(BL54:BL56) -> 180 | BM57: =SUM(BM54:BM56) -> 178 | BN57: =SUM(BN54:BN56) -> 178 | BO57: =SUM(BO54:BO56) -> 176 | BP57: =SUM(BP54:BP56) -> 174 | BQ57: =SUM(BQ54:BQ56) -> 172 | ... BV57: =SUM(BV54:BV56) -> 170
A58: Q/Q Pottery Barn stores - EoP growth, % | H58: =H57/G57-1 -> 0.0051282051 | I58: =I57/H57-1 -> 0 | J58: =J57/I57-1 -> -0.010204082 | L58: =L57/J57-1 -> 0.0051546392 | M58: =M57/L57-1 -> 0 | N58: =N57/M57-1 -> 0.015384615 | O58: =O57/N57-1 -> 0.0050505051 | Q58: =Q57/O57-1 -> -0.0050251256 | R58: =R57/Q57-1 -> 0.0050505051 | S58: =S57/R57-1 -> 0.0050251256 | T58: =T57/S57-1 -> -0.015 | V58: =V57/T57-1 -> 0.015228426 | W58: =W57/V57-1 -> 0.005 | X58: =X57/W57-1 -> 0.0049751244 | Y58: =Y57/X57-1 -> -0.004950495 | AA58: =AA57/Y57-1 -> -0.0099502488 | AB58: =AB57/AA57-1 -> 0.025125628 | AC58: =AC57/AB57-1 -> -0.0098039216 | AD58: =AD57/AC57-1 -> 0.004950495 | AF58: =AF57/AD57-1 -> 0 | AG58: =AG57/AF57-1 -> 0.0098522167 | AH58: =AH57/AG57-1 -> 0 | AI58: =AI57/AH57-1 -> 0 | AK58: =AK57/AI57-1 -> 0 | AL58: =AL57/AK57-1 -> 0 | AM58: =AM57/AL57-1 -> 0 | AN58: =AN57/AM57-1 -> -0.019512195 | AP58: =AP57/AN57-1 -> 0 | AQ58: =AQ57/AP57-1 -> 0 | AR58: =AR57/AQ57-1 -> 0 | AS58: =AS57/AR57-1 -> -0.029850746 | AU58: =AU57/AS57-1 -> 0 | AV58: =AV57/AU57-1 -> 0 | AW58: =AW57/AV57-1 -> 0 | AX58: =AX57/AW57-1 -> -0.035897436 | AZ58: =AZ57/AX57-1 -> 0 | BA58: =BA57/AZ57-1 -> 0.0053191489 | BB58: =BB57/BA57-1 -> 0 | BC58: =BC57/BB57-1 -> -0.0052910053 | BE58: =BE57/BC57-1 -> 0 | BF58: =BF57/BE57-1 -> 0.010638298 | BG58: =BG57/BF57-1 -> 0.0052631579 | BH58: =BH57/BG57-1 -> -0.036649215 | BJ58: =BJ57/BH57-1 -> 0 | BK58: =BK57/BJ57-1 -> -0.010869565 | BL58: =BL57/BK57-1 -> -0.010989011 | BM58: =BM57/BL57-1 -> -0.011111111 | BO58: =BO57/BM57-1 -> -0.011235955 | BP58: =BP57/BO57-1 -> -0.011363636 | BQ58: =BQ57/BP57-1 -> -0.011494253 | BR58: =BR57/BQ57-1 -> -0.011627907
A59: Y/Y Pottery Barn stores - EoP growth, % | D59: =D57/C57-1 -> -0.030150754 | E59: =E57/D57-1 -> 0.0051813472 | F59: =F57/E57-1 -> -0.010309278 | K59: =K57/F57-1 -> 0.010416667 | L59: =L57/G57-1 -> 0 | M59: =M57/H57-1 -> -0.0051020408 | N59: =N57/I57-1 -> 0.010204082 | O59: =O57/J57-1 -> 0.025773196 | P59: =P57/K57-1 -> 0.025773196 | Q59: =Q57/L57-1 -> 0.015384615 | R59: =R57/M57-1 -> 0.020512821 | ... BS59: =BS57/BN57-1 -> -0.04494382 | BT59: =BT57/BS57-1 -> 0 | BU59: =BU57/BT57-1 -> 0 | BV59: =BV57/BU57-1 -> 0
A60: Pottery Barn Stores - Average, # of stores | C60: =AVERAGE(C57,C54) -> 201.5 | D60: =AVERAGE(D57,D54) -> 196 | E60: =AVERAGE(E57,E54) -> 193.5 | F60: =AVERAGE(F57,F54) -> 193 | G60: =AVERAGE(G57,G54) -> 193.5 | H60: =AVERAGE(H57,H54) -> 195.5 | I60: =AVERAGE(I57,I54) -> 196 | J60: =AVERAGE(J57,J54) -> 195 | K60: =SUM(G60*G$3,H60*H$3,I60*I$3,J60*J$3)/K$3 -> 195 | L60: =AVERAGE(L57,L54) -> 194.5 | M60: =AVERAGE(M57,M54) -> 195 | N60: =AVERAGE(N57,N54) -> 196.5 | O60: =AVERAGE(O57,O54) -> 198.5 | P60: =SUM(L60*L$3,M60*M$3,N60*N$3,O60*O$3)/P$3 -> 196.125 | Q60: =AVERAGE(Q57,Q54) -> 198.5 | R60: =AVERAGE(R57,R54) -> 198.5 | S60: =AVERAGE(S57,S54) -> 199.5 | T60: =AVERAGE(T57,T54) -> 198.5 | U60: =SUM(Q60*Q$3,R60*R$3,S60*S$3,T60*T$3)/U$3 -> 198.75 | V60: =AVERAGE(V57,V54) -> 198.5 | W60: =AVERAGE(W57,W54) -> 200.5 | X60: =AVERAGE(X57,X54) -> 201.5 | Y60: =AVERAGE(Y57,Y54) -> 201.5 | Z60: =SUM(V60*V$3,W60*W$3,X60*X$3,Y60*Y$3)/Z$3 -> 200.5 | AA60: =AVERAGE(AA57,AA54) -> 200 | AB60: =AVERAGE(AB57,AB54) -> 201.5 | AC60: =AVERAGE(AC57,AC54) -> 203 | AD60: =AVERAGE(AD57,AD54) -> 202.5 | AE60: =SUM(AA60*AA$3,AB60*AB$3,AC60*AC$3,AD60*AD$3)/AE$3 -> 201.75 | AF60: =AVERAGE(AF57,AF54) -> 203 | AG60: =AVERAGE(AG57,AG54) -> 204 | AH60: =AVERAGE(AH57,AH54) -> 205 | AI60: =AVERAGE(AI57,AI54) -> 205 | AJ60: =SUM(AF60*AF$3,AG60*AG$3,AH60*AH$3,AI60*AI$3)/AJ$3 -> 204.26415 | AK60: =AVERAGE(AK57,AK54) -> 205 | AL60: =AVERAGE(AL57,AL54) -> 205 | AM60: =AVERAGE(AM57,AM54) -> 205 | AN60: =AVERAGE(AN57,AN54) -> 203 | AO60: =SUM(AK60*AK$3,AL60*AL$3,AM60*AM$3,AN60*AN$3)/AO$3 -> 204.5 | AP60: =AVERAGE(AP57,AP54) -> 201 | AQ60: =AVERAGE(AQ57,AQ54) -> 201 | AR60: =AVERAGE(AR57,AR54) -> 201 | AS60: =AVERAGE(AS57,AS54) -> 198 | AT60: =SUM(AP60*AP$3,AQ60*AQ$3,AR60*AR$3,AS60*AS$3)/AT$3 -> 200.25 | AU60: =AVERAGE(AU57,AU54) -> 195 | AV60: =AVERAGE(AV57,AV54) -> 195 | AW60: =AVERAGE(AW57,AW54) -> 195 | AX60: =AVERAGE(AX57,AX54) -> 191.5 | AY60: =SUM(AU60*AU$3,AV60*AV$3,AW60*AW$3,AX60*AX$3)/AY$3 -> 194.125 | AZ60: =AVERAGE(AZ57,AZ54) -> 188 | BA60: =AVERAGE(BA57,BA54) -> 188.5 | BB60: =AVERAGE(BB57,BB54) -> 189 | BC60: =AVERAGE(BC57,BC54) -> 188.5 | BD60: =SUM(AZ60*AZ$3,BA60*BA$3,BB60*BB$3,BC60*BC$3)/BD$3 -> 188.5 | BE60: =AVERAGE(BE57,BE54) -> 188 | BF60: =AVERAGE(BF57,BF54) -> 189 | BG60: =AVERAGE(BG57,BG54) -> 190.5 | BH60: =AVERAGE(BH57,BH54) -> 187.5 | BI60: =SUM(BE60*BE$3,BF60*BF$3,BG60*BG$3,BH60*BH$3)/BI$3 -> 188.75 | BJ60: =AVERAGE(BJ57,BJ54) -> 184 | BK60: =AVERAGE(BK57,BK54) -> 183 | BL60: =AVERAGE(BL57,BL54) -> 181 | BM60: =AVERAGE(BM57,BM54) -> 179 | BN60: =SUM(BJ60*BJ$3,BK60*BK$3,BL60*BL$3,BM60*BM$3)/BN$3 -> 181.69811 | BO60: =AVERAGE(BO57,BO54) -> 177 | BP60: =AVERAGE(BP57,BP54) -> 175 | BQ60: =AVERAGE(BQ57,BQ54) -> 173 | BR60: =AVERAGE(BR57,BR54) -> 171 | BS60: =SUM(BO60*BO$3,BP60*BP$3,BQ60*BQ$3,BR60*BR$3)/BS$3 -> 174 | BT60: =AVERAGE(BT57,BT54) -> 170 | BU60: =AVERAGE(BU57,BU54) -> 170 | BV60: =AVERAGE(BV57,BV54) -> 170
A62: Pottery Barn comp stores, # of stores | D62: =C57+SUM(D56) -> 190 | E62: =D57+SUM(E56) -> 176 | F62: =E57+SUM(F56) -> 184 | K62: =F57+SUM(K56) -> 187 | L62: =G57+SUM(L56,J56,I56,H56) -> 190 | M62: =H57+SUM(M56,L56,J56,I56) -> 191 | N62: =I57+SUM(N56,M56,L56,J56) -> 192 | O62: =J57+SUM(O56,N56,M56,L56) -> 192 | P62: =K57+SUM(P56) -> 192 | Q62: =L57+SUM(Q56,O56,N56,M56) -> 193 | R62: =M57+SUM(R56,Q56,O56,N56) -> 192 | S62: =N57+SUM(S56,R56,Q56,O56) -> 194 | T62: =O57+SUM(T56,S56,R56,Q56) -> 193 | U62: =P57+SUM(U56) -> 193 | V62: =Q57+SUM(V56,T56,S56,R56) -> 193 | W62: =R57+SUM(W56,V56,T56,S56) -> 195 | X62: =S57+SUM(X56,W56,V56,T56) -> 197 | Y62: =T57+SUM(Y56,X56,W56,V56) -> 195 | Z62: =U57+SUM(Z56) -> 195 | AA62: =V57+SUM(AA56,Y56,X56,W56) -> 195 | AB62: =W57+SUM(AB56,AA56,Y56,X56) -> 195 | AC62: =X57+SUM(AC56,AB56,AA56,Y56) -> 193 | AD62: =Y57+SUM(AD56,AC56,AB56,AA56) -> 193 | AE62: =Z57+SUM(AE56) -> 193 | AF62: =AA57+SUM(AF56,AD56,AC56,AB56) -> 193 | AG62: =AB57+SUM(AG56,AF56,AD56,AC56) -> 199 | AH62: =AC57+SUM(AH56,AG56,AF56,AD56) -> 200 | AI62: =AD57+SUM(AI56,AH56,AG56,AF56) -> 199 | AJ62: =AE57+SUM(AJ56) -> 199 | AK62: =AF57+SUM(AK56,AI56,AH56,AG56) -> 200 | AL62: =AG57+SUM(AL56,AK56,AI56,AH56) -> 200 | AM62: =AH57+SUM(AM56,AL56,AK56,AI56) -> 200 | AN62: =AI57+SUM(AN56,AM56,AL56,AK56) -> 199 | AO62: =AJ57+SUM(AO56) -> 199 | AP62: =AK57+SUM(AP56,AN56,AM56,AL56) -> 199 | AQ62: =AL57+SUM(AQ56,AP56,AN56,AM56) -> 201 | AR62: =AM57+SUM(AR56,AQ56,AP56,AN56) -> 200 | AS62: =AN57+SUM(AS56,AR56,AQ56,AP56) -> 194 | AT62: =AO57+SUM(AT56) -> 194 | AU62: =AP57+SUM(AU56,AS56,AR56,AQ56) -> 192 | AV62: =AQ57+SUM(AV56,AU56,AS56,AR56) -> 191 | AW62: =AR57+SUM(AW56,AV56,AU56,AS56) -> 192 | AX62: =AS57+SUM(AX56,AW56,AV56,AU56) -> 184 | AY62: =AT57+SUM(AY56) -> 184 | AZ62: =AU57+SUM(AZ56,AX56,AW56,AV56) -> 185 | BA62: =AV57+SUM(BA56,AZ56,AX56,AW56) -> 185 | BB62: =AW57+SUM(BB56,BA56,AZ56,AX56) -> 183 | BC62: =AX57+SUM(BC56,BB56,BA56,AZ56) -> 181 | BD62: =AY57+SUM(BD56) -> 181 | BE62: =AZ57+SUM(BE56,BC56,BB56,BA56) -> 182 | BF62: =BA57+SUM(BF56,BE56,BC56,BB56) -> 183 | BG62: =BB57+SUM(BG56,BF56,BE56,BC56) -> 184 | BH62: =BC57+SUM(BH56,BG56,BF56,BE56) -> 178 | BI62: =BD57+SUM(BI56) -> 178 | BJ62: =BE57+SUM(BJ56,BH56,BG56,BF56) -> 177 | BK62: =BF57+SUM(BK56,BJ56,BH56,BG56) -> 178 | BL62: =BG57+SUM(BL56,BK56,BJ56,BH56) -> 178 | BM62: =BH57+SUM(BM56,BL56,BK56,BJ56) -> 177 | BN62: =BI57+SUM(BN56) -> 177 | BO62: =BJ57+SUM(BO56,BM56,BL56,BK56) -> 176 | BP62: =BK57+SUM(BP56,BO56,BM56,BL56) -> 174 | BQ62: =BL57+SUM(BQ56,BP56,BO56,BM56) -> 172 | BR62: =BM57+SUM(BR56,BQ56,BP56,BO56) -> 170 | BS62: =BN57+SUM(BS56) -> 170 | BT62: =BS57+SUM(BT56) -> 170 | BU62: =BT57+SUM(BU56) -> 170 | BV62: =BU57+SUM(BV56) -> 170
A63: Pottery Barn new stores, # of stores | D63: =SUM(D55) -> 3 | E63: =SUM(E55) -> 18 | F63: =SUM(F55) -> 8 | K63: =SUM(K55) -> 7 | L63: =SUM(L55,J55,I55,H55) -> 5 | M63: =SUM(M55,L55,J55,I55) -> 4 | N63: =SUM(N55,M55,L55,J55) -> 6 | O63: =SUM(O55,N55,M55,L55) -> 7 | P63: =SUM(P55) -> 7 | Q63: =SUM(Q55,O55,N55,M55) -> 5 | R63: =SUM(R55,Q55,O55,N55) -> 7 | S63: =SUM(S55,R55,Q55,O55) -> 6 | T63: =SUM(T55,S55,R55,Q55) -> 4 | U63: =SUM(U55) -> 4 | V63: =SUM(V55,T55,S55,R55) -> 7 | W63: =SUM(W55,V55,T55,S55) -> 6 | X63: =SUM(X55,W55,V55,T55) -> 5 | Y63: =SUM(Y55,X55,W55,V55) -> 6 | Z63: =SUM(Z55) -> 6 | AA63: =SUM(AA55,Y55,X55,W55) -> 4 | AB63: =SUM(AB55,AA55,Y55,X55) -> 9 | AC63: =SUM(AC55,AB55,AA55,Y55) -> 9 | AD63: =SUM(AD55,AC55,AB55,AA55) -> 10 | AE63: =SUM(AE55) -> 10 | AF63: =SUM(AF55,AD55,AC55,AB55) -> 10 | AG63: =SUM(AG55,AF55,AD55,AC55) -> 6 | AH63: =SUM(AH55,AG55,AF55,AD55) -> 5 | AI63: =SUM(AI55,AH55,AG55,AF55) -> 6 | AJ63: =SUM(AJ55) -> 6 | AK63: =SUM(AK55,AI55,AH55,AG55) -> 5 | AL63: =SUM(AL55,AK55,AI55,AH55) -> 5 | AM63: =SUM(AM55,AL55,AK55,AI55) -> 5 | AN63: =SUM(AN55,AM55,AL55,AK55) -> 2 | AO63: =SUM(AO55) -> 2 | AP63: =SUM(AP55,AN55,AM55,AL55) -> 2 | AQ63: =SUM(AQ55,AP55,AN55,AM55) -> 0 | AR63: =SUM(AR55,AQ55,AP55,AN55) -> 1 | AS63: =SUM(AS55,AR55,AQ55,AP55) -> 1 | AT63: =SUM(AT55) -> 1 | AU63: =SUM(AU55,AS55,AR55,AQ55) -> 3 | AV63: =SUM(AV55,AU55,AS55,AR55) -> 4 | AW63: =SUM(AW55,AV55,AU55,AS55) -> 3 | AX63: =SUM(AX55,AW55,AV55,AU55) -> 4 | AY63: =SUM(AY55) -> 4 | AZ63: =SUM(AZ55,AX55,AW55,AV55) -> 3 | BA63: =SUM(BA55,AZ55,AX55,AW55) -> 4 | BB63: =SUM(BB55,BA55,AZ55,AX55) -> 6 | BC63: =SUM(BC55,BB55,BA55,AZ55) -> 7 | BD63: =SUM(BD55) -> 7 | BE63: =SUM(BE55,BC55,BB55,BA55) -> 6 | BF63: =SUM(BF55,BE55,BC55,BB55) -> 7 | BG63: =SUM(BG55,BF55,BE55,BC55) -> 7 | BH63: =SUM(BH55,BG55,BF55,BE55) -> 6 | BI63: =SUM(BI55) -> 6 | BJ63: =SUM(BJ55,BH55,BG55,BF55) -> 7 | BK63: =SUM(BK55,BJ55,BH55,BG55) -> 4 | BL63: =SUM(BL55,BK55,BJ55,BH55) -> 2 | BM63: =SUM(BM55,BL55,BK55,BJ55) -> 1 | BN63: =SUM(BN55) -> 1 | BO63: =SUM(BO55,BM55,BL55,BK55) -> 0 | BP63: =SUM(BP55,BO55,BM55,BL55) -> 0 | BQ63: =SUM(BQ55,BP55,BO55,BM55) -> 0 | BR63: =SUM(BR55,BQ55,BP55,BO55) -> 0 | BS63: =SUM(BS55) -> 0 | BT63: =SUM(BT55) -> 0 | BU63: =SUM(BU55) -> 0 | BV63: =SUM(BV55) -> 0
A65: Pottery Barn leased square footage per comp store (calculated), sq ft/store | D65: =D79/D62*1000 -> 13000 | E65: =E79/E62*1000 -> 13109.659 | F65: =F79/F62*1000 -> 13837.519 | K65: =K79/K62*1000 -> 13901.671 | L65: =L79/L62*1000 -> 13798.675 | M65: =M79/M62*1000 -> 13696.588 | N65: =N79/N62*1000 -> 13697.322 | O65: =O79/O62*1000 -> 13698.443 | P65: =O65 -> 13698.443 | Q65: =Q79/Q62*1000 -> 13700.014 | R65: =R79/R62*1000 -> 13700.014 | S65: =S79/S62*1000 -> 13700.014 | T65: =T79/T62*1000 -> 13802.072 | U65: =T65 -> 13802.072 | V65: =V79/V62*1000 -> 13802.072 | W65: =W79/W62*1000 -> 13801.026 | X65: =X79/X62*1000 -> 13800 | Y65: =Y79/Y62*1000 -> 13800 | Z65: =Y65 -> 13800 | AA65: =AA79/AA62*1000 -> 13800 | AB65: =AB79/AB62*1000 -> 13800 | AC65: =AC79/AC62*1000 -> 13800 | AD65: =AD79/AD62*1000 -> 13904.145 | AE65: =AD65 -> 13904.145 | AF65: =AF79/AF62*1000 -> 13799.46 | AG65: =AG79/AG62*1000 -> 13799.477 | AH65: =AH79/AH62*1000 -> 13900.479 | AI65: =AI79/AI62*1000 -> 13899.972 | AJ65: =AI65 -> 13899.972 | AK65: =AK79/AK62*1000 -> 13797.493 | AL65: =AL79/AL62*1000 -> 13798.518 | AM65: =AM79/AM62*1000 -> 13798.518 | AN65: =AN79/AN62*1000 -> 14097.01 | AO65: =AN65 -> 14097.01 | AP65: =AP79/AP62*1000 -> 14097.01 | AQ65: =AQ79/AQ62*1000 -> 14400 | AR65: =AR79/AR62*1000 -> 14400 | AS65: =AS79/AS62*1000 -> 14601.031 | AT65: =AS65 -> 14601.031 | AU65: =AU79/AU62*1000 -> 14601.031 | AV65: =AV79/AV62*1000 -> 14601.031 | AW65: =AW79/AW62*1000 -> 14498.421 | AX65: =AX79/AX62*1000 -> 14498.421 | AY65: =AX65 -> 14498.421 | AZ65: =AZ79/AZ62*1000 -> 14499.531 | BA65: =BA79/BA62*1000 -> 14500.079 | BB65: =BB79/BB62*1000 -> 14500.079 | BC65: =BC79/BC62*1000 -> 14500.009 | BD65: =BC65 -> 14500.009 | BE65: =BE79/BE62*1000 -> 14500 | BF65: =BF79/BF62*1000 -> 14603.277 | BG65: =BG79/BG62*1000 -> 14807.59 | BH65: =BH79/BH62*1000 -> 14802.449 | BI65: =BH65 -> 14802.449 | BJ65: =BJ79/BJ62*1000 -> 14802.449 | BK65: =BK79/BK62*1000 -> 15014.206 | BL65: =BL79/BL62*1000 -> 15011.818 | BM65: =BM79/BM62*1000 -> 15003.054 | BN65: =BM65 -> 15003.054 | BO65: =BO79/BO62*1000 -> 15106.46 | BP65: =BP79/BP62*1000 -> 15106.46 | BQ65: =BQ79/BQ62*1000 -> 15106.46 | BR65: =BR79/BR62*1000 -> 15106.46 | BS65: =BR65 -> 15106.46 | BT65: =BT79/BT62*1000 -> 15106.46 | BU65: =BU79/BU62*1000 -> 15106.46 | BV65: =BV79/BV62*1000 -> 15106.46
A66: Pottery Barn opened store size as a % of comp store (calculated), % | D66: =IFERROR(D68/D65,"n/a") -> 1.4948718 | E66: =IFERROR(E68/E65,"n/a") -> 1.5675465 | F66: =IFERROR(F68/F65,"n/a") -> 1.1083688 | K66: =IFERROR(K68/K65,"n/a") -> 0.79731006 | L66: =IFERROR(L68/L65,"n/a") -> 1.0037801 | M66: =IFERROR(M68/M65,"n/a") -> n/a | N66: =IFERROR(N68/N65,"n/a") -> 1.0001955 | O66: =IFERROR(O68/O65,"n/a") -> 1.0000159 | P66: =IFERROR(P68/P65,"n/a") -> 1.0032318 | Q66: =IFERROR(Q68/Q65,"n/a") -> n/a | R66: =IFERROR(R68/R65,"n/a") -> 0.99999949 | ... BJ66: =IFERROR(BJ68/BJ65,"n/a") -> 2.2430375 | BK66: 1 | BL66: 1 | BM66: 1 | BN66: =IFERROR(BN68/BN65,"n/a") -> 2.213046 | BO66: 1 | BP66: 1 | BQ66: 1 | BR66: 1 | BS66: =IFERROR(BS68/BS65,"n/a") -> n/a | BT66: 1 | BU66: 1 | BV66: 1
A67: Pottery Barn closed store size as a % of prior comp store (estimated), % | D67: 1 | E67: 1 | F67: 1 | K67: =K74/K56*1000/F65 -> 1 | L67: 1 | M67: 1 | N67: 1 | O67: 1 | P67: =SUM(L74*L67,M74*M67,N74*N67,O74*O67)/P74 -> 1 | Q67: 1 | R67: 1 | S67: 1 | T67: 1 | U67: =SUM(Q74*Q67,R74*R67,S74*S67,T74*T67)/U74 -> 1 | V67: 1 | W67: 1 | X67: 1 | Y67: 1 | Z67: =SUM(V74*V67,W74*W67,X74*X67,Y74*Y67)/Z74 -> 1 | AA67: 1 | AB67: 1 | AC67: 1 | AD67: 1 | AE67: =SUM(AA74*AA67,AB74*AB67,AC74*AC67,AD74*AD67)/AE74 -> 1 | AF67: 1 | AG67: 1 | AH67: 1 | AI67: 1 | AJ67: =SUM(AF74*AF67,AG74*AG67,AH74*AH67,AI74*AI67)/AJ74 -> 1 | AK67: 1 | AL67: 1 | AM67: 1 | AN67: 1 | AO67: =SUM(AK74*AK67,AL74*AL67,AM74*AM67,AN74*AN67)/AO74 -> 1 | AP67: 1 | AQ67: 1 | AR67: 1 | AS67: 1 | AT67: =SUM(AP74*AP67,AQ74*AQ67,AR74*AR67,AS74*AS67)/AT74 -> 1 | AU67: 1 | AV67: 1 | AW67: 1 | AX67: 1 | AY67: =SUM(AU74*AU67,AV74*AV67,AW74*AW67,AX74*AX67)/AY74 -> 1 | AZ67: 1 | BA67: 1 | BB67: 1 | BC67: 1 | BD67: =SUM(AZ74*AZ67,BA74*BA67,BB74*BB67,BC74*BC67)/BD74 -> 1 | BE67: 1 | BF67: 1 | BG67: 1 | BH67: 1 | BI67: =SUM(BE74*BE67,BF74*BF67,BG74*BG67,BH74*BH67)/BI74 -> 1 | BJ67: 1 | BK67: 1 | BL67: 1 | BM67: 1 | BN67: =SUM(BJ74*BJ67,BK74*BK67,BL74*BL67,BM74*BM67)/BN74 -> 1 | BO67: 1 | BP67: 1 | BQ67: 1 | BR67: 1 | BS67: =SUM(BO74*BO67,BP74*BP67,BQ74*BQ67,BR74*BR67)/BS74 -> 1 | BT67: 1 | BU67: 1 | BV67: 1
A68: Pottery Barn leased square footage per opened store (calculated), sq ft/store | D68: =IFERROR(D73/D55*1000,"n/a") -> 19433.333 | E68: =IFERROR(E73/E55*1000,"n/a") -> 20550 | F68: =IFERROR(F73/F55*1000,"n/a") -> 15337.074 | K68: =IFERROR(K73/K55*1000,"n/a") -> 11083.942 | L68: =IFERROR(L73/L55*1000,"n/a") -> 13850.835 | M68: =IFERROR(M73/M55*1000,"n/a") -> n/a | N68: =IFERROR(N73/N55*1000,"n/a") -> 13700 | O68: =IFERROR(O73/O55*1000,"n/a") -> 13698.661 | P68: =IFERROR(P73/P55*1000,"n/a") -> 13742.713 | Q68: =IFERROR(Q73/Q55*1000,"n/a") -> n/a | R68: =IFERROR(R73/R55*1000,"n/a") -> 13700.007 | ... BJ68: =IFERROR(BJ73/BJ55*1000,"n/a") -> 33202.449 | BK68: =IF(BK55=0,"n/a",BK65*BK66) -> n/a | BL68: =IF(BL55=0,"n/a",BL65*BL66) -> n/a | BM68: =IF(BM55=0,"n/a",BM65*BM66) -> n/a | BN68: =IFERROR(BN73/BN55*1000,"n/a") -> 33202.449 | BO68: =IF(BO55=0,"n/a",BO65*BO66) -> n/a | BP68: =IF(BP55=0,"n/a",BP65*BP66) -> n/a | BQ68: =IF(BQ55=0,"n/a",BQ65*BQ66) -> n/a | BR68: =IF(BR55=0,"n/a",BR65*BR66) -> n/a | BS68: =IFERROR(BS73/BS55*1000,"n/a") -> n/a | BT68: =IF(BT55=0,"n/a",BT65*BT66) -> n/a | BU68: =IF(BU55=0,"n/a",BU65*BU66) -> n/a | BV68: =IF(BV55=0,"n/a",BV65*BV66) -> n/a
A69: Pottery Barn leased square footage per new store (calculated), sq ft/store | D69: =IFERROR(D73/D55*1000,"n/a") -> 19433.333 | E69: =IFERROR(E73/E55*1000,"n/a") -> 20550 | F69: =IFERROR(F73/F55*1000,"n/a") -> 15337.074 | K69: =IFERROR(K73/K55*1000,"n/a") -> 11083.942 | L69: =IFERROR(SUM(L73,J73,I73,H73)/SUM(L55,J55,I55,H55)*1000,"n/a") -> 13850.349 | M69: =IFERROR(SUM(M73,L73,J73,I73)/SUM(M55,L55,J55,I55)*1000,"n/a") -> 13862.936 | N69: =IFERROR(SUM(N73,M73,L73,J73)/SUM(N55,M55,L55,J55)*1000,"n/a") -> 13785.704 | O69: =IFERROR(SUM(O73,N73,M73,L73)/SUM(O55,N55,M55,L55)*1000,"n/a") -> 13742.713 | P69: =O69 -> 13742.713 | Q69: =IFERROR(SUM(Q73,O73,N73,M73)/SUM(Q55,O55,N55,M55)*1000,"n/a") -> 13699.464 | R69: =IFERROR(SUM(R73,Q73,O73,N73)/SUM(R55,Q55,O55,N55)*1000,"n/a") -> 13699.619 | S69: =IFERROR(SUM(S73,R73,Q73,O73)/SUM(S55,R55,Q55,O55)*1000,"n/a") -> 13699.558 | T69: =IFERROR(SUM(T73,S73,R73,Q73)/SUM(T55,S55,R55,Q55)*1000,"n/a") -> 13700.007 | U69: =T69 -> 13700.007 | V69: =IFERROR(SUM(V73,T73,S73,R73)/SUM(V55,T55,S55,R55)*1000,"n/a") -> 13742.861 | W69: =IFERROR(SUM(W73,V73,T73,S73)/SUM(W55,V55,T55,S55)*1000,"n/a") -> 13766.669 | X69: =IFERROR(SUM(X73,W73,V73,T73)/SUM(X55,W55,V55,T55)*1000,"n/a") -> 13800 | Y69: =IFERROR(SUM(Y73,X73,W73,V73)/SUM(Y55,X55,W55,V55)*1000,"n/a") -> 17150 | Z69: =Y69 -> 17150 | AA69: =IFERROR(SUM(AA73,Y73,X73,W73)/SUM(AA55,Y55,X55,W55)*1000,"n/a") -> 13800 | AB69: =IFERROR(SUM(AB73,AA73,Y73,X73)/SUM(AB55,AA55,Y55,X55)*1000,"n/a") -> 13800 | AC69: =IFERROR(SUM(AC73,AB73,AA73,Y73)/SUM(AC55,AB55,AA55,Y55)*1000,"n/a") -> 16044.444 | AD69: =IFERROR(SUM(AD73,AC73,AB73,AA73)/SUM(AD55,AC55,AB55,AA55)*1000,"n/a") -> 13820 | AE69: =AD69 -> 13820 | AF69: =IFERROR(SUM(AF73,AD73,AC73,AB73)/SUM(AF55,AD55,AC55,AB55)*1000,"n/a") -> 15840.415 | AG69: =IFERROR(SUM(AG73,AF73,AD73,AC73)/SUM(AG55,AF55,AD55,AC55)*1000,"n/a") -> 17234.024 | AH69: =IFERROR(SUM(AH73,AG73,AF73,AD73)/SUM(AH55,AG55,AF55,AD55)*1000,"n/a") -> 13880.829 | AI69: =IFERROR(SUM(AI73,AH73,AG73,AF73)/SUM(AI55,AH55,AG55,AF55)*1000,"n/a") -> 24150.93 | AJ69: =AI69 -> 24150.93 | AK69: =IFERROR(SUM(AK73,AI73,AH73,AG73)/SUM(AK55,AI55,AH55,AG55)*1000,"n/a") -> 26200.288 | AL69: =IFERROR(SUM(AL73,AK73,AI73,AH73)/SUM(AL55,AK55,AI55,AH55)*1000,"n/a") -> 38459.285 | AM69: =IFERROR(SUM(AM73,AL73,AK73,AI73)/SUM(AM55,AL55,AK55,AI55)*1000,"n/a") -> 38459.285 | AN69: =IFERROR(SUM(AN73,AM73,AL73,AK73)/SUM(AN55,AM55,AL55,AK55)*1000,"n/a") -> 44547.493 | AO69: =AN69 -> 44547.493 | AP69: =IFERROR(SUM(AP73,AN73,AM73,AL73)/SUM(AP55,AN55,AM55,AL55)*1000,"n/a") -> 44547.493 | AQ69: =IFERROR(SUM(AQ73,AP73,AN73,AM73)/SUM(AQ55,AP55,AN55,AM55)*1000,"n/a") -> n/a | AR69: =IFERROR(SUM(AR73,AQ73,AP73,AN73)/SUM(AR55,AQ55,AP55,AN55)*1000,"n/a") -> 14400 | AS69: =IFERROR(SUM(AS73,AR73,AQ73,AP73)/SUM(AS55,AR55,AQ55,AP55)*1000,"n/a") -> 14400 | AT69: =AS69 -> 14400 | AU69: =IFERROR(SUM(AU73,AS73,AR73,AQ73)/SUM(AU55,AS55,AR55,AQ55)*1000,"n/a") -> 14534.021 | AV69: =IFERROR(SUM(AV73,AU73,AS73,AR73)/SUM(AV55,AU55,AS55,AR55)*1000,"n/a") -> 14550.773 | AW69: =IFERROR(SUM(AW73,AV73,AU73,AS73)/SUM(AW55,AV55,AU55,AS55)*1000,"n/a") -> 14601.031 | AX69: =IFERROR(SUM(AX73,AW73,AV73,AU73)/SUM(AX55,AW55,AV55,AU55)*1000,"n/a") -> 14572.616 | AY69: =AX69 -> 14572.616 | AZ69: =IFERROR(SUM(AZ73,AX73,AW73,AV73)/SUM(AZ55,AX55,AW55,AV55)*1000,"n/a") -> 14528.941 | BA69: =IFERROR(SUM(BA73,AZ73,AX73,AW73)/SUM(BA55,AZ55,AX55,AW55)*1000,"n/a") -> 19221.331 | BB69: =IFERROR(SUM(BB73,BA73,AZ73,AX73)/SUM(BB55,BA55,AZ55,AX55)*1000,"n/a") -> 23947.58 | BC69: =IFERROR(SUM(BC73,BB73,BA73,AZ73)/SUM(BC55,BB55,BA55,AZ55)*1000,"n/a") -> 22556.907 | BD69: =BC69 -> 22556.907 | BE69: =IFERROR(SUM(BE73,BC73,BB73,BA73)/SUM(BE55,BC55,BB55,BA55)*1000,"n/a") -> 23899.988 | BF69: =IFERROR(SUM(BF73,BE73,BC73,BB73)/SUM(BF55,BE55,BC55,BB55)*1000,"n/a") -> 25371.485 | BG69: =IFERROR(SUM(BG73,BF73,BE73,BC73)/SUM(BG55,BF55,BE55,BC55)*1000,"n/a") -> 20057.645 | BH69: =IFERROR(SUM(BH73,BG73,BF73,BE73)/SUM(BH55,BG55,BF55,BE55)*1000,"n/a") -> 20860.666 | BI69: =BH69 -> 20860.666 | BJ69: =IFERROR(SUM(BJ73,BH73,BG73,BF73)/SUM(BJ55,BH55,BG55,BF55)*1000,"n/a") -> 22623.778 | BK69: =IFERROR(SUM(BK73,BJ73,BH73,BG73)/SUM(BK55,BJ55,BH55,BG55)*1000,"n/a") -> 19066.611 | BL69: =IFERROR(SUM(BL73,BK73,BJ73,BH73)/SUM(BL55,BK55,BJ55,BH55)*1000,"n/a") -> 23331.583 | BM69: =IFERROR(SUM(BM73,BL73,BK73,BJ73)/SUM(BM55,BL55,BK55,BJ55)*1000,"n/a") -> 33202.449 | BN69: =BM69 -> 33202.449 | BO69: =IFERROR(SUM(BO73,BM73,BL73,BK73)/SUM(BO55,BM55,BL55,BK55)*1000,"n/a") -> n/a | BP69: =IFERROR(SUM(BP73,BO73,BM73,BL73)/SUM(BP55,BO55,BM55,BL55)*1000,"n/a") -> n/a | BQ69: =IFERROR(SUM(BQ73,BP73,BO73,BM73)/SUM(BQ55,BP55,BO55,BM55)*1000,"n/a") -> n/a | BR69: =IFERROR(SUM(BR73,BQ73,BP73,BO73)/SUM(BR55,BQ55,BP55,BO55)*1000,"n/a") -> n/a | BS69: =BR69 -> n/a | BT69: =IFERROR(BT73/BT55*1000,"n/a") -> n/a | BU69: =IFERROR(BU73/BU55*1000,"n/a") -> n/a | BV69: =IFERROR(BV73/BV55*1000,"n/a") -> n/a
A70: Pottery Barn Leased Square Footage Per Store, sq ft | C70: =C440 -> 13000 | D70: =D440 -> 13100 | E70: =E440 -> 13800 | F70: =F440 -> 13900 | G70: =G440 -> 13800 | H70: =H440 -> 13800 | I70: =I440 -> 13800 | J70: =J440 -> 13800 | ... BJ70: =BJ440 -> 15100 | BK70: =BK76/BK57*1000 -> 15103.27 | BL70: =BL76/BL57*1000 -> 15104.259 | BM70: =BM76/BM57*1000 -> 15105.298 | BN70: =BN76/BN57*1000 -> 15105.298 | BO70: =BO76/BO57*1000 -> 15106.46 | BP70: =BP76/BP57*1000 -> 15106.46 | BQ70: =BQ76/BQ57*1000 -> 15106.46 | BR70: =BR76/BR57*1000 -> 15106.46 | ... BV70: =BV76/BV57*1000 -> 15106.46
A72: Pottery Barn Leased Square Footage (Calculated) - BoP, 000s sq ft | D72: =C76 -> 2587 | E72: =D76 -> 2528.3 | F72: =E76 -> 2677.2 | G72: =F76 -> 2668.8 | H72: =G76 -> 2691 | I72: =H76 -> 2704.8 | J72: =I76 -> 2704.8 | K72: =F76 -> 2668.8 | L72: =K76 -> 2677.2 | M72: =L76 -> 2691 | N72: =M76 -> 2671.5 | O72: =N76 -> 2712.6 | P72: =K76 -> 2677.2 | Q72: =P76 -> 2726.3 | R72: =Q76 -> 2712.6 | S72: =R76 -> 2726.3 | T72: =S76 -> 2740 | U72: =P76 -> 2726.3 | V72: =U76 -> 2718.6 | W72: =V76 -> 2760 | X72: =W76 -> 2773.8 | Y72: =X76 -> 2787.6 | Z72: =U76 -> 2718.6 | AA72: =Z76 -> 2793.9 | AB72: =AA76 -> 2746.2 | AC72: =AB76 -> 2815.2 | AD72: =AC76 -> 2807.8 | AE72: =Z76 -> 2793.9 | AF72: =AE76 -> 2821.7 | AG72: =AF76 -> 2821.7 | AH72: =AG76 -> 2849.5 | AI72: =AH76 -> 2849.5 | AJ72: =AE76 -> 2821.7 | AK72: =AJ76 -> 2911 | AL72: =AK76 -> 2890.5 | AM72: =AL76 -> 2952 | AN72: =AM76 -> 2952 | AO72: =AJ76 -> 2911 | AP72: =AO76 -> 2894.4 | AQ72: =AP76 -> 2894.4 | AR72: =AQ76 -> 2894.4 | AS72: =AR76 -> 2894.4 | AT72: =AO76 -> 2894.4 | AU72: =AT76 -> 2847 | AV72: =AU76 -> 2847 | AW72: =AV76 -> 2847 | AX72: =AW76 -> 2827.5 | AY72: =AT76 -> 2847 | AZ72: =AY76 -> 2726 | BA72: =AZ76 -> 2726 | BB72: =BA76 -> 2759.4 | BC72: =BB76 -> 2797.2 | BD72: =AY76 -> 2726 | BE72: =BD76 -> 2782.4 | BF72: =BE76 -> 2782.4 | BG72: =BF76 -> 2850 | BH72: =BG76 -> 2865 | BI72: =BD76 -> 2782.4 | BJ72: =BI76 -> 2760 | BK72: =BJ76 -> 2778.4 | BL72: =BK76 -> 2748.7951 | BM72: =BL76 -> 2718.7667 | BN72: =BI76 -> 2760 | BO72: =BN76 -> 2688.7431 | BP72: =BO76 -> 2658.7369 | BQ72: =BP76 -> 2628.524 | BR72: =BQ76 -> 2598.3111 | BS72: =BN76 -> 2688.7431 | BT72: =BS76 -> 2568.0982 | BU72: =BT76 -> 2568.0982 | BV72: =BU76 -> 2568.0982
A73: Pottery Barn opened store leased square footage (calculated), 000s sq ft | D73: =IF(D55=0,0,D75-D74) -> 58.3 | E73: =IF(E55=0,0,E75-E74) -> 369.9 | F73: =IF(F55=0,0,F75-F74) -> 122.69659 | G73: =IF(G55=0,0,G75-G74) -> 36.037519 | H73: =IF(H55=0,0,H75-H74) -> 13.8 | I73: =IF(I55=0,0,I75-I74) -> 13.837519 | J73: =IF(J55=0,0,J75-J74) -> 13.912556 | K73: =K75-K74 -> 77.587593 | L73: =IF(L55=0,0,L75-L74) -> 27.701671 | M73: =IF(M55=0,0,M75-M74) -> 0 | N73: =IF(N55=0,0,N75-N74) -> 41.1 | O73: =IF(O55=0,0,O75-O74) -> 27.397322 | P73: =P75-P74 -> 96.198992 | Q73: =IF(Q55=0,0,Q75-Q74) -> 0 | R73: =IF(R55=0,0,R75-R74) -> 27.400014 | S73: =IF(S55=0,0,S75-S74) -> 27.400014 | T73: =IF(T55=0,0,T75-T74) -> 0 | U73: =U75-U74 -> 54.800028 | V73: =IF(V55=0,0,V75-V74) -> 41.4 | W73: =IF(W55=0,0,W75-W74) -> 13.8 | X73: =IF(X55=0,0,X75-X74) -> 13.8 | Y73: =IF(Y55=0,0,Y75-Y74) -> 33.9 | Z73: =Z75-Z74 -> 102.9 | AA73: =IF(AA55=0,0,AA75-AA74) -> -6.3 | AB73: =IF(AB55=0,0,AB75-AB74) -> 82.8 | AC73: =IF(AC55=0,0,AC75-AC74) -> 34 | AD73: =IF(AD55=0,0,AD75-AD74) -> 27.7 | AE73: =AE75-AE74 -> 138.2 | AF73: =IF(AF55=0,0,AF75-AF74) -> 13.904145 | AG73: =IF(AG55=0,0,AG75-AG74) -> 27.8 | AH73: =IF(AH55=0,0,AH75-AH74) -> 0 | AI73: =IF(AI55=0,0,AI75-AI74) -> 103.20144 | AJ73: =AJ75-AJ74 -> 144.90558 | AK73: =IF(AK55=0,0,AK75-AK74) -> 0 | AL73: =IF(AL55=0,0,AL75-AL74) -> 89.094986 | AM73: =IF(AM55=0,0,AM75-AM74) -> 0 | AN73: =IF(AN55=0,0,AN75-AN74) -> 0 | AO73: =AO75-AO74 -> 89.094986 | AP73: =IF(AP55=0,0,AP75-AP74) -> 0 | AQ73: =IF(AQ55=0,0,AQ75-AQ74) -> 0 | AR73: =IF(AR55=0,0,AR75-AR74) -> 14.4 | AS73: =IF(AS55=0,0,AS75-AS74) -> 0 | AT73: =AT75-AT74 -> 14.4 | AU73: =IF(AU55=0,0,AU75-AU74) -> 29.202062 | AV73: =IF(AV55=0,0,AV75-AV74) -> 14.601031 | AW73: =IF(AW55=0,0,AW75-AW74) -> 0 | AX73: =IF(AX55=0,0,AX75-AX74) -> 14.487371 | AY73: =AY75-AY74 -> 58.290464 | AZ73: =IF(AZ55=0,0,AZ75-AZ74) -> 14.498421 | BA73: =IF(BA55=0,0,BA75-BA74) -> 47.899531 | BB73: =IF(BB55=0,0,BB75-BB74) -> 66.800159 | BC73: =IF(BC55=0,0,BC75-BC74) -> 28.700238 | BD73: =BD75-BD74 -> 157.89835 | BE73: =IF(BE55=0,0,BE75-BE74) -> 0 | BF73: =IF(BF55=0,0,BF75-BF74) -> 82.1 | BG73: =IF(BG55=0,0,BG75-BG74) -> 29.603277 | BH73: =IF(BH55=0,0,BH75-BH74) -> 13.460717 | BI73: =BI75-BI74 -> 125.16399 | BJ73: =IF(BJ55=0,0,BJ75-BJ74) -> 33.202449 | BK73: =IF(BK55=0,0,BK68*BK55/1000) -> 0 | BL73: =IF(BL55=0,0,BL68*BL55/1000) -> 0 | BM73: =IF(BM55=0,0,BM68*BM55/1000) -> 0 | BN73: =SUM(BJ73,BK73,BL73,BM73) -> 33.202449 | BO73: =IF(BO55=0,0,BO68*BO55/1000) -> 0 | BP73: =IF(BP55=0,0,BP68*BP55/1000) -> 0 | BQ73: =IF(BQ55=0,0,BQ68*BQ55/1000) -> 0 | BR73: =IF(BR55=0,0,BR68*BR55/1000) -> 0 | BS73: =SUM(BO73,BP73,BQ73,BR73) -> 0 | BT73: =IF(BT55=0,0,BT68*BT55/1000) -> 0 | BU73: =IF(BU55=0,0,BU68*BU55/1000) -> 0 | BV73: =IF(BV55=0,0,BV68*BV55/1000) -> 0
A74: Pottery Barn closed store leased square footage (calculated), 000s sq ft | D74: =IF(D55=0,D75-D73,C70*D67*D56/1000) -> -117 | E74: =IF(E55=0,E75-E73,D65*E67*E56/1000) -> -221 | F74: =IF(F55=0,F75-F73,E65*F67*F56/1000) -> -131.09659 | G74: =IF(G55=0,G75-G73,F65*G56/1000) -> -13.837519 | H74: =IF(H55=0,H75-H73,F65*H56/1000) -> 0 | I74: =IF(I55=0,I75-I73,F65*I56/1000) -> -13.837519 | J74: =IF(J55=0,J75-J73,F65*J56/1000) -> -41.512556 | K74: =SUM(G74,H74,I74,J74) -> -69.187593 | L74: =IF(L55=0,L75-L73,K65*L67*L56/1000) -> -13.901671 | M74: =IF(M55=0,M75-M73,L65*M67*M56/1000) -> -19.5 | N74: =IF(N55=0,N75-N73,M65*N67*N56/1000) -> 0 | O74: =IF(O55=0,O75-O73,N65*O67*O56/1000) -> -13.697322 | P74: =SUM(L74,M74,N74,O74) -> -47.098992 | Q74: =IF(Q55=0,Q75-Q73,P65*Q67*Q56/1000) -> -13.7 | R74: =IF(R55=0,R75-R73,Q65*R67*R56/1000) -> -13.700014 | S74: =IF(S55=0,S75-S73,R65*S67*S56/1000) -> -13.700014 | T74: =IF(T55=0,T75-T73,S65*T67*T56/1000) -> -21.4 | U74: =SUM(Q74,R74,S74,T74) -> -62.500028 | V74: =IF(V55=0,V75-V73,U65*V67*V56/1000) -> 0 | W74: =IF(W55=0,W75-W73,V65*W67*W56/1000) -> 0 | X74: =IF(X55=0,X75-X73,W65*X67*X56/1000) -> 0 | Y74: =IF(Y55=0,Y75-Y73,X65*Y67*Y56/1000) -> -27.6 | Z74: =SUM(V74,W74,X74,Y74) -> -27.6 | AA74: =IF(AA55=0,AA75-AA73,Z65*AA67*AA56/1000) -> -41.4 | AB74: =IF(AB55=0,AB75-AB73,AA65*AB67*AB56/1000) -> -13.8 | AC74: =IF(AC55=0,AC75-AC73,AB65*AC67*AC56/1000) -> -41.4 | AD74: =IF(AD55=0,AD75-AD73,AC65*AD67*AD56/1000) -> -13.8 | AE74: =SUM(AA74,AB74,AC74,AD74) -> -110.4 | AF74: =IF(AF55=0,AF75-AF73,AE65*AF67*AF56/1000) -> -13.904145 | AG74: =IF(AG55=0,AG75-AG73,AF65*AG67*AG56/1000) -> 0 | AH74: =IF(AH55=0,AH75-AH73,AG65*AH67*AH56/1000) -> 0 | AI74: =IF(AI55=0,AI75-AI73,AH65*AI67*AI56/1000) -> -41.701438 | AJ74: =SUM(AF74,AG74,AH74,AI74) -> -55.605583 | AK74: =IF(AK55=0,AK75-AK73,AJ65*AK67*AK56/1000) -> -20.5 | AL74: =IF(AL55=0,AL75-AL73,AK65*AL67*AL56/1000) -> -27.594986 | AM74: =IF(AM55=0,AM75-AM73,AL65*AM67*AM56/1000) -> 0 | AN74: =IF(AN55=0,AN75-AN73,AM65*AN67*AN56/1000) -> -57.6 | AO74: =SUM(AK74,AL74,AM74,AN74) -> -105.69499 | AP74: =IF(AP55=0,AP75-AP73,AO65*AP67*AP56/1000) -> 0 | AQ74: =IF(AQ55=0,AQ75-AQ73,AP65*AQ67*AQ56/1000) -> 0 | AR74: =IF(AR55=0,AR75-AR73,AQ65*AR67*AR56/1000) -> -14.4 | AS74: =IF(AS55=0,AS75-AS73,AR65*AS67*AS56/1000) -> -47.4 | AT74: =SUM(AP74,AQ74,AR74,AS74) -> -61.8 | AU74: =IF(AU55=0,AU75-AU73,AT65*AU67*AU56/1000) -> -29.202062 | AV74: =IF(AV55=0,AV75-AV73,AU65*AV67*AV56/1000) -> -14.601031 | AW74: =IF(AW55=0,AW75-AW73,AV65*AW67*AW56/1000) -> -19.5 | AX74: =IF(AX55=0,AX75-AX73,AW65*AX67*AX56/1000) -> -115.98737 | AY74: =SUM(AU74,AV74,AW74,AX74) -> -179.29046 | AZ74: =IF(AZ55=0,AZ75-AZ73,AY65*AZ67*AZ56/1000) -> -14.498421 | BA74: =IF(BA55=0,BA75-BA73,AZ65*BA67*BA56/1000) -> -14.499531 | BB74: =IF(BB55=0,BB75-BB73,BA65*BB67*BB56/1000) -> -29.000159 | BC74: =IF(BC55=0,BC75-BC73,BB65*BC67*BC56/1000) -> -43.500238 | BD74: =SUM(AZ74,BA74,BB74,BC74) -> -101.49835 | BE74: =IF(BE55=0,BE75-BE73,BD65*BE67*BE56/1000) -> 0 | BF74: =IF(BF55=0,BF75-BF73,BE65*BF67*BF56/1000) -> -14.5 | BG74: =IF(BG55=0,BG75-BG73,BF65*BG67*BG56/1000) -> -14.603277 | BH74: =IF(BH55=0,BH75-BH73,BG65*BH67*BH56/1000) -> -118.46072 | BI74: =SUM(BE74,BF74,BG74,BH74) -> -147.56399 | BJ74: =IF(BJ55=0,BJ75-BJ73,BI65*BJ67*BJ56/1000) -> -14.802449 | BK74: =BJ65*BK67*BK56/1000 -> -29.604899 | BL74: =BK65*BL67*BL56/1000 -> -30.028412 | BM74: =BL65*BM67*BM56/1000 -> -30.023635 | BN74: =SUM(BJ74,BK74,BL74,BM74) -> -104.4594 | BO74: =BN65*BO67*BO56/1000 -> -30.006109 | BP74: =BO65*BP67*BP56/1000 -> -30.21292 | BQ74: =BP65*BQ67*BQ56/1000 -> -30.21292 | BR74: =BQ65*BR67*BR56/1000 -> -30.21292 | BS74: =SUM(BO74,BP74,BQ74,BR74) -> -120.64487 | BT74: =BS65*BT67*BT56/1000 -> 0 | BU74: =BT65*BU67*BU56/1000 -> 0 | BV74: =BU65*BV67*BV56/1000 -> 0
A75: Pottery Barn net leased square footage addition (calculated), 000s sq ft | D75: =D76-D72 -> -58.7 | E75: =E76-E72 -> 148.9 | F75: =F76-F72 -> -8.4 | G75: =G76-G72 -> 22.2 | H75: =H76-H72 -> 13.8 | I75: =I76-I72 -> 0 | J75: =J76-J72 -> -27.6 | K75: =K76-K72 -> 8.4 | ... BJ75: =BJ76-BJ72 -> 18.4 | BK75: =SUM(BK73:BK74) -> -29.604899 | BL75: =SUM(BL73:BL74) -> -30.028412 | BM75: =SUM(BM73:BM74) -> -30.023635 | BN75: =SUM(BN73:BN74) -> -71.256946 | BO75: =SUM(BO73:BO74) -> -30.006109 | BP75: =SUM(BP73:BP74) -> -30.21292 | BQ75: =SUM(BQ73:BQ74) -> -30.21292 | BR75: =SUM(BR73:BR74) -> -30.21292 | ... BV75: =SUM(BV73:BV74) -> 0
A76: Pottery Barn Leased Square Footage (Calculated) - EoP, 000s sq ft | C76: =C57*C70/1000 -> 2587 | D76: =D57*D70/1000 -> 2528.3 | E76: =E57*E70/1000 -> 2677.2 | F76: =F57*F70/1000 -> 2668.8 | G76: =G57*G70/1000 -> 2691 | H76: =H57*H70/1000 -> 2704.8 | I76: =I57*I70/1000 -> 2704.8 | J76: =J57*J70/1000 -> 2677.2 | ... BJ76: =BJ57*BJ70/1000 -> 2778.4 | BK76: =BK72+BK75 -> 2748.7951 | BL76: =BL72+BL75 -> 2718.7667 | BM76: =BM72+BM75 -> 2688.7431 | BN76: =BN72+BN75 -> 2688.7431 | BO76: =BO72+BO75 -> 2658.7369 | BP76: =BP72+BP75 -> 2628.524 | BQ76: =BQ72+BQ75 -> 2598.3111 | BR76: =BR72+BR75 -> 2568.0982 | ... BV76: =BV72+BV75 -> 2568.0982
A77: Pottery Barn Leased Square Footage (Calculated) - Average, 000s sq ft | D77: =AVERAGE(D76,D72) -> 2557.65 | E77: =AVERAGE(E76,E72) -> 2602.75 | F77: =AVERAGE(F76,F72) -> 2673 | G77: =AVERAGE(G76,G72) -> 2679.9 | H77: =AVERAGE(H76,H72) -> 2697.9 | I77: =AVERAGE(I76,I72) -> 2704.8 | J77: =AVERAGE(J76,J72) -> 2691 | K77: =SUM(G77*G$3,H77*H$3,I77*I$3,J77*J$3)/K$3 -> 2693.4 | L77: =AVERAGE(L76,L72) -> 2684.1 | M77: =AVERAGE(M76,M72) -> 2681.25 | N77: =AVERAGE(N76,N72) -> 2692.05 | O77: =AVERAGE(O76,O72) -> 2719.45 | P77: =SUM(L77*L$3,M77*M$3,N77*N$3,O77*O$3)/P$3 -> 2694.2125 | Q77: =AVERAGE(Q76,Q72) -> 2719.45 | R77: =AVERAGE(R76,R72) -> 2719.45 | S77: =AVERAGE(S76,S72) -> 2733.15 | T77: =AVERAGE(T76,T72) -> 2729.3 | U77: =SUM(Q77*Q$3,R77*R$3,S77*S$3,T77*T$3)/U$3 -> 2725.3375 | V77: =AVERAGE(V76,V72) -> 2739.3 | W77: =AVERAGE(W76,W72) -> 2766.9 | X77: =AVERAGE(X76,X72) -> 2780.7 | Y77: =AVERAGE(Y76,Y72) -> 2790.75 | Z77: =SUM(V77*V$3,W77*W$3,X77*X$3,Y77*Y$3)/Z$3 -> 2769.4125 | AA77: =AVERAGE(AA76,AA72) -> 2770.05 | AB77: =AVERAGE(AB76,AB72) -> 2780.7 | AC77: =AVERAGE(AC76,AC72) -> 2811.5 | AD77: =AVERAGE(AD76,AD72) -> 2814.75 | AE77: =SUM(AA77*AA$3,AB77*AB$3,AC77*AC$3,AD77*AD$3)/AE$3 -> 2794.25 | AF77: =AVERAGE(AF76,AF72) -> 2821.7 | AG77: =AVERAGE(AG76,AG72) -> 2835.6 | AH77: =AVERAGE(AH76,AH72) -> 2849.5 | AI77: =AVERAGE(AI76,AI72) -> 2880.25 | AJ77: =SUM(AF77*AF$3,AG77*AG$3,AH77*AH$3,AI77*AI$3)/AJ$3 -> 2847.3943 | AK77: =AVERAGE(AK76,AK72) -> 2900.75 | AL77: =AVERAGE(AL76,AL72) -> 2921.25 | AM77: =AVERAGE(AM76,AM72) -> 2952 | AN77: =AVERAGE(AN76,AN72) -> 2923.2 | AO77: =SUM(AK77*AK$3,AL77*AL$3,AM77*AM$3,AN77*AN$3)/AO$3 -> 2924.3 | AP77: =AVERAGE(AP76,AP72) -> 2894.4 | AQ77: =AVERAGE(AQ76,AQ72) -> 2894.4 | AR77: =AVERAGE(AR76,AR72) -> 2894.4 | AS77: =AVERAGE(AS76,AS72) -> 2870.7 | AT77: =SUM(AP77*AP$3,AQ77*AQ$3,AR77*AR$3,AS77*AS$3)/AT$3 -> 2888.475 | AU77: =AVERAGE(AU76,AU72) -> 2847 | AV77: =AVERAGE(AV76,AV72) -> 2847 | AW77: =AVERAGE(AW76,AW72) -> 2837.25 | AX77: =AVERAGE(AX76,AX72) -> 2776.75 | AY77: =SUM(AU77*AU$3,AV77*AV$3,AW77*AW$3,AX77*AX$3)/AY$3 -> 2827 | AZ77: =AVERAGE(AZ76,AZ72) -> 2726 | BA77: =AVERAGE(BA76,BA72) -> 2742.7 | BB77: =AVERAGE(BB76,BB72) -> 2778.3 | BC77: =AVERAGE(BC76,BC72) -> 2789.8 | BD77: =SUM(AZ77*AZ$3,BA77*BA$3,BB77*BB$3,BC77*BC$3)/BD$3 -> 2759.2 | BE77: =AVERAGE(BE76,BE72) -> 2782.4 | BF77: =AVERAGE(BF76,BF72) -> 2816.2 | BG77: =AVERAGE(BG76,BG72) -> 2857.5 | BH77: =AVERAGE(BH76,BH72) -> 2812.5 | BI77: =SUM(BE77*BE$3,BF77*BF$3,BG77*BG$3,BH77*BH$3)/BI$3 -> 2817.15 | BJ77: =AVERAGE(BJ76,BJ72) -> 2769.2 | BK77: =AVERAGE(BK76,BK72) -> 2763.5976 | BL77: =AVERAGE(BL76,BL72) -> 2733.7809 | BM77: =AVERAGE(BM76,BM72) -> 2703.7549 | BN77: =SUM(BJ77*BJ$3,BK77*BK$3,BL77*BL$3,BM77*BM$3)/BN$3 -> 2741.8507 | BO77: =AVERAGE(BO76,BO72) -> 2673.74 | BP77: =AVERAGE(BP76,BP72) -> 2643.6305 | BQ77: =AVERAGE(BQ76,BQ72) -> 2613.4176 | BR77: =AVERAGE(BR76,BR72) -> 2583.2046 | BS77: =SUM(BO77*BO$3,BP77*BP$3,BQ77*BQ$3,BR77*BR$3)/BS$3 -> 2628.4982 | BT77: =AVERAGE(BT76,BT72) -> 2568.0982 | BU77: =AVERAGE(BU76,BU72) -> 2568.0982 | BV77: =AVERAGE(BV76,BV72) -> 2568.0982
A79: Pottery Barn comp store leased square footage - EoP (calculated), 000s sq ft | D79: =D76-D82 -> 2470 | E79: =E76-E82 -> 2307.3 | F79: =F76-F82 -> 2546.1034 | K79: =K76-K82 -> 2599.6124 | L79: =L76-L82 -> 2621.7483 | M79: =M76-M82 -> 2616.0483 | N79: =N76-N82 -> 2629.8858 | O79: =O76-O82 -> 2630.101 | P79: =P76-P82 -> 2630.101 | Q79: =Q76-Q82 -> 2644.1027 | R79: =R76-R82 -> 2630.4027 | ... BJ79: =BJ76-BJ82 -> 2620.0336 | BK79: =BJ79+BF73+BK74 -> 2672.5287 | BL79: =BK79+BG73+BL74 -> 2672.1035 | BM79: =BL79+BH73+BM74 -> 2655.5406 | BN79: =BN76-BN82 -> 2655.5406 | BO79: =BN79+BJ73+BO74 -> 2658.7369 | BP79: =BO79+BK73+BP74 -> 2628.524 | BQ79: =BP79+BL73+BQ74 -> 2598.3111 | BR79: =BQ79+BM73+BR74 -> 2568.0982 | BS79: =BS76-BS82 -> 2568.0982 | BT79: =BS79+BS73+BT74 -> 2568.0982 | BU79: =BT79+BT73+BU74 -> 2568.0982 | BV79: =BU79+BU73+BV74 -> 2568.0982
A80: Pottery Barn comp store leased square footage - average (calculated), 000s sq ft | D80: =D77-D83 -> 2479.9167 | E80: =E77-E83 -> 2386.975 | F80: =F77-F83 -> 2473.618 | K80: =K77-K83 -> 2642.1368 | L80: =L77-L83 -> 2600.9979 | M80: =M77-M83 -> 2618.8668 | N80: =N77-N83 -> 2623.1215 | O80: =O77-O83 -> 2630.1224 | P80: =SUM(L80*L$3,M80*M$3,N80*N$3,O80*O$3)/P$3 -> 2618.2771 | Q80: =Q77-Q83 -> 2637.2532 | R80: =R77-R83 -> 2637.2523 | S80: =S77-S83 -> 2644.1029 | T80: =T77-T83 -> 2660.8 | U80: =SUM(Q80*Q$3,R80*R$3,S80*S$3,T80*T$3)/U$3 -> 2644.8521 | V80: =V77-V83 -> 2663.7143 | W80: =W77-W83 -> 2677.4167 | X80: =X77-X83 -> 2704.8 | Y80: =Y77-Y83 -> 2696.425 | Z80: =SUM(V80*V$3,W80*W$3,X80*X$3,Y80*Y$3)/Z$3 -> 2685.589 | AA80: =AA77-AA83 -> 2701.05 | AB80: =AB77-AB83 -> 2691 | AC80: =AC77-AC83 -> 2667.1 | AD80: =AD77-AD83 -> 2683.46 | AE80: =SUM(AA80*AA$3,AB80*AB$3,AC80*AC$3,AD80*AD$3)/AE$3 -> 2685.6525 | AF80: =AF77-AF83 -> 2663.2959 | AG80: =AG77-AG83 -> 2697.7278 | AH80: =AH77-AH83 -> 2773.1554 | AI80: =AI77-AI83 -> 2747.4199 | AJ80: =SUM(AF80*AF$3,AG80*AG$3,AH80*AH$3,AI80*AI$3)/AJ$3 -> 2720.9096 | AK80: =AK77-AK83 -> 2756.6484 | AL80: =AL77-AL83 -> 2728.9536 | AM80: =AM77-AM83 -> 2759.7036 | AN80: =AN77-AN83 -> 2767.2838 | AO80: =SUM(AK80*AK$3,AL80*AL$3,AM80*AM$3,AN80*AN$3)/AO$3 -> 2753.1473 | AP80: =AP77-AP83 -> 2805.305 | AQ80: =AQ77-AQ83 -> 2880 | AR80: =AR77-AR83 -> 2887.2 | AS80: =AS77-AS83 -> 2856.3 | AT80: =SUM(AP80*AP$3,AQ80*AQ$3,AR80*AR$3,AS80*AS$3)/AT$3 -> 2857.2013 | AU80: =AU77-AU83 -> 2817.932 | AV80: =AV77-AV83 -> 2796.0723 | AW80: =AW77-AW83 -> 2786.1464 | AX80: =AX77-AX83 -> 2725.7458 | AY80: =SUM(AU80*AU$3,AV80*AV$3,AW80*AW$3,AX80*AX$3)/AY$3 -> 2781.4741 | AZ80: =AZ77-AZ83 -> 2675.1487 | BA80: =BA77-BA83 -> 2675.4253 | BB80: =BB77-BB83 -> 2658.5621 | BC80: =BC77-BC83 -> 2643.1801 | BD80: =SUM(AZ80*AZ$3,BA80*BA$3,BB80*BB$3,BC80*BC$3)/BD$3 -> 2663.0791 | BE80: =BE77-BE83 -> 2627.0501 | BF80: =BF77-BF83 -> 2651.2853 | BG80: =BG77-BG83 -> 2717.0965 | BH80: =BH77-BH83 -> 2676.9057 | BI80: =SUM(BE80*BE$3,BF80*BF$3,BG80*BG$3,BH80*BH$3)/BI$3 -> 2668.0844 | BJ80: =BJ77-BJ83 -> 2622.1454 | BK80: =BK77-BK83 -> 2658.7312 | BL80: =BL77-BL83 -> 2663.7861 | BM80: =BM77-BM83 -> 2653.9512 | BN80: =SUM(BJ80*BJ$3,BK80*BK$3,BL80*BL$3,BM80*BM$3)/BN$3 -> 2649.7346 | BO80: =BO77-BO83 -> 2666.1868 | BP80: =BP77-BP83 -> 2643.6305 | BQ80: =BQ77-BQ83 -> 2613.4176 | BR80: =BR77-BR83 -> 2583.2046 | BS80: =SUM(BO80*BO$3,BP80*BP$3,BQ80*BQ$3,BR80*BR$3)/BS$3 -> 2626.6099 | BT80: =BT77-BT83 -> 2568.0982 | BU80: =BU77-BU83 -> 2568.0982 | BV80: =BV77-BV83 -> 2568.0982
A82: Pottery Barn new store leased square footage - EoP (calculated), 000s sq ft | D82: =IFERROR(D69*D63/1000,0) -> 58.3 | E82: =IFERROR(E69*E63/1000,0) -> 369.9 | F82: =IFERROR(F69*F63/1000,0) -> 122.69659 | K82: =IFERROR(K69*K63/1000,0) -> 77.587593 | L82: =IFERROR(L69*L63/1000,0) -> 69.251745 | M82: =IFERROR(M69*M63/1000,0) -> 55.451745 | N82: =IFERROR(N69*N63/1000,0) -> 82.714226 | O82: =IFERROR(O69*O63/1000,0) -> 96.198992 | P82: =IFERROR(P69*P63/1000,0) -> 96.198992 | Q82: =IFERROR(Q69*Q63/1000,0) -> 68.497322 | R82: =IFERROR(R69*R63/1000,0) -> 95.897336 | ... BV82: =IFERROR(BV69*BV63/1000,0) -> 0
A83: Pottery Barn new store leased square footage - average (calculated), 000s sq ft | D83: =IFERROR(D82-(D55-C55)/2*D69/1000,D82-(D55-C55)/2*D70/1000) -> 77.733333 | E83: =IFERROR(E82-(E55-D55)/2*E69/1000,E82-(E55-D55)/2*E70/1000) -> 215.775 | F83: =IFERROR(F82-(F55-E55)/2*F69/1000,F82-(F55-E55)/2*F70/1000) -> 199.38196 | K83: =K82-(G55*G$3/2/K$3+H55*(H$3/2+G$3)/K$3+I55*(I$3/2+H$3+G$3)/K$3+J55*(J$3/2+I$3+H$3+G$3)/K$3)*K69/1000 -> 51.263231 | L83: =IFERROR(L82-(L55-G55)/2*L69/1000,L82-(L55-G55)/2*L70/1000) -> 83.102094 | M83: =IFERROR(M82-(M55-H55)/2*M69/1000,M82-(M55-H55)/2*M70/1000) -> 62.383213 | N83: =IFERROR(N82-(N55-I55)/2*N69/1000,N82-(N55-I55)/2*N70/1000) -> 68.928522 | O83: =IFERROR(O82-(O55-J55)/2*O69/1000,O82-(O55-J55)/2*O70/1000) -> 89.327636 | P83: =SUM(L83*L$3,M83*M$3,N83*N$3,O83*O$3)/P$3 -> 75.935366 | Q83: =IFERROR(Q82-(Q55-L55)/2*Q69/1000,Q82-(Q55-L55)/2*Q70/1000) -> 82.196786 | R83: =IFERROR(R82-(R55-M55)/2*R69/1000,R82-(R55-M55)/2*R70/1000) -> 82.197716 | S83: =IFERROR(S82-(S55-N55)/2*S69/1000,S82-(S55-N55)/2*S70/1000) -> 89.047129 | T83: =IFERROR(T82-(T55-O55)/2*T69/1000,T82-(T55-O55)/2*T70/1000) -> 68.500035 | U83: =SUM(Q83*Q$3,R83*R$3,S83*S$3,T83*T$3)/U$3 -> 80.485416 | V83: =IFERROR(V82-(V55-Q55)/2*V69/1000,V82-(V55-Q55)/2*V70/1000) -> 75.585736 | W83: =IFERROR(W82-(W55-R55)/2*W69/1000,W82-(W55-R55)/2*W70/1000) -> 89.483348 | X83: =IFERROR(X82-(X55-S55)/2*X69/1000,X82-(X55-S55)/2*X70/1000) -> 75.9 | Y83: =IFERROR(Y82-(Y55-T55)/2*Y69/1000,Y82-(Y55-T55)/2*Y70/1000) -> 94.325 | Z83: =SUM(V83*V$3,W83*W$3,X83*X$3,Y83*Y$3)/Z$3 -> 83.823521 | AA83: =IFERROR(AA82-(AA55-V55)/2*AA69/1000,AA82-(AA55-V55)/2*AA70/1000) -> 69 | AB83: =IFERROR(AB82-(AB55-W55)/2*AB69/1000,AB82-(AB55-W55)/2*AB70/1000) -> 89.7 | AC83: =IFERROR(AC82-(AC55-X55)/2*AC69/1000,AC82-(AC55-X55)/2*AC70/1000) -> 144.4 | AD83: =IFERROR(AD82-(AD55-Y55)/2*AD69/1000,AD82-(AD55-Y55)/2*AD70/1000) -> 131.29 | AE83: =SUM(AA83*AA$3,AB83*AB$3,AC83*AC$3,AD83*AD$3)/AE$3 -> 108.5975 | AF83: =IFERROR(AF82-(AF55-AA55)/2*AF69/1000,AF82-(AF55-AA55)/2*AF70/1000) -> 158.40415 | AG83: =IFERROR(AG82-(AG55-AB55)/2*AG69/1000,AG82-(AG55-AB55)/2*AG70/1000) -> 137.87219 | AH83: =IFERROR(AH82-(AH55-AC55)/2*AH69/1000,AH82-(AH55-AC55)/2*AH70/1000) -> 76.34456 | AI83: =IFERROR(AI82-(AI55-AD55)/2*AI69/1000,AI82-(AI55-AD55)/2*AI70/1000) -> 132.83012 | AJ83: =SUM(AF83*AF$3,AG83*AG$3,AH83*AH$3,AI83*AI$3)/AJ$3 -> 126.48478 | AK83: =IFERROR(AK82-(AK55-AF55)/2*AK69/1000,AK82-(AK55-AF55)/2*AK70/1000) -> 144.10158 | AL83: =IFERROR(AL82-(AL55-AG55)/2*AL69/1000,AL82-(AL55-AG55)/2*AL70/1000) -> 192.29642 | AM83: =IFERROR(AM82-(AM55-AH55)/2*AM69/1000,AM82-(AM55-AH55)/2*AM70/1000) -> 192.29642 | AN83: =IFERROR(AN82-(AN55-AI55)/2*AN69/1000,AN82-(AN55-AI55)/2*AN70/1000) -> 155.91622 | AO83: =SUM(AK83*AK$3,AL83*AL$3,AM83*AM$3,AN83*AN$3)/AO$3 -> 171.15266 | AP83: =IFERROR(AP82-(AP55-AK55)/2*AP69/1000,AP82-(AP55-AK55)/2*AP70/1000) -> 89.094986 | AQ83: =IFERROR(AQ82-(AQ55-AL55)/2*AQ69/1000,AQ82-(AQ55-AL55)/2*AQ70/1000) -> 14.4 | AR83: =IFERROR(AR82-(AR55-AM55)/2*AR69/1000,AR82-(AR55-AM55)/2*AR70/1000) -> 7.2 | AS83: =IFERROR(AS82-(AS55-AN55)/2*AS69/1000,AS82-(AS55-AN55)/2*AS70/1000) -> 14.4 | AT83: =SUM(AP83*AP$3,AQ83*AQ$3,AR83*AR$3,AS83*AS$3)/AT$3 -> 31.273746 | AU83: =IFERROR(AU82-(AU55-AP55)/2*AU69/1000,AU82-(AU55-AP55)/2*AU70/1000) -> 29.068041 | AV83: =IFERROR(AV82-(AV55-AQ55)/2*AV69/1000,AV82-(AV55-AQ55)/2*AV70/1000) -> 50.927706 | AW83: =IFERROR(AW82-(AW55-AR55)/2*AW69/1000,AW82-(AW55-AR55)/2*AW70/1000) -> 51.103608 | AX83: =IFERROR(AX82-(AX55-AS55)/2*AX69/1000,AX82-(AX55-AS55)/2*AX70/1000) -> 51.004156 | AY83: =SUM(AU83*AU$3,AV83*AV$3,AW83*AW$3,AX83*AX$3)/AY$3 -> 45.525878 | AZ83: =IFERROR(AZ82-(AZ55-AU55)/2*AZ69/1000,AZ82-(AZ55-AU55)/2*AZ70/1000) -> 50.851294 | BA83: =IFERROR(BA82-(BA55-AV55)/2*BA69/1000,BA82-(BA55-AV55)/2*BA70/1000) -> 67.274658 | BB83: =IFERROR(BB82-(BB55-AW55)/2*BB69/1000,BB82-(BB55-AW55)/2*BB70/1000) -> 119.7379 | BC83: =IFERROR(BC82-(BC55-AX55)/2*BC69/1000,BC82-(BC55-AX55)/2*BC70/1000) -> 146.6199 | BD83: =SUM(AZ83*AZ$3,BA83*BA$3,BB83*BB$3,BC83*BC$3)/BD$3 -> 96.120937 | BE83: =IFERROR(BE82-(BE55-AZ55)/2*BE69/1000,BE82-(BE55-AZ55)/2*BE70/1000) -> 155.34992 | BF83: =IFERROR(BF82-(BF55-BA55)/2*BF69/1000,BF82-(BF55-BA55)/2*BF70/1000) -> 164.91465 | BG83: =IFERROR(BG82-(BG55-BB55)/2*BG69/1000,BG82-(BG55-BB55)/2*BG70/1000) -> 140.40351 | BH83: =IFERROR(BH82-(BH55-BC55)/2*BH69/1000,BH82-(BH55-BC55)/2*BH70/1000) -> 135.59433 | BI83: =SUM(BE83*BE$3,BF83*BF$3,BG83*BG$3,BH83*BH$3)/BI$3 -> 149.0656 | BJ83: =IFERROR(BJ82-(BJ55-BE55)/2*BJ69/1000,BJ82-(BJ55-BE55)/2*BJ70/1000) -> 147.05455 | BK83: =IFERROR(BK82-(BK55-BF55)/2*BK69/1000,BK82-(BK55-BF55)/2*BK70/1000) -> 104.86636 | BL83: =IFERROR(BL82-(BL55-BG55)/2*BL69/1000,BL82-(BL55-BG55)/2*BL70/1000) -> 69.994749 | BM83: =IFERROR(BM82-(BM55-BH55)/2*BM69/1000,BM82-(BM55-BH55)/2*BM70/1000) -> 49.803674 | BN83: =SUM(BJ83*BJ$3,BK83*BK$3,BL83*BL$3,BM83*BM$3)/BN$3 -> 92.116133 | BO83: =IFERROR(BO82-(BO55-BJ55)/2*BO69/1000,BO82-(BO55-BJ55)/2*BO70/1000) -> 7.55323 | BP83: =IFERROR(BP82-(BP55-BK55)/2*BP69/1000,BP82-(BP55-BK55)/2*BP70/1000) -> 0 | BQ83: =IFERROR(BQ82-(BQ55-BL55)/2*BQ69/1000,BQ82-(BQ55-BL55)/2*BQ70/1000) -> 0 | BR83: =IFERROR(BR82-(BR55-BM55)/2*BR69/1000,BR82-(BR55-BM55)/2*BR70/1000) -> 0 | BS83: =SUM(BO83*BO$3,BP83*BP$3,BQ83*BQ$3,BR83*BR$3)/BS$3 -> 1.8883075 | BT83: =IFERROR(BT82-(BT55-BS55)/2*BT69/1000,BT82-(BT55-BS55)/2*BT70/1000) -> 0 | BU83: =IFERROR(BU82-(BU55-BT55)/2*BU69/1000,BU82-(BU55-BT55)/2*BU70/1000) -> 0 | BV83: =IFERROR(BV82-(BV55-BU55)/2*BV69/1000,BV82-(BV55-BU55)/2*BV70/1000) -> 0
A85: Y/Y Pottery Barn Comparable Brand Sales Growth, % | C85: =C274 -> -0.111 | D85: =D274 -> 0.177 | E85: =E274 -> 0.076 | F85: =F274 -> 0.085 | G85: =G274 -> 0.076 | H85: =H274 -> 0.099 | I85: =I274 -> 0.084 | J85: =J274 -> 0.146 | ... BJ85: =BJ274 -> -0.108 | BK85: 0.005 | BL85: 0.005 | BM85: 0.005 | BN85: =SUM(BJ85*BE$102,BK85*BF$102,BL85*BG$102,BM85*BH$102)/BI$102 -> -0.022057755 | BO85: 0.05 | BP85: 0.05 | BQ85: 0.05 | BR85: 0.05 | BS85: =SUM(BO85*BJ$102,BP85*BK$102,BQ85*BL$102,BR85*BM$102)/BN$102 -> 0.05 | BT85: 0.09 | BU85: 0.09 | BV85: 0.09
A86: Y/Y Pottery Barn impact of store base change, % | AK86: =AK88-AK87 -> -0.02121397 | AL86: =AL88-AL87 -> -0.018648389 | AM86: =AM88-AM87 -> -0.010494132 | AN86: =AN88-AN87 -> -0.090879549 | AO86: =AO88-AO87 -> -0.038304947 | AP86: =AP88-AP87 -> -0.018446224 | AQ86: =AQ88-AQ87 -> -0.0090259895 | AR86: =AR88-AR87 -> -0.013919723 | ... BV86: =BV88-BV87 -> 0
A87: Y/Y Pottery Barn new store sales growth, % | AK87: =AK101/AF102 -> 0.0097908466 | AL87: =AL101/AG102 -> 0.012953329 | AM87: =AM101/AH102 -> 0.020575419 | AN87: =AN101/AI102 -> 0.013673117 | AO87: =AO101/AJ102 -> 0.01432247 | AP87: =AP101/AK102 -> 0.0040238727 | AQ87: =AQ101/AL102 -> 0.001245423 | AR87: =AR101/AM102 -> 0.0010120418 | ... BS87: =BS101/BN102 -> 0.00019005065 | BT87: =BT101/BS102 -> 0 | BU87: =BU101/BT102 -> 0 | BV87: =BV101/BU102 -> 0
A88: Y/Y Pottery Barn Non-Comparable Store Sales Growth, % | D88: =D89-D85 -> -0.018518831 | E88: =E89-E85 -> -0.016558388 | F88: =F89-F85 -> 0.010043436 | K88: =K89-K85 -> -0.013879481 | P88: =P89-P85 -> 0.00027016324 | U88: =U89-U85 -> 0.0065744485 | Z88: =Z89-Z85 -> 0.010973108 | AE88: =AE89-AE85 -> 0.010790251 | AJ88: =AJ89-AJ85 -> 0.041739482 | AK88: =AK89-AK85 -> -0.011423124 | AL88: =AL89-AL85 -> -0.0056950598 | AM88: =AM89-AM85 -> 0.010081287 | AN88: =AN89-AN85 -> -0.077206431 | AO88: =AO89-AO85 -> -0.023982478 | AP88: =AP89-AP85 -> -0.014422351 | AQ88: =AQ89-AQ85 -> -0.0077805665 | ... BV88: =BV89-BV85 -> 0
A89: Y/Y Pottery Barn Revenue Growth, % | D89: =D102/C102-1 -> 0.15848117 | E89: =E102/D102-1 -> 0.059441612 | F89: =F102/E102-1 -> 0.095043436 | K89: =K102/F102-1 -> 0.090120519 | P89: =P102/K102-1 -> 0.058270163 | U89: =U102/P102-1 -> 0.025574448 | Z89: =Z102/U102-1 -> -0.024026892 | AE89: =AE102/Z102-1 -> 0.020790251 | AJ89: =AJ102/AE102-1 -> 0.053739482 | AK89: =AK102/AF102-1 -> 0.0035768763 | AL89: =AL102/AG102-1 -> 0.03630494 | AM89: =AM102/AH102-1 -> 0.044081287 | AN89: =AN102/AI102-1 -> -0.010206431 | AO89: =AO102/AJ102-1 -> 0.017017522 | AP89: =AP102/AK102-1 -> -0.025422351 | AQ89: =AQ102/AL102-1 -> 0.073219433 | ... BS89: =BS102/BN102-1 -> 0.014895422 | BT89: =BT102/BS102-1 -> 0.064953002 | BU89: =BU102/BT102-1 -> 0.09 | BV89: =BV102/BU102-1 -> 0.09
A91: Pottery Barn closed store productivity (estimated), % | AK91: 0.9 | AL91: 0.35 | AM91: 0.3 | AN91: 0.3 | AO91: =AVERAGE(AK91,AL91,AM91,AN91) -> 0.4625 | AP91: 0.5 | AQ91: 0.7 | AR91: 0.55 | AS91: 0.3 | AT91: =AVERAGE(AP91,AQ91,AR91,AS91) -> 0.5125 | AU91: 0.2 | AV91: 0.2 | AW91: 0.25 | AX91: 0.4 | AY91: =AVERAGE(AU91,AV91,AW91,AX91) -> 0.2625 | AZ91: 0.2 | BA91: 0.3 | BB91: 0.3 | BC91: 0.3 | BD91: =AVERAGE(AZ91,BA91,BB91,BC91) -> 0.275 | BE91: 0.3 | BF91: 0.3 | BG91: 0.3 | BH91: 0.3 | BI91: =AVERAGE(BE91,BF91,BG91,BH91) -> 0.3 | BJ91: 0.3 | BK91: 0.3 | BL91: 0.3 | BM91: 0.3 | BN91: =AVERAGE(BJ91,BK91,BL91,BM91) -> 0.3 | BO91: 0.3 | BP91: 0.3 | BQ91: 0.3 | BR91: 0.3 | BS91: =AVERAGE(BO91,BP91,BQ91,BR91) -> 0.3 | BT91: 0.3 | BU91: 0.3 | BV91: 0.3
A92: Pottery Barn closed and other impact on comp base (calculated), % | AK92: =(AK79-(2-AK91)*SUM(AK74,AI74,AH74,AG74))/(AK79-SUM(AK74,AI74,AH74,AG74))-1 -> 0.0022043959 | AL92: =(AL79-(2-AL91)*SUM(AL74,AK74,AI74,AH74))/(AL79-SUM(AL74,AK74,AI74,AH74))-1 -> 0.02048348 | AM92: =(AM79-(2-AM91)*SUM(AM74,AL74,AK74,AI74))/(AM79-SUM(AM74,AL74,AK74,AI74))-1 -> 0.022059132 | AN92: =(AN79-(2-AN91)*SUM(AN74,AM74,AL74,AK74))/(AN79-SUM(AN74,AM74,AL74,AK74))-1 -> 0.025416177 | AO92: =(AO93*AJ$3/AO$3)/AJ98-1 -> 0.015333773 | AP92: =(AP79-(2-AP91)*SUM(AP74,AN74,AM74,AL74))/(AP79-SUM(AP74,AN74,AM74,AL74))-1 -> 0.014737067 | AQ92: =(AQ79-(2-AQ91)*SUM(AQ74,AP74,AN74,AM74))/(AQ79-SUM(AQ74,AP74,AN74,AM74))-1 -> 0.0058536585 | AR92: =(AR79-(2-AR91)*SUM(AR74,AQ74,AP74,AN74))/(AR79-SUM(AR74,AQ74,AP74,AN74))-1 -> 0.01097561 | AS92: =(AS79-(2-AS91)*SUM(AS74,AR74,AQ74,AP74))/(AS79-SUM(AS74,AR74,AQ74,AP74))-1 -> 0.014946103 | AT92: =(AT93*AO$3/AT$3)/AO98-1 -> 0.011889774 | AU92: =(AU79-(2-AU91)*SUM(AU74,AS74,AR74,AQ74))/(AU79-SUM(AU74,AS74,AR74,AQ74))-1 -> 0.025152588 | AV92: =(AV79-(2-AV91)*SUM(AV74,AU74,AS74,AR74))/(AV79-SUM(AV74,AU74,AS74,AR74))-1 -> 0.029188251 | AW92: =(AW79-(2-AW91)*SUM(AW74,AV74,AU74,AS74))/(AW79-SUM(AW74,AV74,AU74,AS74))-1 -> 0.028685503 | AX92: =(AX79-(2-AX91)*SUM(AX74,AW74,AV74,AU74))/(AX79-SUM(AX74,AW74,AV74,AU74))-1 -> 0.037785135 | AY92: =(AY93*AT$3/AY$3)/AT98-1 -> 0.029321469 | AZ92: =(AZ79-(2-AZ91)*SUM(AZ74,AX74,AW74,AV74))/(AZ79-SUM(AZ74,AX74,AW74,AV74))-1 -> 0.046248493 | BA92: =(BA79-(2-BA91)*SUM(BA74,AZ74,AX74,AW74))/(BA79-SUM(BA74,AZ74,AX74,AW74))-1 -> 0.040442475 | BB92: =(BB79-(2-BB91)*SUM(BB74,BA74,AZ74,AX74))/(BB79-SUM(BB74,BA74,AZ74,AX74))-1 -> 0.043073329 | BC92: =(BC79-(2-BC91)*SUM(BC74,BB74,BA74,AZ74))/(BC79-SUM(BC74,BB74,BA74,AZ74))-1 -> 0.026063406 | BD92: =(BD93*AY$3/BD$3)/AY98-1 -> 0.038641045 | BE92: =(BE79-(2-BE91)*SUM(BE74,BC74,BB74,BA74))/(BE79-SUM(BE74,BC74,BB74,BA74))-1 -> 0.022340407 | BF92: =(BF79-(2-BF91)*SUM(BF74,BE74,BC74,BB74))/(BF79-SUM(BF74,BE74,BC74,BB74))-1 -> 0.022070116 | BG92: =(BG79-(2-BG91)*SUM(BG74,BF74,BE74,BC74))/(BG79-SUM(BG74,BF74,BE74,BC74))-1 -> 0.018169048 | BH92: =(BH79-(2-BH91)*SUM(BH74,BG74,BF74,BE74))/(BH79-SUM(BH74,BG74,BF74,BE74))-1 -> 0.037124351 | BI92: =(BI93*BD$3/BI$3)/BD98-1 -> 0.025195707 | BJ92: =(BJ79-(2-BJ91)*SUM(BJ74,BH74,BG74,BF74))/(BJ79-SUM(BJ74,BH74,BG74,BF74))-1 -> 0.040848372 | BK92: =(BK79-(2-BK91)*SUM(BK74,BJ74,BH74,BG74))/(BK79-SUM(BK74,BJ74,BH74,BG74))-1 -> 0.043589452 | BL92: =(BL79-(2-BL91)*SUM(BL74,BK74,BJ74,BH74))/(BL79-SUM(BL74,BK74,BJ74,BH74))-1 -> 0.047130029 | BM92: =(BM79-(2-BM91)*SUM(BM74,BL74,BK74,BJ74))/(BM79-SUM(BM74,BL74,BK74,BJ74))-1 -> 0.026493325 | BN92: =(BN93*BI$3/BN$3)/BI98-1 -> 0.041302884 | BO92: =(BO79-(2-BO91)*SUM(BO74,BM74,BL74,BK74))/(BO79-SUM(BO74,BM74,BL74,BK74))-1 -> 0.030148336 | BP92: =(BP79-(2-BP91)*SUM(BP74,BO74,BM74,BL74))/(BP79-SUM(BP74,BO74,BM74,BL74))-1 -> 0.030627875 | BQ92: =(BQ79-(2-BQ91)*SUM(BQ74,BP74,BO74,BM74))/(BQ79-SUM(BQ74,BP74,BO74,BM74))-1 -> 0.031013661 | BR92: =(BR79-(2-BR91)*SUM(BR74,BQ74,BP74,BO74))/(BR79-SUM(BR74,BQ74,BP74,BO74))-1 -> 0.031409252 | BS92: =(BS93*BN$3/BS$3)/BN98-1 -> 0.028185371 | BT92: =(BT79-(2-BT91)*BT74)/(BT79-BT74)-1 -> 0 | BU92: =(BU79-(2-BU91)*BU74)/(BU79-BU74)-1 -> 0 | BV92: =(BV79-(2-BV91)*BV74)/(BV79-BV74)-1 -> 0
A93: Pottery Barn prior year sales per comp store leased sq ft (calculated), $/sq ft | AK93: =(AF98*AK$3/AF$3)*(1+AK92) -> 174.16911 | AL93: =(AG98*AL$3/AG$3)*(1+AL92) -> 182.26621 | AM93: =(AH98*AM$3/AH$3)*(1+AM92) -> 191.34475 | AN93: =(AI98*AN$3/AI$3)*(1+AN92) -> 213.90377 | AO93: =AO95/(1+AO85) -> 761.75574 | AP93: =(AK98*AP$3/AK$3)*(1+AP92) -> 172.15496 | AQ93: =(AL98*AQ$3/AL$3)*(1+AQ92) -> 180.71691 | AR93: =(AM98*AR$3/AM$3)*(1+AR92) -> 190.75144 | AS93: =(AN98*AS$3/AN$3)*(1+AS92) -> 222.36284 | AT93: =AT95/(1+AT85) -> 766.24344 | AU93: =(AP98*AU$3/AP$3)*(1+AU92) -> 169.87236 | AV93: =(AQ98*AV$3/AQ$3)*(1+AV92) -> 200.28919 | AW93: =(AR98*AW$3/AR$3)*(1+AW92) -> 243.10763 | AX93: =(AS98*AX$3/AS$3)*(1+AX92) -> 288.96208 | AY93: =AY95/(1+AY85) -> 900.2377 | AZ93: =(AU98*AZ$3/AU$3)*(1+AZ92) -> 249.54699 | BA93: =(AV98*BA$3/AV$3)*(1+BA92) -> 267.62907 | BB93: =(AW98*BB$3/AW$3)*(1+BB92) -> 289.96575 | BC93: =(AX98*BC$3/AX$3)*(1+BC92) -> 340.1712 | BD93: =BD95/(1+BD85) -> 1146.5418 | BE93: =(AZ98*BE$3/AZ$3)*(1+BE92) -> 290.51794 | BF93: =(BA98*BF$3/BA$3)*(1+BF92) -> 327.60017 | BG93: =(BB98*BG$3/BB$3)*(1+BG92) -> 342.66777 | BH93: =(BC98*BH$3/BC$3)*(1+BH92) -> 359.38489 | BI93: =BI95/(1+BI85) -> 1321.0731 | BJ93: =(BE98*BJ$3/BE$3)*(1+BJ92) -> 287.18871 | BK93: =(BF98*BK$3/BF$3)*(1+BK92) -> 291.37942 | BL93: =(BG98*BL$3/BG$3)*(1+BL92) -> 284.90548 | BM93: =(BH98*BM$3/BH$3)*(1+BM92) -> 343.78942 | BN93: =BN95/(1+BN85) -> 1207.8855 | BO93: =(BJ98*BO$3/BJ$3)*(1+BO92) -> 251.97007 | BP93: =(BK98*BP$3/BK$3)*(1+BP92) -> 293.21614 | BQ93: =(BL98*BQ$3/BL$3)*(1+BQ92) -> 289.91923 | BR93: =(BM98*BR$3/BM$3)*(1+BR92) -> 326.63946 | BS93: =BS95/(1+BS85) -> 1160.5877 | BT93: =(BS98*BT$3/BS$3)*(1+BT92) -> 1217.9697 | BU93: =(BT98*BU$3/BT$3)*(1+BU92) -> 1327.5869 | BV93: =(BU98*BV$3/BU$3)*(1+BV92) -> 1447.0698
A95: Pottery Barn sales per comp store leased sq ft (calculated), $/sq ft | AK95: =AK93*(1+AK85) -> 176.78165 | AL95: =AL93*(1+AL85) -> 189.92139 | AM95: =AM93*(1+AM85) -> 197.85047 | AN95: =AN93*(1+AN85) -> 228.23532 | AO95: =AO100/AO80*1000 -> 792.98773 | AP95: =AP93*(1+AP85) -> 170.26125 | AQ95: =AQ93*(1+AQ85) -> 195.35498 | AR95: =AR93*(1+AR85) -> 236.72254 | AS95: =AS93*(1+AS85) -> 279.5101 | AT95: =AT100/AT80*1000 -> 882.71244 | AU95: =AU93*(1+AU85) -> 240.02964 | AV95: =AV93*(1+AV85) -> 259.57479 | AW95: =AW93*(1+AW85) -> 281.76174 | AX95: =AX93*(1+AX85) -> 335.77394 | AY95: =AY100/AY80*1000 -> 1115.3945 | AZ95: =AZ93*(1+AZ85) -> 285.98085 | BA95: =BA93*(1+BA85) -> 325.16932 | BB95: =BB93*(1+BB85) -> 346.79903 | BC95: =BC93*(1+BC85) -> 359.90113 | BD95: =BD100/BD80*1000 -> 1317.3765 | BE95: =BE93*(1+BE85) -> 289.35587 | BF95: =BF93*(1+BF85) -> 292.87455 | BG95: =BG93*(1+BG85) -> 285.78492 | BH95: =BH93*(1+BH85) -> 324.88394 | BI95: =BI100/BI80*1000 -> 1192.929 | BJ95: =BJ93*(1+BJ85) -> 256.17233 | BK95: =BK93*(1+BK85) -> 292.83632 | BL95: =BL93*(1+BL85) -> 286.33001 | BM95: =BM93*(1+BM85) -> 345.50837 | BN95: =BN100/BN80*1000 -> 1181.2423 | BO95: =BO93*(1+BO85) -> 264.56858 | BP95: =BP93*(1+BP85) -> 307.87695 | BQ95: =BQ93*(1+BQ85) -> 304.4152 | BR95: =BR93*(1+BR85) -> 342.97143 | BS95: =BS100/BS80*1000 -> 1218.617 | BT95: =BT93*(1+BT85) -> 1327.5869 | BU95: =BU93*(1+BU85) -> 1447.0698 | BV95: =BV93*(1+BV85) -> 1577.306
A96: Pottery Barn new store productivity (calculated), % | AK96: =IFERROR(AK97/AK95,"n/a") -> 0.18846903 | AL96: =IFERROR(AL97/AL95,"n/a") -> 0.17963108 | AM96: =IFERROR(AM97/AM95,"n/a") -> 0.2885025 | AN96: =IFERROR(AN97/AN95,"n/a") -> 0.24861454 | AO96: =IFERROR(AO97/AO95,"n/a") -> 0.2297708 | AP96: =IFERROR(AP97/AP95,"n/a") -> 0.13054236 | AQ96: =IFERROR(AQ97/AQ95,"n/a") -> 0.23236067 | AR96: =IFERROR(AR97/AR95,"n/a") -> 0.33072716 | ... BJ96: =IFERROR(BJ97/BJ95,"n/a") -> 0.14902305 | BK96: 0.25 | BL96: 0.3 | BM96: 0.3 | BN96: =IFERROR(BN97/BN95,"n/a") -> 0.22484595 | BO96: 0.3 | BP96: 0.25 | BQ96: 0.3 | BR96: 0.3 | BS96: =IFERROR(BS97/BS95,"n/a") -> 0.26052671 | BT96: 0.3 | BU96: 0.3 | BV96: 0.3
A97: Pottery Barn sales per new store leased sq ft (calculated), $/sq ft | AK97: =IFERROR(AK101/AK83*1000,"n/a") -> 33.317865 | AL97: =IFERROR(AL101/AL83*1000,"n/a") -> 34.115784 | AM97: =IFERROR(AM101/AM83*1000,"n/a") -> 57.080356 | AN97: =IFERROR(AN101/AN83*1000,"n/a") -> 56.742619 | AO97: =IFERROR(AO101/AO83*1000,"n/a") -> 182.20542 | AP97: =IFERROR(AP101/AP83*1000,"n/a") -> 22.226305 | AQ97: =IFERROR(AQ101/AQ83*1000,"n/a") -> 45.392815 | AR97: =IFERROR(AR101/AR83*1000,"n/a") -> 78.290573 | ... BJ97: =IFERROR(BJ101/BJ83*1000,"n/a") -> 38.175581 | BK97: =BK95*BK96 -> 73.20908 | BL97: =BL95*BL96 -> 85.899003 | BM97: =BM95*BM96 -> 103.65251 | BN97: =IFERROR(BN101/BN83*1000,"n/a") -> 265.59754 | BO97: =BO95*BO96 -> 79.370573 | BP97: =BP95*BP96 -> 76.969237 | BQ97: =BQ95*BQ96 -> 91.324559 | BR97: =BR95*BR96 -> 102.89143 | BS97: =IFERROR(BS101/BS83*1000,"n/a") -> 317.48229 | BT97: =BT95*BT96 -> 398.27608 | BU97: =BU95*BU96 -> 434.12093 | BV97: =BV95*BV96 -> 473.19181
A98: Pottery Barn Sales per Leased Square Foot (Calculated), $/sq ft | D98: =D102/D77*1000 -> 590.78803 | E98: =E102/E77*1000 -> 615.05984 | F98: =F102/F77*1000 -> 655.81631 | K98: =K102/K77*1000 -> 709.50397 | P98: =P102/P77*1000 -> 750.62045 | U98: =U102/U77*1000 -> 761.02538 | Z98: =Z102/Z77*1000 -> 730.91964 | AE98: =AE102/AE77*1000 -> 739.48358 | AF98: =AF102/AF77*1000 -> 173.78602 | AG98: =AG102/AG77*1000 -> 178.6077 | AH98: =AH102/AH77*1000 -> 187.21495 | AI98: =AI102/AI77*1000 -> 224.64821 | AJ98: =AJ102/AJ77*1000 -> 764.67947 | AK98: =AK102/AK77*1000 -> 169.65474 | AL98: =AL102/AL77*1000 -> 179.66521 | ... BV98: =BV102/BV77*1000 -> 1577.306
A100: Pottery Barn comp store sales (calculated), mm | AK100: =AK95*AK80/1000 -> 487.32484 | AL100: =AL95*AL80/1000 -> 518.28666 | AM100: =AM95*AM80/1000 -> 546.00865 | AN100: =AN95*AN80/1000 -> 631.59191 | AO100: =SUM(AK100,AL100,AM100,AN100) -> 2183.2121 | AP100: =AP95*AP80/1000 -> 477.63475 | AQ100: =AQ95*AQ80/1000 -> 562.62234 | AR100: =AR95*AR80/1000 -> 683.46531 | AS100: =AS95*AS80/1000 -> 798.36469 | AT100: =SUM(AP100,AQ100,AR100,AS100) -> 2522.0871 | AU100: =AU95*AU80/1000 -> 676.38721 | AV100: =AV95*AV80/1000 -> 725.78989 | AW100: =AW95*AW80/1000 -> 785.02945 | AX100: =AX95*AX80/1000 -> 915.23442 | AY100: =SUM(AU100,AV100,AW100,AX100) -> 3102.441 | AZ100: =AZ95*AZ80/1000 -> 765.04129 | BA100: =BA95*BA80/1000 -> 869.96623 | BB100: =BB95*BB80/1000 -> 921.98676 | BC100: =BC95*BC80/1000 -> 951.2835 | BD100: =SUM(AZ100,BA100,BB100,BC100) -> 3508.2778 | BE100: =BE95*BE80/1000 -> 760.15236 | BF100: =BF95*BF80/1000 -> 776.49401 | BG100: =BG95*BG80/1000 -> 776.50521 | BH100: =BH95*BH80/1000 -> 869.68366 | BI100: =SUM(BE100,BF100,BG100,BH100) -> 3182.8352 | BJ100: =BJ95*BJ80/1000 -> 671.72111 | BK100: =BK95*BK80/1000 -> 778.57306 | BL100: =BL95*BL80/1000 -> 762.72192 | BM100: =BM95*BM80/1000 -> 916.96236 | BN100: =SUM(BJ100,BK100,BL100,BM100) -> 3129.9784 | BO100: =BO95*BO80/1000 -> 705.38924 | BP100: =BP95*BP80/1000 -> 813.91288 | BQ100: =BQ95*BQ80/1000 -> 795.56402 | BR100: =BR95*BR80/1000 -> 885.9654 | BS100: =SUM(BO100,BP100,BQ100,BR100) -> 3200.8315 | BT100: =BT95*BT80/1000 -> 3409.3736 | BU100: =BU95*BU80/1000 -> 3716.2172 | BV100: =BV95*BV80/1000 -> 4050.6768
A101: Pottery Barn new store sales (calculated), mm | AK101: =AK102-AK100 -> 4.801157 | AL101: =AL102-AL100 -> 6.5603432 | AM101: =AM102-AM100 -> 10.976348 | AN101: =AN102-AN100 -> 8.847095 | AO101: =AO102-AO100 -> 31.184943 | AP101: =AP102-AP100 -> 1.9802524 | AQ101: =AQ102-AQ100 -> 0.65365653 | AR101: =AR102-AR100 -> 0.56369213 | ... BJ101: =BJ102-BJ100 -> 5.6138931 | BK101: =BK97*BK83/1000 -> 7.6771697 | BL101: =BL97*BL83/1000 -> 6.0124792 | BM101: =BM97*BM83/1000 -> 5.1622759 | BN101: =SUM(BJ101,BK101,BL101,BM101) -> 24.465818 | BO101: =BO97*BO83/1000 -> 0.59950419 | BP101: =BP97*BP83/1000 -> 0 | BQ101: =BQ97*BQ83/1000 -> 0 | BR101: =BR97*BR83/1000 -> 0 | BS101: =SUM(BO101,BP101,BQ101,BR101) -> 0.59950419 | BT101: =BT97*BT83/1000 -> 0 | BU101: =BU97*BU83/1000 -> 0 | BV101: =BV97*BV83/1000 -> 0
A102: Pottery Barn Revenue, mm | C102: =C284 -> 1304.319 | D102: =D284 -> 1511.029 | E102: =E284 -> 1600.847 | F102: =F284 -> 1752.997 | K102: =K284 -> 1910.978 | P102: =P284 -> 2022.331 | U102: =U284 -> 2074.051 | Z102: =Z284 -> 2024.218 | AE102: =AE284 -> 2066.302 | AF102: =AF284 -> 490.372 | AG102: =AG284 -> 506.46 | AH102: =AH284 -> 533.469 | AI102: =AI284 -> 647.043 | AJ102: =AJ284 -> 2177.344 | AK102: =AK284 -> 492.126 | AL102: =AL284 -> 524.847 | ... BJ102: =BJ284 -> 677.335 | BK102: =SUM(BK100:BK101) -> 786.25023 | BL102: =SUM(BL100:BL101) -> 768.7344 | BM102: =SUM(BM100:BM101) -> 922.12463 | BN102: =SUM(BN100:BN101) -> 3154.4443 | BO102: =SUM(BO100:BO101) -> 705.98874 | BP102: =SUM(BP100:BP101) -> 813.91288 | BQ102: =SUM(BQ100:BQ101) -> 795.56402 | BR102: =SUM(BR100:BR101) -> 885.9654 | ... BV102: =SUM(BV100:BV101) -> 4050.6768
A103: Y/Y Pottery Barn revenue growth, % | D103: =D102/C102-1 -> 0.15848117 | E103: =E102/D102-1 -> 0.059441612 | F103: =F102/E102-1 -> 0.095043436 | K103: =K102/F102-1 -> 0.090120519 | P103: =P102/K102-1 -> 0.058270163 | U103: =U102/P102-1 -> 0.025574448 | Z103: =Z102/U102-1 -> -0.024026892 | AE103: =AE102/Z102-1 -> 0.020790251 | AJ103: =AJ102/AE102-1 -> 0.053739482 | AK103: =AK102/AF102-1 -> 0.0035768763 | AL103: =AL102/AG102-1 -> 0.03630494 | AM103: =AM102/AH102-1 -> 0.044081287 | AN103: =AN102/AI102-1 -> -0.010206431 | AO103: =AO102/AJ102-1 -> 0.017017522 | AP103: =AP102/AK102-1 -> -0.025422351 | AQ103: =AQ102/AL102-1 -> 0.073219433 | ... BS103: =BS102/BN102-1 -> 0.014895422 | BT103: =BT102/BS102-1 -> 0.064953002 | BU103: =BU102/BT102-1 -> 0.09 | BV103: =BV102/BU102-1 -> 0.09
A105: Pottery Barn sales per comp store (calculated), k$/store | AK105: =AK100/AK80*AK65 -> 2439.1435 | AL105: =AL100/AL80*AL65 -> 2620.6337 | AM105: =AM100/AM80*AM65 -> 2730.0433 | AN105: =AN100/AN80*AN65 -> 3217.4357 | AO105: =AO100/AO80*AO65 -> 11178.756 | AP105: =AP100/AP80*AP65 -> 2400.1746 | AQ105: =AQ100/AQ80*AQ65 -> 2813.1117 | AR105: =AR100/AR80*AR65 -> 3408.8045 | ... BV105: =BV100/BV80*BV65 -> 23827.51
A106: Pottery Barn sales per new store (calculated), k$/store | AK106: =IFERROR(AK101/AK83*AK69,"n/a") -> 872.93764 | AL106: =IFERROR(AL101/AL83*AL69,"n/a") -> 1312.0686 | AM106: =IFERROR(AM101/AM83*AM69,"n/a") -> 2195.2697 | AN106: =IFERROR(AN101/AN83*AN69,"n/a") -> 2527.7414 | AO106: =IFERROR(AO101/AO83*AO69,"n/a") -> 8116.7948 | AP106: =IFERROR(AP101/AP83*AP69,"n/a") -> 990.12618 | AQ106: =IFERROR(AQ101/AQ83*AQ69,"n/a") -> n/a | AR106: =IFERROR(AR101/AR83*AR69,"n/a") -> 1127.3843 | ... BV106: =IFERROR(BV101/BV83*BV69,"n/a") -> n/a
A107: Pottery Barn Sales per Store (Calculated), k$/store | D107: =D102/D77*D70 -> 7739.3232 | E107: =E102/E77*E70 -> 8487.8258 | F107: =F102/F77*F70 -> 9115.8467 | K107: =K102/K77*K70 -> 9791.1548 | P107: =P102/P77*P70 -> 10283.5 | U107: =U102/U77*U70 -> 10502.15 | Z107: =Z102/Z77*Z70 -> 10159.783 | AE107: =AE102/AE77*AE70 -> 10278.822 | AF107: =AF102/AF77*AF70 -> 2415.6256 | AG107: =AG102/AG77*AG70 -> 2482.6471 | AH107: =AH102/AH77*AH70 -> 2602.2878 | AI107: =AI102/AI77*AI70 -> 3190.0045 | AJ107: =AJ102/AJ77*AJ70 -> 10858.449 | AK107: =AK102/AK77*AK70 -> 2392.1319 | AL107: =AL102/AL77*AL70 -> 2587.1791 | ... BV107: =BV102/BV77*BV70 -> 23827.51
A109: Segmented Results - West Elm (FS)
A110: West Elm Stores - BoP, # of Stores | C110: 36 | D110: =C113 -> 36 | E110: =D113 -> 36 | F110: =E113 -> 37 | G110: =F113 -> 48 | H110: =G113 -> 49 | I110: =H113 -> 51 | J110: =I113 -> 55 | K110: =F113 -> 48 | L110: =K113 -> 58 | M110: =L113 -> 58 | N110: =M113 -> 59 | O110: =N113 -> 68 | P110: =K113 -> 58 | Q110: =P113 -> 69 | R110: =Q113 -> 72 | S110: =R113 -> 78 | T110: =S113 -> 84 | U110: =P113 -> 69 | V110: =U113 -> 87 | W110: =V113 -> 87 | X110: =W113 -> 89 | Y110: =X113 -> 97 | Z110: =U113 -> 87 | AA110: =Z113 -> 98 | AB110: =AA113 -> 99 | AC110: =AB113 -> 101 | AD110: =AC113 -> 105 | AE110: =Z113 -> 98 | AF110: =AE113 -> 106 | AG110: =AF113 -> 108 | AH110: =AG113 -> 109 | AI110: =AH113 -> 112 | AJ110: =AE113 -> 106 | AK110: =AJ113 -> 112 | AL110: =AK113 -> 113 | AM110: =AL113 -> 112 | AN110: =AM113 -> 114 | AO110: =AJ113 -> 112 | AP110: =AO113 -> 118 | AQ110: =AP113 -> 119 | AR110: =AQ113 -> 121 | AS110: =AR113 -> 122 | AT110: =AO113 -> 118 | AU110: =AT113 -> 121 | AV110: =AU113 -> 121 | AW110: =AV113 -> 123 | AX110: =AW113 -> 121 | AY110: =AT113 -> 121 | AZ110: =AY113 -> 121 | BA110: =AZ113 -> 121 | BB110: =BA113 -> 121 | BC110: =BB113 -> 122 | BD110: =AY113 -> 121 | BE110: =BD113 -> 122 | BF110: =BE113 -> 123 | BG110: =BF113 -> 123 | BH110: =BG113 -> 123 | BI110: =BD113 -> 122 | BJ110: =BI113 -> 121 | BK110: =BJ113 -> 121 | BL110: =BK113 -> 121 | BM110: =BL113 -> 121 | BN110: =BI113 -> 121 | BO110: =BN113 -> 121 | BP110: =BO113 -> 121 | BQ110: =BP113 -> 121 | BR110: =BQ113 -> 121 | BS110: =BN113 -> 121 | BT110: =BS113 -> 121 | BU110: =BT113 -> 117 | BV110: =BU113 -> 113
A111: West Elm stores opened, # of stores | C111: =0+1+0+3 -> 4 | D111: =0+0+0+2 -> 2 | E111: =1+1+0+0 -> 2 | F111: =4+5+2+2 -> 13 | G111: 1 | H111: 3 | I111: 4 | J111: 3 | K111: =SUM(G111,H111,I111,J111) -> 11 | L111: 0 | M111: 1 | N111: 9 | O111: 1 | P111: =SUM(L111,M111,N111,O111) -> 11 | Q111: 3 | R111: 6 | S111: 6 | T111: 3 | U111: =SUM(Q111,R111,S111,T111) -> 18 | V111: 0 | W111: 2 | X111: 10 | Y111: 1 | Z111: =SUM(V111,W111,X111,Y111) -> 13 | AA111: 1 | AB111: 2 | AC111: 5 | AD111: 3 | AE111: =SUM(AA111,AB111,AC111,AD111) -> 11 | AF111: 2 | AG111: 3 | AH111: 3 | AI111: 1 | AJ111: =SUM(AF111,AG111,AH111,AI111) -> 9 | AK111: 1 | AL111: 0 | AM111: 2 | AN111: 4 | AO111: =SUM(AK111,AL111,AM111,AN111) -> 7 | AP111: 2 | AQ111: 3 | AR111: 2 | AS111: 0 | AT111: =SUM(AP111,AQ111,AR111,AS111) -> 7 | AU111: 0 | AV111: 2 | AW111: 1 | AX111: 1 | AY111: =SUM(AU111,AV111,AW111,AX111) -> 4 | AZ111: 0 | BA111: 1 | BB111: 2 | BC111: 1 | BD111: =SUM(AZ111,BA111,BB111,BC111) -> 4 | BE111: 1 | BF111: 1 | BG111: 0 | BH111: 0 | BI111: =SUM(BE111,BF111,BG111,BH111) -> 2 | BJ111: 1 | BK111: 1 | BL111: 1 | BM111: 1 | BN111: =SUM(BJ111,BK111,BL111,BM111) -> 4 | BO111: 1 | BP111: 1 | BQ111: 1 | BR111: 1 | BS111: =SUM(BO111,BP111,BQ111,BR111) -> 4 | BT111: 4 | BU111: 4 | BV111: 4
A112: West Elm stores closed, # of stores | C112: =-4+0+0+0 -> -4 | D112: =-1+0+0-1 -> -2 | E112: =0+0+0-1 -> -1 | F112: =-1+0+0-1 -> -2 | G112: 0 | H112: -1 | I112: 0 | J112: 0 | K112: =SUM(G112,H112,I112,J112) -> -1 | L112: 0 | M112: 0 | N112: 0 | O112: 0 | P112: =SUM(L112,M112,N112,O112) -> 0 | Q112: 0 | R112: 0 | S112: 0 | T112: 0 | U112: =SUM(Q112,R112,S112,T112) -> 0 | V112: 0 | W112: 0 | X112: -2 | Y112: 0 | Z112: =SUM(V112,W112,X112,Y112) -> -2 | AA112: 0 | AB112: 0 | AC112: -1 | AD112: -2 | AE112: =SUM(AA112,AB112,AC112,AD112) -> -3 | AF112: 0 | AG112: -2 | AH112: 0 | AI112: -1 | AJ112: =SUM(AF112,AG112,AH112,AI112) -> -3 | AK112: 0 | AL112: -1 | AM112: 0 | AN112: 0 | AO112: =SUM(AK112,AL112,AM112,AN112) -> -1 | AP112: -1 | AQ112: -1 | AR112: -1 | AS112: -1 | AT112: =SUM(AP112,AQ112,AR112,AS112) -> -4 | AU112: 0 | AV112: 0 | AW112: -3 | AX112: -1 | AY112: =SUM(AU112,AV112,AW112,AX112) -> -4 | AZ112: 0 | BA112: -1 | BB112: -1 | BC112: -1 | BD112: =SUM(AZ112,BA112,BB112,BC112) -> -3 | BE112: 0 | BF112: -1 | BG112: 0 | BH112: -2 | BI112: =SUM(BE112,BF112,BG112,BH112) -> -3 | BJ112: -1 | BK112: -1 | BL112: -1 | BM112: -1 | BN112: =SUM(BJ112,BK112,BL112,BM112) -> -4 | BO112: -1 | BP112: -1 | BQ112: -1 | BR112: -1 | BS112: =SUM(BO112,BP112,BQ112,BR112) -> -4 | BT112: -8 | BU112: -8 | BV112: -8
A113: West Elm Stores - EoP, # of Stores | C113: =SUM(C110:C112) -> 36 | D113: =SUM(D110:D112) -> 36 | E113: =SUM(E110:E112) -> 37 | F113: =SUM(F110:F112) -> 48 | G113: =SUM(G110:G112) -> 49 | H113: =SUM(H110:H112) -> 51 | I113: =SUM(I110:I112) -> 55 | J113: =SUM(J110:J112) -> 58 | K113: =J113 -> 58 | L113: =SUM(L110:L112) -> 58 | M113: =SUM(M110:M112) -> 59 | N113: =SUM(N110:N112) -> 68 | O113: =SUM(O110:O112) -> 69 | P113: =O113 -> 69 | Q113: =SUM(Q110:Q112) -> 72 | R113: =SUM(R110:R112) -> 78 | S113: =SUM(S110:S112) -> 84 | T113: =SUM(T110:T112) -> 87 | U113: =T113 -> 87 | V113: =SUM(V110:V112) -> 87 | W113: =SUM(W110:W112) -> 89 | X113: =SUM(X110:X112) -> 97 | Y113: =SUM(Y110:Y112) -> 98 | Z113: =Y113 -> 98 | AA113: =SUM(AA110:AA112) -> 99 | AB113: =SUM(AB110:AB112) -> 101 | AC113: =SUM(AC110:AC112) -> 105 | AD113: =SUM(AD110:AD112) -> 106 | AE113: =AD113 -> 106 | AF113: =SUM(AF110:AF112) -> 108 | AG113: =SUM(AG110:AG112) -> 109 | AH113: =SUM(AH110:AH112) -> 112 | AI113: =SUM(AI110:AI112) -> 112 | AJ113: =AI113 -> 112 | AK113: =SUM(AK110:AK112) -> 113 | AL113: =SUM(AL110:AL112) -> 112 | AM113: =SUM(AM110:AM112) -> 114 | AN113: =SUM(AN110:AN112) -> 118 | AO113: =AN113 -> 118 | AP113: =SUM(AP110:AP112) -> 119 | AQ113: =SUM(AQ110:AQ112) -> 121 | AR113: =SUM(AR110:AR112) -> 122 | AS113: =SUM(AS110:AS112) -> 121 | AT113: =AS113 -> 121 | AU113: =SUM(AU110:AU112) -> 121 | AV113: =SUM(AV110:AV112) -> 123 | AW113: =SUM(AW110:AW112) -> 121 | AX113: =SUM(AX110:AX112) -> 121 | AY113: =AX113 -> 121 | AZ113: =SUM(AZ110:AZ112) -> 121 | BA113: =SUM(BA110:BA112) -> 121 | BB113: =SUM(BB110:BB112) -> 122 | BC113: =SUM(BC110:BC112) -> 122 | BD113: =BC113 -> 122 | BE113: =SUM(BE110:BE112) -> 123 | BF113: =SUM(BF110:BF112) -> 123 | BG113: =SUM(BG110:BG112) -> 123 | BH113: =SUM(BH110:BH112) -> 121 | BI113: =BH113 -> 121 | BJ113: =SUM(BJ110:BJ112) -> 121 | BK113: =SUM(BK110:BK112) -> 121 | BL113: =SUM(BL110:BL112) -> 121 | BM113: =SUM(BM110:BM112) -> 121 | BN113: =SUM(BN110:BN112) -> 121 | BO113: =SUM(BO110:BO112) -> 121 | BP113: =SUM(BP110:BP112) -> 121 | BQ113: =SUM(BQ110:BQ112) -> 121 | ... BV113: =SUM(BV110:BV112) -> 109
A114: Q/Q West Elm stores - EoP growth, % | H114: =H113/G113-1 -> 0.040816327 | I114: =I113/H113-1 -> 0.078431373 | J114: =J113/I113-1 -> 0.054545455 | L114: =L113/J113-1 -> 0 | M114: =M113/L113-1 -> 0.017241379 | N114: =N113/M113-1 -> 0.15254237 | O114: =O113/N113-1 -> 0.014705882 | Q114: =Q113/O113-1 -> 0.043478261 | R114: =R113/Q113-1 -> 0.083333333 | S114: =S113/R113-1 -> 0.076923077 | T114: =T113/S113-1 -> 0.035714286 | V114: =V113/T113-1 -> 0 | W114: =W113/V113-1 -> 0.022988506 | X114: =X113/W113-1 -> 0.08988764 | Y114: =Y113/X113-1 -> 0.010309278 | AA114: =AA113/Y113-1 -> 0.010204082 | AB114: =AB113/AA113-1 -> 0.02020202 | AC114: =AC113/AB113-1 -> 0.03960396 | AD114: =AD113/AC113-1 -> 0.0095238095 | AF114: =AF113/AD113-1 -> 0.018867925 | AG114: =AG113/AF113-1 -> 0.0092592593 | AH114: =AH113/AG113-1 -> 0.027522936 | AI114: =AI113/AH113-1 -> 0 | AK114: =AK113/AI113-1 -> 0.0089285714 | AL114: =AL113/AK113-1 -> -0.0088495575 | AM114: =AM113/AL113-1 -> 0.017857143 | AN114: =AN113/AM113-1 -> 0.035087719 | AP114: =AP113/AN113-1 -> 0.0084745763 | AQ114: =AQ113/AP113-1 -> 0.016806723 | AR114: =AR113/AQ113-1 -> 0.0082644628 | AS114: =AS113/AR113-1 -> -0.0081967213 | AU114: =AU113/AS113-1 -> 0 | AV114: =AV113/AU113-1 -> 0.016528926 | AW114: =AW113/AV113-1 -> -0.016260163 | AX114: =AX113/AW113-1 -> 0 | AZ114: =AZ113/AX113-1 -> 0 | BA114: =BA113/AZ113-1 -> 0 | BB114: =BB113/BA113-1 -> 0.0082644628 | BC114: =BC113/BB113-1 -> 0 | BE114: =BE113/BC113-1 -> 0.0081967213 | BF114: =BF113/BE113-1 -> 0 | BG114: =BG113/BF113-1 -> 0 | BH114: =BH113/BG113-1 -> -0.016260163 | BJ114: =BJ113/BH113-1 -> 0 | BK114: =BK113/BJ113-1 -> 0 | BL114: =BL113/BK113-1 -> 0 | BM114: =BM113/BL113-1 -> 0 | BO114: =BO113/BM113-1 -> 0 | BP114: =BP113/BO113-1 -> 0 | BQ114: =BQ113/BP113-1 -> 0 | BR114: =BR113/BQ113-1 -> 0
A115: Y/Y West Elm stores - EoP growth, % | D115: =D113/C113-1 -> 0 | E115: =E113/D113-1 -> 0.027777778 | F115: =F113/E113-1 -> 0.2972973 | K115: =K113/F113-1 -> 0.20833333 | L115: =L113/G113-1 -> 0.18367347 | M115: =M113/H113-1 -> 0.15686275 | N115: =N113/I113-1 -> 0.23636364 | O115: =O113/J113-1 -> 0.18965517 | P115: =P113/K113-1 -> 0.18965517 | Q115: =Q113/L113-1 -> 0.24137931 | R115: =R113/M113-1 -> 0.3220339 | ... BS115: =BS113/BN113-1 -> 0 | BT115: =BT113/BS113-1 -> -0.033057851 | BU115: =BU113/BT113-1 -> -0.034188034 | BV115: =BV113/BU113-1 -> -0.03539823
A116: West Elm Stores - Average, # of stores | C116: =AVERAGE(C113,C110) -> 36 | D116: =AVERAGE(D113,D110) -> 36 | E116: =AVERAGE(E113,E110) -> 36.5 | F116: =AVERAGE(F113,F110) -> 42.5 | G116: =AVERAGE(G113,G110) -> 48.5 | H116: =AVERAGE(H113,H110) -> 50 | I116: =AVERAGE(I113,I110) -> 53 | J116: =AVERAGE(J113,J110) -> 56.5 | K116: =SUM(G116*G$3,H116*H$3,I116*I$3,J116*J$3)/K$3 -> 52 | L116: =AVERAGE(L113,L110) -> 58 | M116: =AVERAGE(M113,M110) -> 58.5 | N116: =AVERAGE(N113,N110) -> 63.5 | O116: =AVERAGE(O113,O110) -> 68.5 | P116: =SUM(L116*L$3,M116*M$3,N116*N$3,O116*O$3)/P$3 -> 62.125 | Q116: =AVERAGE(Q113,Q110) -> 70.5 | R116: =AVERAGE(R113,R110) -> 75 | S116: =AVERAGE(S113,S110) -> 81 | T116: =AVERAGE(T113,T110) -> 85.5 | U116: =SUM(Q116*Q$3,R116*R$3,S116*S$3,T116*T$3)/U$3 -> 78 | V116: =AVERAGE(V113,V110) -> 87 | W116: =AVERAGE(W113,W110) -> 88 | X116: =AVERAGE(X113,X110) -> 93 | Y116: =AVERAGE(Y113,Y110) -> 97.5 | Z116: =SUM(V116*V$3,W116*W$3,X116*X$3,Y116*Y$3)/Z$3 -> 91.375 | AA116: =AVERAGE(AA113,AA110) -> 98.5 | AB116: =AVERAGE(AB113,AB110) -> 100 | AC116: =AVERAGE(AC113,AC110) -> 103 | AD116: =AVERAGE(AD113,AD110) -> 105.5 | AE116: =SUM(AA116*AA$3,AB116*AB$3,AC116*AC$3,AD116*AD$3)/AE$3 -> 101.75 | AF116: =AVERAGE(AF113,AF110) -> 107 | AG116: =AVERAGE(AG113,AG110) -> 108.5 | AH116: =AVERAGE(AH113,AH110) -> 110.5 | AI116: =AVERAGE(AI113,AI110) -> 112 | AJ116: =SUM(AF116*AF$3,AG116*AG$3,AH116*AH$3,AI116*AI$3)/AJ$3 -> 109.54717 | AK116: =AVERAGE(AK113,AK110) -> 112.5 | AL116: =AVERAGE(AL113,AL110) -> 112.5 | AM116: =AVERAGE(AM113,AM110) -> 113 | AN116: =AVERAGE(AN113,AN110) -> 116 | AO116: =SUM(AK116*AK$3,AL116*AL$3,AM116*AM$3,AN116*AN$3)/AO$3 -> 113.5 | AP116: =AVERAGE(AP113,AP110) -> 118.5 | AQ116: =AVERAGE(AQ113,AQ110) -> 120 | AR116: =AVERAGE(AR113,AR110) -> 121.5 | AS116: =AVERAGE(AS113,AS110) -> 121.5 | AT116: =SUM(AP116*AP$3,AQ116*AQ$3,AR116*AR$3,AS116*AS$3)/AT$3 -> 120.375 | AU116: =AVERAGE(AU113,AU110) -> 121 | AV116: =AVERAGE(AV113,AV110) -> 122 | AW116: =AVERAGE(AW113,AW110) -> 122 | AX116: =AVERAGE(AX113,AX110) -> 121 | AY116: =SUM(AU116*AU$3,AV116*AV$3,AW116*AW$3,AX116*AX$3)/AY$3 -> 121.5 | AZ116: =AVERAGE(AZ113,AZ110) -> 121 | BA116: =AVERAGE(BA113,BA110) -> 121 | BB116: =AVERAGE(BB113,BB110) -> 121.5 | BC116: =AVERAGE(BC113,BC110) -> 122 | BD116: =SUM(AZ116*AZ$3,BA116*BA$3,BB116*BB$3,BC116*BC$3)/BD$3 -> 121.375 | BE116: =AVERAGE(BE113,BE110) -> 122.5 | BF116: =AVERAGE(BF113,BF110) -> 123 | BG116: =AVERAGE(BG113,BG110) -> 123 | BH116: =AVERAGE(BH113,BH110) -> 122 | BI116: =SUM(BE116*BE$3,BF116*BF$3,BG116*BG$3,BH116*BH$3)/BI$3 -> 122.625 | BJ116: =AVERAGE(BJ113,BJ110) -> 121 | BK116: =AVERAGE(BK113,BK110) -> 121 | BL116: =AVERAGE(BL113,BL110) -> 121 | BM116: =AVERAGE(BM113,BM110) -> 121 | BN116: =SUM(BJ116*BJ$3,BK116*BK$3,BL116*BL$3,BM116*BM$3)/BN$3 -> 121 | BO116: =AVERAGE(BO113,BO110) -> 121 | BP116: =AVERAGE(BP113,BP110) -> 121 | BQ116: =AVERAGE(BQ113,BQ110) -> 121 | BR116: =AVERAGE(BR113,BR110) -> 121 | BS116: =SUM(BO116*BO$3,BP116*BP$3,BQ116*BQ$3,BR116*BR$3)/BS$3 -> 121 | BT116: =AVERAGE(BT113,BT110) -> 119 | BU116: =AVERAGE(BU113,BU110) -> 115 | BV116: =AVERAGE(BV113,BV110) -> 111
A118: West Elm comp stores, # of stores | D118: =C113+SUM(D112) -> 34 | E118: =D113+SUM(E112) -> 35 | F118: =E113+SUM(F112) -> 35 | K118: =F113+SUM(K112) -> 47 | L118: =G113+SUM(L112,J112,I112,H112) -> 48 | M118: =H113+SUM(M112,L112,J112,I112) -> 51 | N118: =I113+SUM(N112,M112,L112,J112) -> 55 | O118: =J113+SUM(O112,N112,M112,L112) -> 58 | P118: =K113+SUM(P112) -> 58 | Q118: =L113+SUM(Q112,O112,N112,M112) -> 58 | R118: =M113+SUM(R112,Q112,O112,N112) -> 59 | S118: =N113+SUM(S112,R112,Q112,O112) -> 68 | T118: =O113+SUM(T112,S112,R112,Q112) -> 69 | U118: =P113+SUM(U112) -> 69 | V118: =Q113+SUM(V112,T112,S112,R112) -> 72 | W118: =R113+SUM(W112,V112,T112,S112) -> 78 | X118: =S113+SUM(X112,W112,V112,T112) -> 82 | Y118: =T113+SUM(Y112,X112,W112,V112) -> 85 | Z118: =U113+SUM(Z112) -> 85 | AA118: =V113+SUM(AA112,Y112,X112,W112) -> 85 | AB118: =W113+SUM(AB112,AA112,Y112,X112) -> 87 | AC118: =X113+SUM(AC112,AB112,AA112,Y112) -> 96 | AD118: =Y113+SUM(AD112,AC112,AB112,AA112) -> 95 | AE118: =Z113+SUM(AE112) -> 95 | AF118: =AA113+SUM(AF112,AD112,AC112,AB112) -> 96 | AG118: =AB113+SUM(AG112,AF112,AD112,AC112) -> 96 | AH118: =AC113+SUM(AH112,AG112,AF112,AD112) -> 101 | AI118: =AD113+SUM(AI112,AH112,AG112,AF112) -> 103 | AJ118: =AE113+SUM(AJ112) -> 103 | AK118: =AF113+SUM(AK112,AI112,AH112,AG112) -> 105 | AL118: =AG113+SUM(AL112,AK112,AI112,AH112) -> 107 | AM118: =AH113+SUM(AM112,AL112,AK112,AI112) -> 110 | AN118: =AI113+SUM(AN112,AM112,AL112,AK112) -> 111 | AO118: =AJ113+SUM(AO112) -> 111 | AP118: =AK113+SUM(AP112,AN112,AM112,AL112) -> 111 | AQ118: =AL113+SUM(AQ112,AP112,AN112,AM112) -> 110 | AR118: =AM113+SUM(AR112,AQ112,AP112,AN112) -> 111 | AS118: =AN113+SUM(AS112,AR112,AQ112,AP112) -> 114 | AT118: =AO113+SUM(AT112) -> 114 | AU118: =AP113+SUM(AU112,AS112,AR112,AQ112) -> 116 | AV118: =AQ113+SUM(AV112,AU112,AS112,AR112) -> 119 | AW118: =AR113+SUM(AW112,AV112,AU112,AS112) -> 118 | AX118: =AS113+SUM(AX112,AW112,AV112,AU112) -> 117 | AY118: =AT113+SUM(AY112) -> 117 | AZ118: =AU113+SUM(AZ112,AX112,AW112,AV112) -> 117 | BA118: =AV113+SUM(BA112,AZ112,AX112,AW112) -> 118 | BB118: =AW113+SUM(BB112,BA112,AZ112,AX112) -> 118 | BC118: =AX113+SUM(BC112,BB112,BA112,AZ112) -> 118 | BD118: =AY113+SUM(BD112) -> 118 | BE118: =AZ113+SUM(BE112,BC112,BB112,BA112) -> 118 | BF118: =BA113+SUM(BF112,BE112,BC112,BB112) -> 118 | BG118: =BB113+SUM(BG112,BF112,BE112,BC112) -> 120 | BH118: =BC113+SUM(BH112,BG112,BF112,BE112) -> 119 | BI118: =BD113+SUM(BI112) -> 119 | BJ118: =BE113+SUM(BJ112,BH112,BG112,BF112) -> 119 | BK118: =BF113+SUM(BK112,BJ112,BH112,BG112) -> 119 | BL118: =BG113+SUM(BL112,BK112,BJ112,BH112) -> 118 | BM118: =BH113+SUM(BM112,BL112,BK112,BJ112) -> 117 | BN118: =BI113+SUM(BN112) -> 117 | BO118: =BJ113+SUM(BO112,BM112,BL112,BK112) -> 117 | BP118: =BK113+SUM(BP112,BO112,BM112,BL112) -> 117 | BQ118: =BL113+SUM(BQ112,BP112,BO112,BM112) -> 117 | BR118: =BM113+SUM(BR112,BQ112,BP112,BO112) -> 117 | BS118: =BN113+SUM(BS112) -> 117 | BT118: =BS113+SUM(BT112) -> 113 | BU118: =BT113+SUM(BU112) -> 109 | BV118: =BU113+SUM(BV112) -> 105
A119: West Elm new stores, # of stores | D119: =SUM(D111) -> 2 | E119: =SUM(E111) -> 2 | F119: =SUM(F111) -> 13 | K119: =SUM(K111) -> 11 | L119: =SUM(L111,J111,I111,H111) -> 10 | M119: =SUM(M111,L111,J111,I111) -> 8 | N119: =SUM(N111,M111,L111,J111) -> 13 | O119: =SUM(O111,N111,M111,L111) -> 11 | P119: =SUM(P111) -> 11 | Q119: =SUM(Q111,O111,N111,M111) -> 14 | R119: =SUM(R111,Q111,O111,N111) -> 19 | S119: =SUM(S111,R111,Q111,O111) -> 16 | T119: =SUM(T111,S111,R111,Q111) -> 18 | U119: =SUM(U111) -> 18 | V119: =SUM(V111,T111,S111,R111) -> 15 | W119: =SUM(W111,V111,T111,S111) -> 11 | X119: =SUM(X111,W111,V111,T111) -> 15 | Y119: =SUM(Y111,X111,W111,V111) -> 13 | Z119: =SUM(Z111) -> 13 | AA119: =SUM(AA111,Y111,X111,W111) -> 14 | AB119: =SUM(AB111,AA111,Y111,X111) -> 14 | AC119: =SUM(AC111,AB111,AA111,Y111) -> 9 | AD119: =SUM(AD111,AC111,AB111,AA111) -> 11 | AE119: =SUM(AE111) -> 11 | AF119: =SUM(AF111,AD111,AC111,AB111) -> 12 | AG119: =SUM(AG111,AF111,AD111,AC111) -> 13 | AH119: =SUM(AH111,AG111,AF111,AD111) -> 11 | AI119: =SUM(AI111,AH111,AG111,AF111) -> 9 | AJ119: =SUM(AJ111) -> 9 | AK119: =SUM(AK111,AI111,AH111,AG111) -> 8 | AL119: =SUM(AL111,AK111,AI111,AH111) -> 5 | AM119: =SUM(AM111,AL111,AK111,AI111) -> 4 | AN119: =SUM(AN111,AM111,AL111,AK111) -> 7 | AO119: =SUM(AO111) -> 7 | AP119: =SUM(AP111,AN111,AM111,AL111) -> 8 | AQ119: =SUM(AQ111,AP111,AN111,AM111) -> 11 | AR119: =SUM(AR111,AQ111,AP111,AN111) -> 11 | AS119: =SUM(AS111,AR111,AQ111,AP111) -> 7 | AT119: =SUM(AT111) -> 7 | AU119: =SUM(AU111,AS111,AR111,AQ111) -> 5 | AV119: =SUM(AV111,AU111,AS111,AR111) -> 4 | AW119: =SUM(AW111,AV111,AU111,AS111) -> 3 | AX119: =SUM(AX111,AW111,AV111,AU111) -> 4 | AY119: =SUM(AY111) -> 4 | AZ119: =SUM(AZ111,AX111,AW111,AV111) -> 4 | BA119: =SUM(BA111,AZ111,AX111,AW111) -> 3 | BB119: =SUM(BB111,BA111,AZ111,AX111) -> 4 | BC119: =SUM(BC111,BB111,BA111,AZ111) -> 4 | BD119: =SUM(BD111) -> 4 | BE119: =SUM(BE111,BC111,BB111,BA111) -> 5 | BF119: =SUM(BF111,BE111,BC111,BB111) -> 5 | BG119: =SUM(BG111,BF111,BE111,BC111) -> 3 | BH119: =SUM(BH111,BG111,BF111,BE111) -> 2 | BI119: =SUM(BI111) -> 2 | BJ119: =SUM(BJ111,BH111,BG111,BF111) -> 2 | BK119: =SUM(BK111,BJ111,BH111,BG111) -> 2 | BL119: =SUM(BL111,BK111,BJ111,BH111) -> 3 | BM119: =SUM(BM111,BL111,BK111,BJ111) -> 4 | BN119: =SUM(BN111) -> 4 | BO119: =SUM(BO111,BM111,BL111,BK111) -> 4 | BP119: =SUM(BP111,BO111,BM111,BL111) -> 4 | BQ119: =SUM(BQ111,BP111,BO111,BM111) -> 4 | BR119: =SUM(BR111,BQ111,BP111,BO111) -> 4 | BS119: =SUM(BS111) -> 4 | BT119: =SUM(BT111) -> 4 | BU119: =SUM(BU111) -> 4 | BV119: =SUM(BV111) -> 4
A121: West Elm leased square footage per comp store (calculated), sq ft/store | D121: =D135/D118*1000 -> 17600 | E121: =E135/E118*1000 -> 17085.714 | F121: =F135/F118*1000 -> 17100.816 | K121: =K135/K118*1000 -> 14853.174 | L121: =L135/L118*1000 -> 14752.066 | M121: =M135/M118*1000 -> 14600 | N121: =N135/N118*1000 -> 14300 | O121: =O135/O118*1000 -> 14100 | P121: =O121 -> 14100 | Q121: =Q135/Q118*1000 -> 14100 | R121: =R135/R118*1000 -> 14000 | S121: =S135/S118*1000 -> 13800 | T121: =T135/T118*1000 -> 13700 | U121: =T121 -> 13700 | V121: =V135/V118*1000 -> 13600 | W121: =W135/W118*1000 -> 13400 | X121: =X135/X118*1000 -> 13400 | Y121: =Y135/Y118*1000 -> 13195.294 | Z121: =Y121 -> 13195.294 | AA121: =AA135/AA118*1000 -> 13195.294 | AB121: =AB135/AB118*1000 -> 13297.701 | AC121: =AC135/AC118*1000 -> 13300.024 | AD121: =AD135/AD118*1000 -> 13300.024 | AE121: =AD121 -> 13300.024 | AF121: =AF135/AF118*1000 -> 13300.023 | AG121: =AG135/AG118*1000 -> 13194.815 | AH121: =AH135/AH118*1000 -> 13092.078 | AI121: =AI135/AI118*1000 -> 13096.193 | AJ121: =AI121 -> 13096.193 | AK121: =AK135/AK118*1000 -> 12993.408 | AL121: =AL135/AL118*1000 -> 13100.074 | AM121: =AM135/AM118*1000 -> 13201.89 | AN121: =AN135/AN118*1000 -> 13100 | AO121: =AN121 -> 13100 | AP121: =AP135/AP118*1000 -> 13100 | AQ121: =AQ135/AQ118*1000 -> 13100 | AR121: =AR135/AR118*1000 -> 13100 | AS121: =AS135/AS118*1000 -> 13100 | AT121: =AS121 -> 13100 | AU121: =AU135/AU118*1000 -> 13202.586 | AV121: =AV135/AV118*1000 -> 13201.681 | AW121: =AW135/AW118*1000 -> 13097.415 | AX121: =AX135/AX118*1000 -> 13097.415 | AY121: =AX121 -> 13097.415 | AZ121: =AZ135/AZ118*1000 -> 13097.415 | BA121: =BA135/BA118*1000 -> 13097.459 | BB121: =BB135/BB118*1000 -> 13100.065 | BC121: =BC135/BC118*1000 -> 13202.585 | BD121: =BC121 -> 13202.585 | BE121: =BE135/BE118*1000 -> 13202.585 | BF121: =BF135/BF118*1000 -> 13201.694 | BG121: =BG135/BG118*1000 -> 13200.811 | BH121: =BH135/BH118*1000 -> 13199.978 | BI121: =BH121 -> 13199.978 | BJ121: =BJ135/BJ118*1000 -> 13199.978 | BK121: =BK135/BK118*1000 -> 13200 | BL121: =BL135/BL118*1000 -> 13200 | BM121: =BM135/BM118*1000 -> 13200 | BN121: =BM121 -> 13200 | BO121: =BO135/BO118*1000 -> 13303.419 | BP121: =BP135/BP118*1000 -> 13302.535 | BQ121: =BQ135/BQ118*1000 -> 13301.659 | BR121: =BR135/BR118*1000 -> 13300.79 | BS121: =BR121 -> 13300.79 | BT121: =BT135/BT118*1000 -> 13300.836 | BU121: =BU135/BU118*1000 -> 13300.836 | BV121: =BV135/BV118*1000 -> 13300.836
A122: West Elm opened store size as a % of comp store (calculated), % | D122: =IFERROR(D124/D121,"n/a") -> 0.48863636 | E122: =IFERROR(E124/E121,"n/a") -> 1.0154682 | F122: =IFERROR(F124/F121,"n/a") -> 0.52481268 | K122: =IFERROR(K124/K121,"n/a") -> 0.73263077 | L122: =IFERROR(L124/L121,"n/a") -> n/a | M122: =IFERROR(M124/M121,"n/a") -> 0.56164384 | N122: =IFERROR(N124/N121,"n/a") -> 0.87334887 | O122: =IFERROR(O124/O121,"n/a") -> 0.4893617 | P122: =IFERROR(P124/P121,"n/a") -> 0.82205029 | Q122: =IFERROR(Q124/Q121,"n/a") -> 0.80141844 | R122: =IFERROR(R124/R121,"n/a") -> 0.78571429 | ... BJ122: =IFERROR(BJ124/BJ121,"n/a") -> 1.9166681 | BK122: 1 | BL122: 1 | BM122: 1 | BN122: =IFERROR(BN124/BN121,"n/a") -> 1.2291662 | BO122: 1 | BP122: 1 | BQ122: 1 | BR122: 1 | BS122: =IFERROR(BS124/BS121,"n/a") -> 1.0000986 | BT122: 1 | BU122: 1 | BV122: 1
A123: West Elm closed store size as a % of prior comp store (estimated), % | D123: 1 | E123: 1 | F123: 1 | K123: =K130/K112*1000/F121 -> 1 | L123: 1 | M123: 1 | N123: 1 | O123: 1 | P123: =IFERROR(SUM(L130*L123,M130*M123,N130*N123,O130*O123)/P130,"n/a") -> n/a | Q123: 1 | R123: 1 | S123: 1 | T123: 1 | U123: =IFERROR(SUM(Q130*Q123,R130*R123,S130*S123,T130*T123)/U130,"n/a") -> n/a | V123: 1 | W123: 1 | X123: 1 | Y123: 1 | Z123: =SUM(V130*V123,W130*W123,X130*X123,Y130*Y123)/Z130 -> 1 | AA123: 1 | AB123: 1 | AC123: 1 | AD123: 1 | AE123: =SUM(AA130*AA123,AB130*AB123,AC130*AC123,AD130*AD123)/AE130 -> 1 | AF123: 1 | AG123: 1 | AH123: 1 | AI123: 1 | AJ123: =SUM(AF130*AF123,AG130*AG123,AH130*AH123,AI130*AI123)/AJ130 -> 1 | AK123: 1 | AL123: 1 | AM123: 1 | AN123: 1 | AO123: =SUM(AK130*AK123,AL130*AL123,AM130*AM123,AN130*AN123)/AO130 -> 1 | AP123: 1 | AQ123: 1 | AR123: 1 | AS123: 1 | AT123: =SUM(AP130*AP123,AQ130*AQ123,AR130*AR123,AS130*AS123)/AT130 -> 1 | AU123: 1 | AV123: 1 | AW123: 1 | AX123: 1 | AY123: =SUM(AU130*AU123,AV130*AV123,AW130*AW123,AX130*AX123)/AY130 -> 1 | AZ123: 1 | BA123: 1 | BB123: 1 | BC123: 1 | BD123: =SUM(AZ130*AZ123,BA130*BA123,BB130*BB123,BC130*BC123)/BD130 -> 1 | BE123: 1 | BF123: 1 | BG123: 1 | BH123: 1 | BI123: =SUM(BE130*BE123,BF130*BF123,BG130*BG123,BH130*BH123)/BI130 -> 1 | BJ123: 1 | BK123: 1 | BL123: 1 | BM123: 1 | BN123: =SUM(BJ130*BJ123,BK130*BK123,BL130*BL123,BM130*BM123)/BN130 -> 1 | BO123: 1 | BP123: 1 | BQ123: 1 | BR123: 1 | BS123: =SUM(BO130*BO123,BP130*BP123,BQ130*BQ123,BR130*BR123)/BS130 -> 1 | BT123: 1 | BU123: 1 | BV123: 1
A124: West Elm leased square footage per opened store (calculated), sq ft/store | D124: =IFERROR(D129/D111*1000,"n/a") -> 8600 | E124: =IFERROR(E129/E111*1000,"n/a") -> 17350 | F124: =IFERROR(F129/F111*1000,"n/a") -> 8974.7253 | K124: =IFERROR(K129/K111*1000,"n/a") -> 10881.892 | L124: =IFERROR(L129/L111*1000,"n/a") -> n/a | M124: =IFERROR(M129/M111*1000,"n/a") -> 8200 | N124: =IFERROR(N129/N111*1000,"n/a") -> 12488.889 | O124: =IFERROR(O129/O111*1000,"n/a") -> 6900 | P124: =IFERROR(P129/P111*1000,"n/a") -> 11590.909 | Q124: =IFERROR(Q129/Q111*1000,"n/a") -> 11300 | R124: =IFERROR(R129/R111*1000,"n/a") -> 11000 | ... BJ124: =IFERROR(BJ129/BJ111*1000,"n/a") -> 25299.978 | BK124: =IF(BK111=0,"n/a",BK121*BK122) -> 13200 | BL124: =IF(BL111=0,"n/a",BL121*BL122) -> 13200 | BM124: =IF(BM111=0,"n/a",BM121*BM122) -> 13200 | BN124: =IFERROR(BN129/BN111*1000,"n/a") -> 16224.995 | BO124: =IF(BO111=0,"n/a",BO121*BO122) -> 13303.419 | BP124: =IF(BP111=0,"n/a",BP121*BP122) -> 13302.535 | BQ124: =IF(BQ111=0,"n/a",BQ121*BQ122) -> 13301.659 | BR124: =IF(BR111=0,"n/a",BR121*BR122) -> 13300.79 | BS124: =IFERROR(BS129/BS111*1000,"n/a") -> 13302.101 | BT124: =IF(BT111=0,"n/a",BT121*BT122) -> 13300.836 | BU124: =IF(BU111=0,"n/a",BU121*BU122) -> 13300.836 | BV124: =IF(BV111=0,"n/a",BV121*BV122) -> 13300.836
...

Sheet Wayfair
A1: Wayfair Inc.
A2: =CHOOSE(MO.DataSourceIndex,MO.Ticker.Bloomberg,MO.Ticker.CapIQ,MO.Ticker.FactSet,MO.Ticker.Thomson) -> WSM US | C2: =EOMONTH(C4,-12) -> 39813 | BH2: c
A3: =HP.TradeCurrency -> USD | B3: =IF(MO.RealTime="OFF",MO.LastPriceHardcoded,MO.LastPriceFormula) -> 292.52 | C3: =C4-C2 -> 365 | D3: =D4-C4 -> 365 | E3: =E4-D4 -> 365 | F3: =F4-E4 -> 366 | G3: =G4-F4 -> 90 | H3: =H4-G4 -> 91 | I3: =I4-H4 -> 92 | J3: =J4-I4 -> 92 | K3: =K4-F4 -> 365 | L3: =L4-K4 -> 90 | M3: =M4-L4 -> 91 | N3: =N4-M4 -> 92 | O3: =O4-N4 -> 92 | P3: =P4-K4 -> 365 | Q3: =Q4-P4 -> 90 | R3: =R4-Q4 -> 91 | S3: =S4-R4 -> 92 | T3: =T4-S4 -> 92 | U3: =U4-P4 -> 365 | V3: =V4-U4 -> 91 | W3: =W4-V4 -> 91 | X3: =X4-W4 -> 92 | Y3: =Y4-X4 -> 92 | Z3: =Z4-U4 -> 366 | AA3: =AA4-Z4 -> 90 | AB3: =AB4-AA4 -> 91 | AC3: =AC4-AB4 -> 92 | AD3: =AD4-AC4 -> 92 | AE3: =AE4-Z4 -> 365 | AF3: =AF4-AE4 -> 90 | AG3: =AG4-AF4 -> 91 | AH3: =AH4-AG4 -> 92 | AI3: =AI4-AH4 -> 92 | AJ3: =AJ4-AE4 -> 365 | AK3: =AK4-AJ4 -> 90 | AL3: =AL4-AK4 -> 91 | AM3: =AM4-AL4 -> 92 | AN3: =AN4-AM4 -> 92 | AO3: =AO4-AJ4 -> 365 | AP3: =AP4-AO4 -> 91 | AQ3: =AQ4-AP4 -> 91 | AR3: =AR4-AQ4 -> 92 | AS3: =AS4-AR4 -> 92 | AT3: =AT4-AO4 -> 366 | AU3: =AU4-AT4 -> 90 | AV3: =AV4-AU4 -> 91 | AW3: =AW4-AV4 -> 92 | AX3: =AX4-AW4 -> 92 | AY3: =AY4-AT4 -> 365 | AZ3: =AZ4-AY4 -> 90 | BA3: =BA4-AZ4 -> 91 | BB3: =BB4-BA4 -> 92 | BC3: =BC4-BB4 -> 92 | BD3: =BD4-AY4 -> 365 | BE3: =BE4-BD4 -> 90 | BF3: =BF4-BE4 -> 91 | BG3: =BG4-BF4 -> 92 | BH3: =BH4-BG4 -> 92 | BI3: =BI4-BD4 -> 365 | BJ3: =BJ4-BI4 -> 91 | BK3: =BK4-BJ4 -> 91 | BL3: =BL4-BK4 -> 92 | BM3: =BM4-BL4 -> 92 | BN3: =BN4-BI4 -> 366 | BO3: =BO4-BN4 -> 90 | BP3: =BP4-BO4 -> 91 | BQ3: =BQ4-BP4 -> 92 | BR3: =BR4-BQ4 -> 92 | BS3: =BS4-BN4 -> 365 | BT3: =BT4-BS4 -> 365 | BU3: =BU4-BT4 -> 365 | BV3: =BV4-BU4 -> 366
A4: =FP.DataSourceName -> Bloomberg | B4: =IF(AND(MO.RealTimeStockPriceToggle,MO.LastPriceFormula<>"N/A"),"ON","OFF") -> OFF | C4: 40178 | D4: =EOMONTH(C4,12) -> 40543 | E4: =EOMONTH(D4,12) -> 40908 | F4: =EOMONTH(E4,12) -> 41274 | G4: =EOMONTH(F4,3) -> 41364 | H4: =EOMONTH(G4,3) -> 41455 | I4: =EOMONTH(H4,3) -> 41547 | J4: =EOMONTH(I4,3) -> 41639 | K4: =J4 -> 41639 | L4: =EOMONTH(K4,3) -> 41729 | M4: =EOMONTH(L4,3) -> 41820 | N4: =EOMONTH(M4,3) -> 41912 | O4: =EOMONTH(N4,3) -> 42004 | P4: =O4 -> 42004 | Q4: =EOMONTH(P4,3) -> 42094 | R4: =EOMONTH(Q4,3) -> 42185 | S4: =EOMONTH(R4,3) -> 42277 | T4: =EOMONTH(S4,3) -> 42369 | U4: =T4 -> 42369 | V4: =EOMONTH(U4,3) -> 42460 | W4: =EOMONTH(V4,3) -> 42551 | X4: =EOMONTH(W4,3) -> 42643 | Y4: =EOMONTH(X4,3) -> 42735 | Z4: =Y4 -> 42735 | AA4: =EOMONTH(Z4,3) -> 42825 | AB4: =EOMONTH(AA4,3) -> 42916 | AC4: =EOMONTH(AB4,3) -> 43008 | AD4: =EOMONTH(AC4,3) -> 43100 | AE4: =AD4 -> 43100 | AF4: =EOMONTH(AE4,3) -> 43190 | AG4: =EOMONTH(AF4,3) -> 43281 | AH4: =EOMONTH(AG4,3) -> 43373 | AI4: =EOMONTH(AH4,3) -> 43465 | AJ4: =AI4 -> 43465 | AK4: =EOMONTH(AJ4,3) -> 43555 | AL4: =EOMONTH(AK4,3) -> 43646 | AM4: =EOMONTH(AL4,3) -> 43738 | AN4: =EOMONTH(AM4,3) -> 43830 | AO4: =AN4 -> 43830 | AP4: =EOMONTH(AO4,3) -> 43921 | AQ4: =EOMONTH(AP4,3) -> 44012 | AR4: =EOMONTH(AQ4,3) -> 44104 | AS4: =EOMONTH(AR4,3) -> 44196 | AT4: =AS4 -> 44196 | AU4: =EOMONTH(AT4,3) -> 44286 | AV4: =EOMONTH(AU4,3) -> 44377 | AW4: =EOMONTH(AV4,3) -> 44469 | AX4: =EOMONTH(AW4,3) -> 44561 | AY4: =AX4 -> 44561 | AZ4: =EOMONTH(AY4,3) -> 44651 | BA4: =EOMONTH(AZ4,3) -> 44742 | BB4: =EOMONTH(BA4,3) -> 44834 | BC4: =EOMONTH(BB4,3) -> 44926 | BD4: =BC4 -> 44926 | BE4: =EOMONTH(BD4,3) -> 45016 | BF4: =EOMONTH(BE4,3) -> 45107 | BG4: =EOMONTH(BF4,3) -> 45199 | BH4: =EOMONTH(BG4,3) -> 45291 | BI4: =BH4 -> 45291 | BJ4: =EOMONTH(BI4,3) -> 45382 | BK4: =EOMONTH(BJ4,3) -> 45473 | BL4: =EOMONTH(BK4,3) -> 45565 | BM4: =EOMONTH(BL4,3) -> 45657 | BN4: =BM4 -> 45657 | BO4: =EOMONTH(BN4,3) -> 45747 | BP4: =EOMONTH(BO4,3) -> 45838 | BQ4: =EOMONTH(BP4,3) -> 45930 | BR4: =EOMONTH(BQ4,3) -> 46022 | BS4: =BR4 -> 46022 | BT4: =EOMONTH(BS4,12) -> 46387 | BU4: =EOMONTH(BT4,12) -> 46752 | BV4: =EOMONTH(BU4,12) -> 47118
A5: =MO.ReportCurrency -> USD | C5: FY2009 | D5: =CONCATENATE("FY",RIGHT(C5,4)+1) -> FY2010 | E5: =CONCATENATE("FY",RIGHT(D5,4)+1) -> FY2011 | F5: =CONCATENATE("FY",RIGHT(E5,4)+1) -> FY2012 | G5: =CONCATENATE("Q1","-",RIGHT(F5,4)+1) -> Q1-2013 | H5: =CONCATENATE("Q2","-",RIGHT(G5,4)) -> Q2-2013 | I5: =CONCATENATE("Q3","-",RIGHT(H5,4)) -> Q3-2013 | J5: =CONCATENATE("Q4","-",RIGHT(I5,4)) -> Q4-2013 | K5: =CONCATENATE("FY",RIGHT(F5,4)+1) -> FY2013 | L5: =CONCATENATE("Q1","-",RIGHT(K5,4)+1) -> Q1-2014 | M5: =CONCATENATE("Q2","-",RIGHT(L5,4)) -> Q2-2014 | N5: =CONCATENATE("Q3","-",RIGHT(M5,4)) -> Q3-2014 | O5: =CONCATENATE("Q4","-",RIGHT(N5,4)) -> Q4-2014 | P5: =CONCATENATE("FY",RIGHT(K5,4)+1) -> FY2014 | Q5: =CONCATENATE("Q1","-",RIGHT(P5,4)+1) -> Q1-2015 | R5: =CONCATENATE("Q2","-",RIGHT(Q5,4)) -> Q2-2015 | S5: =CONCATENATE("Q3","-",RIGHT(R5,4)) -> Q3-2015 | T5: =CONCATENATE("Q4","-",RIGHT(S5,4)) -> Q4-2015 | U5: =CONCATENATE("FY",RIGHT(P5,4)+1) -> FY2015 | V5: =CONCATENATE("Q1","-",RIGHT(U5,4)+1) -> Q1-2016 | W5: =CONCATENATE("Q2","-",RIGHT(V5,4)) -> Q2-2016 | X5: =CONCATENATE("Q3","-",RIGHT(W5,4)) -> Q3-2016 | Y5: =CONCATENATE("Q4","-",RIGHT(X5,4)) -> Q4-2016 | Z5: =CONCATENATE("FY",RIGHT(U5,4)+1) -> FY2016 | AA5: =CONCATENATE("Q1","-",RIGHT(Z5,4)+1) -> Q1-2017 | AB5: =CONCATENATE("Q2","-",RIGHT(AA5,4)) -> Q2-2017 | AC5: =CONCATENATE("Q3","-",RIGHT(AB5,4)) -> Q3-2017 | AD5: =CONCATENATE("Q4","-",RIGHT(AC5,4)) -> Q4-2017 | AE5: =CONCATENATE("FY",RIGHT(Z5,4)+1) -> FY2017 | AF5: =CONCATENATE("Q1","-",RIGHT(AE5,4)+1) -> Q1-2018 | AG5: =CONCATENATE("Q2","-",RIGHT(AF5,4)) -> Q2-2018 | AH5: =CONCATENATE("Q3","-",RIGHT(AG5,4)) -> Q3-2018 | AI5: =CONCATENATE("Q4","-",RIGHT(AH5,4)) -> Q4-2018 | AJ5: =CONCATENATE("FY",RIGHT(AE5,4)+1) -> FY2018 | AK5: =CONCATENATE("Q1","-",RIGHT(AJ5,4)+1) -> Q1-2019 | AL5: =CONCATENATE("Q2","-",RIGHT(AK5,4)) -> Q2-2019 | AM5: =CONCATENATE("Q3","-",RIGHT(AL5,4)) -> Q3-2019 | AN5: =CONCATENATE("Q4","-",RIGHT(AM5,4)) -> Q4-2019 | AO5: =CONCATENATE("FY",RIGHT(AJ5,4)+1) -> FY2019 | AP5: =CONCATENATE("Q1","-",RIGHT(AO5,4)+1) -> Q1-2020 | AQ5: =CONCATENATE("Q2","-",RIGHT(AP5,4)) -> Q2-2020 | AR5: =CONCATENATE("Q3","-",RIGHT(AQ5,4)) -> Q3-2020 | AS5: =CONCATENATE("Q4","-",RIGHT(AR5,4)) -> Q4-2020 | AT5: =CONCATENATE("FY",RIGHT(AO5,4)+1) -> FY2020 | AU5: =CONCATENATE("Q1","-",RIGHT(AT5,4)+1) -> Q1-2021 | AV5: =CONCATENATE("Q2","-",RIGHT(AU5,4)) -> Q2-2021 | AW5: =CONCATENATE("Q3","-",RIGHT(AV5,4)) -> Q3-2021 | AX5: =CONCATENATE("Q4","-",RIGHT(AW5,4)) -> Q4-2021 | AY5: =CONCATENATE("FY",RIGHT(AT5,4)+1) -> FY2021 | AZ5: =CONCATENATE("Q1","-",RIGHT(AY5,4)+1) -> Q1-2022 | BA5: =CONCATENATE("Q2","-",RIGHT(AZ5,4)) -> Q2-2022 | BB5: =CONCATENATE("Q3","-",RIGHT(BA5,4)) -> Q3-2022 | BC5: =CONCATENATE("Q4","-",RIGHT(BB5,4)) -> Q4-2022 | BD5: =CONCATENATE("FY",RIGHT(AY5,4)+1) -> FY2022 | BE5: =CONCATENATE("Q1","-",RIGHT(BD5,4)+1) -> Q1-2023 | BF5: =CONCATENATE("Q2","-",RIGHT(BE5,4)) -> Q2-2023 | BG5: =CONCATENATE("Q3","-",RIGHT(BF5,4)) -> Q3-2023 | BH5: =CONCATENATE("Q4","-",RIGHT(BG5,4)) -> Q4-2023 | BI5: =CONCATENATE("FY",RIGHT(BD5,4)+1) -> FY2023 | BJ5: =CONCATENATE("Q1","-",RIGHT(BI5,4)+1) -> Q1-2024 | BK5: =CONCATENATE("Q2","-",RIGHT(BJ5,4)) -> Q2-2024 | BL5: =CONCATENATE("Q3","-",RIGHT(BK5,4)) -> Q3-2024 | BM5: =CONCATENATE("Q4","-",RIGHT(BL5,4)) -> Q4-2024 | BN5: =CONCATENATE("FY",RIGHT(BI5,4)+1) -> FY2024 | BO5: =CONCATENATE("Q1","-",RIGHT(BN5,4)+1) -> Q1-2025 | BP5: =CONCATENATE("Q2","-",RIGHT(BO5,4)) -> Q2-2025 | BQ5: =CONCATENATE("Q3","-",RIGHT(BP5,4)) -> Q3-2025 | BR5: =CONCATENATE("Q4","-",RIGHT(BQ5,4)) -> Q4-2025 | BS5: =CONCATENATE("FY",RIGHT(BN5,4)+1) -> FY2025 | BT5: =CONCATENATE("FY",RIGHT(BS5,4)+1) -> FY2026 | BU5: =CONCATENATE("FY",RIGHT(BT5,4)+1) -> FY2027 | BV5: =CONCATENATE("FY",RIGHT(BU5,4)+1) -> FY2028
A6: Revenue Build (PR/FS)
A7: LTM Active Customers - BoP, 000s customers | G7: =F9 -> 1299 | H7: =G9 -> 1366 | I7: =H9 -> 1506 | J7: =I9 -> 1775 | K7: =F9 -> 1299 | L7: =K9 -> 2092 | M7: =L9 -> 2409 | N7: =M9 -> 2635 | O7: =N9 -> 2858 | P7: =K9 -> 2092 | Q7: =P9 -> 3217 | R7: =Q9 -> 3597 | S7: =R9 -> 4044 | T7: =S9 -> 4591 | U7: =P9 -> 3217 | V7: =U9 -> 5360 | W7: =V9 -> 6074 | X7: =W9 -> 6672 | Y7: =X9 -> 7362 | Z7: =U9 -> 5360 | AA7: =Z9 -> 8250 | AB7: =AA9 -> 8855 | AC7: =AB9 -> 9547 | AD7: =AC9 -> 10250 | AE7: =Z9 -> 8250 | AF7: =AE9 -> 10990 | AG7: =AF9 -> 11795 | AH7: =AG9 -> 12792 | AI7: =AH9 -> 13860 | AJ7: =AE9 -> 10990 | AK7: =AJ9 -> 15155 | AL7: =AK9 -> 16408 | AM7: =AL9 -> 17799 | AN7: =AM9 -> 19071 | AO7: =AJ9 -> 15155 | AP7: =AO9 -> 20290 | AQ7: =AP9 -> 21108 | AR7: =AQ9 -> 25979 | AS7: =AR9 -> 28783 | AT7: =AO9 -> 20290 | AU7: =AT9 -> 31194 | AV7: =AU9 -> 33193 | AW7: =AV9 -> 31067 | AX7: =AW9 -> 29213 | AY7: =AT9 -> 31194 | AZ7: =AY9 -> 27300 | BA7: =AZ9 -> 25400 | BB7: =BA9 -> 23600 | BC7: =BB9 -> 22600 | BD7: =AY9 -> 27300 | BE7: =BD9 -> 22100 | BF7: =BE9 -> 21700 | BG7: =BF9 -> 21800 | BH7: =BG9 -> 22300 | BI7: =BD9 -> 22100 | BJ7: =BI9 -> 22400 | BK7: =BJ9 -> 22300 | BL7: =BK9 -> 22236 | BM7: =BL9 -> 22746 | BN7: =BI9 -> 22400 | BO7: =BN9 -> 22848 | BP7: =BO9 -> 22969 | BQ7: =BP9 -> 22903.08 | BR7: =BQ9 -> 23428.38 | BS7: =BN9 -> 22848 | BT7: =BS9 -> 23533.44 | BU7: =BT9 -> 24239.443 | BV7: =BU9 -> 24966.626
A8: Net addition of active customers, 000s customers | G8: =G9-G7 -> 67 | H8: =H9-H7 -> 140 | I8: =I9-I7 -> 269 | J8: =J9-J7 -> 317 | K8: =K9-K7 -> 793 | L8: =L9-L7 -> 317 | M8: =M9-M7 -> 226 | N8: =N9-N7 -> 223 | ... BM8: =BM9-BM7 -> 102 | BN8: =SUM(BJ8,BK8,BL8,BM8) -> 448 | BO8: =BO9-BO7 -> 121 | BP8: =BP9-BP7 -> -65.92 | BQ8: =BQ9-BQ7 -> 525.3 | BR8: =BR9-BR7 -> 105.06 | BS8: =SUM(BO8,BP8,BQ8,BR8) -> 685.44 | BT8: =BT9-BT7 -> 706.0032 | BU8: =BU9-BU7 -> 727.1833 | BV8: =BV9-BV7 -> 748.99879
A9: LTM Active Customers - EoP, 000s customers | F9: 1299 | G9: 1366 | H9: 1506 | I9: 1775 | J9: 2092 | K9: 2092 | L9: 2409 | M9: 2635 | N9: 2858 | O9: 3217 | P9: 3217 | Q9: 3597 | R9: 4044 | S9: 4591 | T9: 5360 | U9: 5360 | V9: 6074 | W9: 6672 | X9: 7362 | Y9: 8250 | Z9: 8250 | AA9: 8855 | AB9: 9547 | AC9: 10250 | AD9: 10990 | AE9: 10990 | AF9: 11795 | AG9: 12792 | AH9: 13860 | AI9: 15155 | AJ9: 15155 | AK9: 16408 | AL9: 17799 | AM9: 19071 | AN9: 20290 | AO9: 20290 | AP9: 21108 | AQ9: 25979 | AR9: 28783 | AS9: 31194 | AT9: 31194 | AU9: 33193 | AV9: 31067 | AW9: 29213 | AX9: 27300 | AY9: =AX9 -> 27300 | AZ9: 25400 | BA9: 23600 | BB9: 22600 | BC9: 22100 | BD9: =BC9 -> 22100 | BE9: 21700 | BF9: 21800 | BG9: 22300 | BH9: 22400 | BI9: =BH9 -> 22400 | BJ9: 22300 | BK9: =BF9*(1+BK11) -> 22236 | BL9: =BG9*(1+BL11) -> 22746 | BM9: =BH9*(1+BM11) -> 22848 | BN9: =BN7+BN8 -> 22848 | BO9: =BJ9*(1+BO11) -> 22969 | BP9: =BK9*(1+BP11) -> 22903.08 | BQ9: =BL9*(1+BQ11) -> 23428.38 | BR9: =BM9*(1+BR11) -> 23533.44 | BS9: =BS7+BS8 -> 23533.44 | BT9: =BS9*(1+BT11) -> 24239.443 | BU9: =BT9*(1+BU11) -> 24966.626 | BV9: =BU9*(1+BV11) -> 25715.625
A10: Q/Q LTM active customers - EoP growth, % | G10: =G9/F9-1 -> 0.051578137 | H10: =H9/G9-1 -> 0.10248902 | I10: =I9/H9-1 -> 0.17861886 | J10: =J9/I9-1 -> 0.17859155 | L10: =L9/J9-1 -> 0.15152964 | M10: =M9/L9-1 -> 0.093814861 | N10: =N9/M9-1 -> 0.084629981 | O10: =O9/N9-1 -> 0.12561232 | Q10: =Q9/O9-1 -> 0.11812247 | R10: =R9/Q9-1 -> 0.12427023 | S10: =S9/R9-1 -> 0.13526212 | T10: =T9/S9-1 -> 0.16750163 | V10: =V9/T9-1 -> 0.13320896 | W10: =W9/V9-1 -> 0.09845242 | X10: =X9/W9-1 -> 0.10341727 | Y10: =Y9/X9-1 -> 0.1206194 | AA10: =AA9/Y9-1 -> 0.073333333 | AB10: =AB9/AA9-1 -> 0.078147939 | AC10: =AC9/AB9-1 -> 0.073635697 | AD10: =AD9/AC9-1 -> 0.072195122 | AF10: =AF9/AD9-1 -> 0.073248408 | AG10: =AG9/AF9-1 -> 0.084527342 | AH10: =AH9/AG9-1 -> 0.083489681 | AI10: =AI9/AH9-1 -> 0.093434343 | AK10: =AK9/AI9-1 -> 0.082678984 | AL10: =AL9/AK9-1 -> 0.084775719 | AM10: =AM9/AL9-1 -> 0.071464689 | AN10: =AN9/AM9-1 -> 0.063919039 | AP10: =AP9/AN9-1 -> 0.040315426 | AQ10: =AQ9/AP9-1 -> 0.23076559 | AR10: =AR9/AQ9-1 -> 0.10793333 | AS10: =AS9/AR9-1 -> 0.083764722 | AU10: =AU9/AS9-1 -> 0.064082836 | AV10: =AV9/AU9-1 -> -0.064049649 | AW10: =AW9/AV9-1 -> -0.059677471 | AX10: =AX9/AW9-1 -> -0.065484545 | AZ10: =AZ9/AX9-1 -> -0.06959707 | BA10: =BA9/AZ9-1 -> -0.070866142 | BB10: =BB9/BA9-1 -> -0.042372881 | BC10: =BC9/BB9-1 -> -0.022123894 | BE10: =BE9/BC9-1 -> -0.018099548 | BF10: =BF9/BE9-1 -> 0.0046082949 | BG10: =BG9/BF9-1 -> 0.02293578 | BH10: =BH9/BG9-1 -> 0.0044843049 | BJ10: =BJ9/BH9-1 -> -0.0044642857 | BK10: =BK9/BJ9-1 -> -0.0028699552 | BL10: =BL9/BK9-1 -> 0.02293578 | BM10: =BM9/BL9-1 -> 0.0044843049 | BO10: =BO9/BM9-1 -> 0.0052958683 | BP10: =BP9/BO9-1 -> -0.0028699552 | BQ10: =BQ9/BP9-1 -> 0.02293578 | BR10: =BR9/BQ9-1 -> 0.0044843049
A11: Y/Y LTM active customers - EoP growth, % | K11: =K9/F9-1 -> 0.61046959 | L11: =L9/G9-1 -> 0.76354319 | M11: =M9/H9-1 -> 0.74966799 | N11: =N9/I9-1 -> 0.61014085 | O11: =O9/J9-1 -> 0.53776291 | P11: =P9/K9-1 -> 0.53776291 | Q11: =Q9/L9-1 -> 0.49315068 | R11: =R9/M9-1 -> 0.53472486 | ... BJ11: =BJ9/BE9-1 -> 0.02764977 | BK11: 0.02 | BL11: 0.02 | BM11: 0.02 | BN11: =BN9/BI9-1 -> 0.02 | BO11: 0.03 | BP11: 0.03 | BQ11: 0.03 | BR11: 0.03 | BS11: =BS9/BN9-1 -> 0.03 | BT11: 0.03 | BU11: 0.03 | BV11: 0.03
A13: Order Frequency from LTM customers, # of orders/customer | G13: =G21/G9 -> 0.40629575 | H13: =H21/H9 -> 0.46679947 | I13: =I21/I9 -> 0.49802817 | J13: =J21/J9 -> 0.56022945 | K13: =K21/K9 -> 1.58413 | L13: =L21/L9 -> 0.47239518 | M13: =M21/M9 -> 0.4113852 | N13: =N21/N9 -> 0.45976207 | ... BJ13: =BJ21/BJ9 -> 0.43049327 | BK13: =BF13*(1+BK14) -> 0.47720183 | BL13: =BG13*(1+BL14) -> 0.44838565 | BM13: =BH13*(1+BM14) -> 0.50950893 | BN13: =BN21/BN9 -> 1.8404806 | BO13: =BJ13*(1+BO14) -> 0.43910314 | BP13: =BK13*(1+BP14) -> 0.48674587 | BQ13: =BL13*(1+BQ14) -> 0.45735336 | BR13: =BM13*(1+BR14) -> 0.51969911 | BS13: =BS21/BS9 -> 1.8772902 | BT13: =BS13*(1+BT14) -> 1.9336089 | BU13: =BT13*(1+BU14) -> 1.9916172 | BV13: =BU13*(1+BV14) -> 2.0513657
A14: Y/Y Growth in order frequency, % | L14: =L13/G13-1 -> 0.16268797 | M14: =M13/H13-1 -> -0.11871108 | N14: =N13/I13-1 -> -0.076835207 | O14: =O13/J13-1 -> -0.056184031 | P14: =P13/K13-1 -> 0.027639263 | Q14: =Q13/L13-1 -> 0.057553087 | R14: =R13/M13-1 -> 0.17753717 | S14: =S13/N13-1 -> 0.10054746 | ... BJ14: =BJ13/BE13-1 -> -0.036937728 | BK14: 0.01 | BL14: 0.01 | BM14: 0.01 | BN14: =BN13/BI13-1 -> 0.00064962878 | BO14: 0.02 | BP14: 0.02 | BQ14: 0.02 | BR14: 0.02 | BS14: =BS13/BN13-1 -> 0.02 | BT14: 0.03 | BU14: 0.03 | BV14: 0.03
A15: LTM Orders Per Customer, # of orders/customer | F15: =F21/F9 -> 1.3772132 | K15: =K21/K9 -> 1.58413 | L15: =(L21+J21+I21+H21)/L9 -> 1.6176837 | M15: =(M21+L21+J21+I21)/M9 -> 1.6235294 | N15: =(N21+M21+L21+J21)/N9 -> 1.6473058 | O15: =(O21+N21+M21+L21)/O9 -> 1.6279142 | P15: =P21/P9 -> 1.6279142 | Q15: =(Q21+O21+N21+M21)/Q9 -> 1.6391437 | R15: =(R21+Q21+O21+N21)/R9 -> 1.6743323 | S15: =(S21+R21+Q21+O21)/S9 -> 1.6946199 | T15: =(T21+S21+R21+Q21)/T9 -> 1.7108209 | U15: =U21/U9 -> 1.7108209 | V15: =(V21+T21+S21+R21)/V9 -> 1.7071123 | W15: =(W21+V21+T21+S21)/W9 -> 1.6996403 | X15: =(X21+W21+V21+T21)/X9 -> 1.6889432 | Y15: =(Y21+X21+W21+V21)/Y9 -> 1.7047273 | Z15: =Z21/Z9 -> 1.7047273 | AA15: =(AA21+Y21+X21+W21)/AA9 -> 1.7256917 | AB15: =(AB21+AA21+Y21+X21)/AB9 -> 1.7418037 | AC15: =(AC21+AB21+AA21+Y21)/AC9 -> 1.7493659 | AD15: =(AD21+AC21+AB21+AA21)/AD9 -> 1.766333 | AE15: =AE21/AE9 -> 1.766242 | AF15: =(AF21+AD21+AC21+AB21)/AF9 -> 1.7877914 | AG15: =(AG21+AF21+AD21+AC21)/AG9 -> 1.8184021 | AH15: =(AH21+AG21+AF21+AD21)/AH9 -> 1.8383838 | AI15: =(AI21+AH21+AG21+AF21)/AI9 -> 1.8531178 | AJ15: =AJ21/AJ9 -> 1.8531178 | AK15: =(AK21+AI21+AH21+AG21)/AK9 -> 1.850256 | AL15: =(AL21+AK21+AI21+AH21)/AL9 -> 1.8579134 | AM15: =(AM21+AL21+AK21+AI21)/AM9 -> 1.848461 | AN15: =(AN21+AM21+AL21+AK21)/AN9 -> 1.8551503 | AO15: =AO21/AO9 -> 1.8551503 | AP15: =(AP21+AN21+AM21+AL21)/AP9 -> 1.8644116 | AQ15: =(AQ21+AP21+AN21+AM21)/AQ9 -> 1.8893722 | AR15: =(AR21+AQ21+AP21+AN21)/AR9 -> 1.9358997 | AS15: =(AS21+AR21+AQ21+AP21)/AS9 -> 1.9554722 | AT15: =AT21/AT9 -> 1.9554722 | AU15: =(AU21+AS21+AR21+AQ21)/AU9 -> 1.9829181 | AV15: =(AV21+AU21+AS21+AR21)/AV9 -> 1.9574468 | AW15: =(AW21+AV21+AU21+AS21)/AW9 -> 1.919351 | AX15: =(AX21+AW21+AV21+AU21)/AX9 -> 1.893663 | AY15: =AY21/AY9 -> 1.893663 | AZ15: =(AZ21+AX21+AW21+AV21)/AZ9 -> 1.8661811 | BA15: =(BA21+AZ21+AX21+AW21)/BA9 -> 1.8438983 | BB15: =(BB21+BA21+AZ21+AX21)/BB9 -> 1.8230088 | BC15: =(BC21+BB21+BA21+AZ21)/BC9 -> 1.8144796 | BD15: =BD21/BD9 -> 1.8144796 | BE15: =(BE21+BC21+BB21+BA21)/BE9 -> 1.8156682 | BF15: =(BF21+BE21+BC21+BB21)/BF9 -> 1.8211009 | BG15: =(BG21+BF21+BE21+BC21)/BG9 -> 1.8340807 | BH15: =(BH21+BG21+BF21+BE21)/BH9 -> 1.8392857 | BI15: =BI21/BI9 -> 1.8392857 | BJ15: =(BJ21+BH21+BG21+BF21)/BJ9 -> 1.8430493 | BK15: =(BK21+BJ21+BH21+BG21)/BK9 -> 1.862343 | BL15: =(BL21+BK21+BJ21+BH21)/BL9 -> 1.8337308 | BM15: =(BM21+BL21+BK21+BJ21)/BM9 -> 1.8404806 | BN15: =BN21/BN9 -> 1.8404806 | BO15: =(BO21+BM21+BL21+BK21)/BO9 -> 1.8519335 | BP15: =(BP21+BO21+BM21+BL21)/BP9 -> 1.8807069 | BQ15: =(BQ21+BP21+BO21+BM21)/BQ9 -> 1.860566 | BR15: =(BR21+BQ21+BP21+BO21)/BR9 -> 1.8772902 | BS15: =BS21/BS9 -> 1.8772902 | BT15: =BT21/BT9 -> 1.9336089 | BU15: =BU21/BU9 -> 1.9916172 | BV15: =BV21/BV9 -> 2.0513657
A16: Y/Y Growth in LTM orders per customer, % | K16: =K15/F15-1 -> 0.15024309 | P16: =P15/K15-1 -> 0.027639263 | Q16: =Q15/L15-1 -> 0.013265909 | R16: =R15/M15-1 -> 0.031291661 | S16: =S15/N15-1 -> 0.028722111 | T16: =T15/O15-1 -> 0.050928169 | U16: =U15/P15-1 -> 0.050928169 | V16: =V15/Q15-1 -> 0.041465888 | W16: =W15/R15-1 -> 0.015115245 | ... BS16: =BS15/BN15-1 -> 0.02 | BT16: =BT15/BS15-1 -> 0.03 | BU16: =BU15/BT15-1 -> 0.03 | BV16: =BV15/BU15-1 -> 0.03
A18: Orders from repeat customers, 000s orders | L18: 577 | M18: 560 | N18: 654 | O18: 856 | P18: =SUM(L18,M18,N18,O18) -> 2647 | Q18: 968 | R18: 1109 | S18: 1282 | T18: 1679 | U18: =SUM(Q18,R18,S18,T18) -> 5038 | V18: 1659 | W18: 1687 | X18: 1943 | Y18: 2739 | Z18: =SUM(V18,W18,X18,Y18) -> 8028 | AA18: 2544 | AB18: 2622 | AC18: 2880 | AD18: 3869 | AE18: =SUM(AA18,AB18,AC18,AD18) -> 11915 | AF18: 3800 | AG18: 4300 | AH18: 4600 | AI18: 5800 | AJ18: =SUM(AF18,AG18,AH18,AI18) -> 18500 | AK18: 5400 | AL18: 6200 | AM18: 6100 | AN18: 7700 | AO18: =SUM(AK18,AL18,AM18,AN18) -> 25400 | AP18: 6900 | AQ18: 12700 | AR18: 11300 | AS18: 11900 | AT18: =SUM(AP18,AQ18,AR18,AS18) -> 42800 | AU18: 10900 | AV18: 10500 | AW18: 8400 | AX18: 9200 | AY18: =SUM(AU18,AV18,AW18,AX18) -> 39000 | AZ18: 8100 | BA18: 7800 | BB18: 6800 | BC18: 8500 | BD18: =SUM(AZ18,BA18,BB18,BC18) -> 31200 | BE18: 7600 | BF18: 8300 | BG18: 7900 | BH18: 9000 | BI18: =SUM(BE18,BF18,BG18,BH18) -> 32800 | BJ18: 7700
A19: Repeat customers orders as % of total orders, % | L19: =L18/L21 -> 0.50702988 | M19: =M18/M21 -> 0.51660517 | N19: =N18/N21 -> 0.49771689 | O19: =O18/O21 -> 0.50323339 | P19: =P18/P21 -> 0.50544205 | Q19: =Q18/Q21 -> 0.53867557 | R19: =R18/R21 -> 0.56610516 | S19: =S18/S21 -> 0.55187258 | ... BJ19: =BJ18/BJ21 -> 0.80208333
A20: Orders from new customers, 000s orders | L20: 561 | M20: 524 | N20: 660 | O20: 845 | P20: =SUM(L20,M20,N20,O20) -> 2590 | Q20: 829 | R20: 850 | S20: 1041 | T20: 1412 | U20: =SUM(Q20,R20,S20,T20) -> 4132 | V20: 1337 | W20: 1243 | X20: 1474 | Y20: 1982 | Z20: =SUM(V20,W20,X20,Y20) -> 6036 | AA20: 1669 | AB20: 1656 | AC20: 1839 | AD20: 2333 | AE20: =SUM(AA20,AB20,AC20,AD20) -> 7497 | AF20: =+AF21-AF18 -> 2088 | AG20: =+AG21-AG18 -> 2152 | AH20: =+AH21-AH18 -> 2338 | AI20: =+AI21-AI18 -> 3006 | AJ20: =+AJ21-AJ18 -> 9584 | AK20: =+AK21-AK18 -> 2763 | AL20: =+AL21-AL18 -> 2962 | AM20: =+AM21-AM18 -> 3021 | ... BJ20: =+BJ21-BJ18 -> 1900
A21: Orders Delivered, 000s orders | F21: 1789 | G21: 555 | H21: 703 | I21: 884 | J21: 1172 | K21: 3314 | L21: =L18+L20 -> 1138 | M21: =M18+M20 -> 1084 | N21: =N18+N20 -> 1314 | O21: =P21-SUM(L21,M21,N21) -> 1701 | P21: =P18+P20 -> 5237 | Q21: =Q18+Q20 -> 1797 | R21: =R18+R20 -> 1959 | S21: =S18+S20 -> 2323 | T21: =U21-SUM(Q21,R21,S21) -> 3091 | U21: =U18+U20 -> 9170 | V21: =V18+V20 -> 2996 | W21: =W18+W20 -> 2930 | X21: =X18+X20 -> 3417 | Y21: =Z21-SUM(V21,W21,X21) -> 4721 | Z21: =Z18+Z20 -> 14064 | AA21: =AA18+AA20 -> 4213 | AB21: =AB18+AB20 -> 4278 | AC21: =AC18+AC20 -> 4719 | AD21: =AD18+AD20 -> 6202 | AE21: 19411 | AF21: 5888 | AG21: 6452 | AH21: 6938 | AI21: 8806 | AJ21: 28084 | AK21: 8163 | AL21: 9162 | AM21: 9121 | AN21: 11195 | AO21: 37641 | AP21: 9876 | AQ21: 18892 | AR21: 15758 | AS21: 16473 | AT21: 60999 | AU21: 14696 | AV21: 13885 | AW21: 11016 | AX21: 12100 | AY21: =SUM(AU21,AV21,AW21,AX21) -> 51697 | AZ21: 10400 | BA21: 10000 | BB21: 8700 | BC21: 11000 | BD21: =SUM(AZ21,BA21,BB21,BC21) -> 40100 | BE21: 9700 | BF21: 10300 | BG21: 9900 | BH21: 11300 | BI21: =SUM(BE21,BF21,BG21,BH21) -> 41200 | BJ21: 9600 | BK21: =BK13*BK9 -> 10611.06 | BL21: =BL13*BL9 -> 10198.98 | BM21: =BM13*BM9 -> 11641.26 | BN21: =SUM(BJ21,BK21,BL21,BM21) -> 42051.3 | BO21: =BO13*BO9 -> 10085.76 | BP21: =BP13*BP9 -> 11147.98 | BQ21: =BQ13*BQ9 -> 10715.048 | BR21: =BR13*BR9 -> 12230.308 | BS21: =SUM(BO21,BP21,BQ21,BR21) -> 44179.096 | BT21: =BT13*BT9 -> 46869.603 | BU21: =BU13*BU9 -> 49723.962 | BV21: =BV13*BV9 -> 52752.151
